// 
// Decompiled by Procyon v0.5.30
// 

package android.support.v4.util;

import java.util.Collection;
import java.util.Iterator;
import java.util.Set;
import java.util.Map;

public class ArrayMap<K, V> extends SimpleArrayMap<K, V> implements Map<K, V>
{
    MapCollections<K, V> mCollections;
    
    private MapCollections<K, V> getCollection() {
        // 
        // This method could not be decompiled.
        // 
        // Original Bytecode:
        // 
        //     0: aload_0        
        //     1: getfield        android/support/v4/util/ArrayMap.mCollections:Landroid/support/v4/util/MapCollections;
        //     4: ifnonnull       19
        //     7: aload_0        
        //     8: new             new            !!! ERROR
        //    11: dup            
        //    12: aload_0        
        //    13: invokespecial   invokespecial  !!! ERROR
        //    16: putfield        android/support/v4/util/ArrayMap.mCollections:Landroid/support/v4/util/MapCollections;
        //    19: aload_0        
        //    20: getfield        android/support/v4/util/ArrayMap.mCollections:Landroid/support/v4/util/MapCollections;
        //    23: areturn        
        //    Signature:
        //  ()Landroid/support/v4/util/MapCollections<TK;TV;>;
        // 
        // The error that occurred was:
        // 
        // java.lang.IllegalArgumentException: Argument 'typeArguments' must not have any null elements.
        //     at com.strobel.core.VerifyArgument.noNullElementsAndNotEmpty(VerifyArgument.java:145)
        //     at com.strobel.assembler.metadata.CoreMetadataFactory$UnresolvedType.makeGenericType(CoreMetadataFactory.java:570)
        //     at com.strobel.assembler.metadata.CoreMetadataFactory.makeParameterizedType(CoreMetadataFactory.java:156)
        //     at com.strobel.assembler.metadata.signatures.Reifier.visitClassTypeSignature(Reifier.java:125)
        //     at com.strobel.assembler.metadata.signatures.ClassTypeSignature.accept(ClassTypeSignature.java:46)
        //     at com.strobel.assembler.metadata.MetadataParser.parseClassSignature(MetadataParser.java:394)
        //     at com.strobel.assembler.metadata.ClassFileReader.populateBaseTypes(ClassFileReader.java:665)
        //     at com.strobel.assembler.metadata.ClassFileReader.readClass(ClassFileReader.java:438)
        //     at com.strobel.assembler.metadata.ClassFileReader.readClass(ClassFileReader.java:366)
        //     at com.strobel.assembler.metadata.MetadataSystem.resolveType(MetadataSystem.java:124)
        //     at com.strobel.decompiler.NoRetryMetadataSystem.resolveType(DecompilerDriver.java:463)
        //     at com.strobel.assembler.metadata.MetadataSystem.resolveCore(MetadataSystem.java:76)
        //     at com.strobel.assembler.metadata.MetadataResolver.resolve(MetadataResolver.java:104)
        //     at com.strobel.assembler.metadata.CoreMetadataFactory$UnresolvedType.resolve(CoreMetadataFactory.java:589)
        //     at com.strobel.assembler.metadata.MetadataResolver.resolve(MetadataResolver.java:128)
        //     at com.strobel.assembler.metadata.CoreMetadataFactory$UnresolvedType.resolve(CoreMetadataFactory.java:599)
        //     at com.strobel.assembler.metadata.MethodReference.resolve(MethodReference.java:172)
        //     at com.strobel.decompiler.ast.TypeAnalysis.inferCall(TypeAnalysis.java:2428)
        //     at com.strobel.decompiler.ast.TypeAnalysis.doInferTypeForExpression(TypeAnalysis.java:1029)
        //     at com.strobel.decompiler.ast.TypeAnalysis.inferTypeForExpression(TypeAnalysis.java:803)
        //     at com.strobel.decompiler.ast.TypeAnalysis.runInference(TypeAnalysis.java:672)
        //     at com.strobel.decompiler.ast.TypeAnalysis.runInference(TypeAnalysis.java:655)
        //     at com.strobel.decompiler.ast.TypeAnalysis.runInference(TypeAnalysis.java:365)
        //     at com.strobel.decompiler.ast.TypeAnalysis.run(TypeAnalysis.java:96)
        //     at com.strobel.decompiler.ast.AstOptimizer.optimize(AstOptimizer.java:109)
        //     at com.strobel.decompiler.ast.AstOptimizer.optimize(AstOptimizer.java:42)
        //     at com.strobel.decompiler.languages.java.ast.AstMethodBodyBuilder.createMethodBody(AstMethodBodyBuilder.java:214)
        //     at com.strobel.decompiler.languages.java.ast.AstMethodBodyBuilder.createMethodBody(AstMethodBodyBuilder.java:99)
        //     at com.strobel.decompiler.languages.java.ast.AstBuilder.createMethodBody(AstBuilder.java:757)
        //     at com.strobel.decompiler.languages.java.ast.AstBuilder.createMethod(AstBuilder.java:655)
        //     at com.strobel.decompiler.languages.java.ast.AstBuilder.addTypeMembers(AstBuilder.java:532)
        //     at com.strobel.decompiler.languages.java.ast.AstBuilder.createTypeCore(AstBuilder.java:499)
        //     at com.strobel.decompiler.languages.java.ast.AstBuilder.createTypeNoCache(AstBuilder.java:141)
        //     at com.strobel.decompiler.languages.java.ast.AstBuilder.createType(AstBuilder.java:130)
        //     at com.strobel.decompiler.languages.java.ast.AstBuilder.addType(AstBuilder.java:105)
        //     at com.strobel.decompiler.languages.java.JavaLanguage.buildAst(JavaLanguage.java:71)
        //     at com.strobel.decompiler.languages.java.JavaLanguage.decompileType(JavaLanguage.java:59)
        //     at com.strobel.decompiler.DecompilerDriver.decompileType(DecompilerDriver.java:317)
        //     at com.strobel.decompiler.DecompilerDriver.decompileJar(DecompilerDriver.java:238)
        //     at com.strobel.decompiler.DecompilerDriver.main(DecompilerDriver.java:138)
        // 
        throw new IllegalStateException("An error occurred while decompiling this method.");
    }
    
    @Override
    public Set<Entry<K, V>> entrySet() {
        return this.getCollection().getEntrySet();
    }
    
    @Override
    public Set<K> keySet() {
        return this.getCollection().getKeySet();
    }
    
    @Override
    public void putAll(final Map<? extends K, ? extends V> map) {
        this.ensureCapacity(this.mSize + map.size());
        for (final Entry<? extends K, ? extends V> entry : map.entrySet()) {
            this.put((K)entry.getKey(), (V)entry.getValue());
        }
    }
    
    public boolean retainAll(final Collection<?> collection) {
        return MapCollections.retainAllHelper((Map<Object, Object>)this, collection);
    }
    
    @Override
    public Collection<V> values() {
        return this.getCollection().getValues();
    }
}
