// 
// Decompiled by Procyon v0.5.30
// 

package bolts;

final class Task$10 implements Runnable
{
    final /* synthetic */ Continuation val$continuation;
    final /* synthetic */ Task val$task;
    final /* synthetic */ Task$TaskCompletionSource val$tcs;
    
    Task$10(final Continuation val$continuation, final Task val$task, final Task$TaskCompletionSource val$tcs) {
        this.val$continuation = val$continuation;
        this.val$task = val$task;
        this.val$tcs = val$tcs;
    }
    
    @Override
    public void run() {
        // 
        // This method could not be decompiled.
        // 
        // Original Bytecode:
        // 
        //     0: aload_0        
        //     1: getfield        bolts/Task$10.val$continuation:Lbolts/Continuation;
        //     4: aload_0        
        //     5: getfield        bolts/Task$10.val$task:Lbolts/Task;
        //     8: invokeinterface bolts/Continuation.then:(Lbolts/Task;)Ljava/lang/Object;
        //    13: checkcast       Lbolts/Task;
        //    16: astore_1       
        //    17: aload_1        
        //    18: ifnonnull       30
        //    21: aload_0        
        //    22: getfield        bolts/Task$10.val$tcs:Lbolts/Task$TaskCompletionSource;
        //    25: aconst_null    
        //    26: invokevirtual   bolts/Task$TaskCompletionSource.setResult:(Ljava/lang/Object;)V
        //    29: return         
        //    30: aload_1        
        //    31: new             new            !!! ERROR
        //    34: dup            
        //    35: aload_0        
        //    36: invokespecial   invokespecial  !!! ERROR
        //    39: invokevirtual   bolts/Task.continueWith:(Lbolts/Continuation;)Lbolts/Task;
        //    42: pop            
        //    43: return         
        //    44: astore_1       
        //    45: aload_0        
        //    46: getfield        bolts/Task$10.val$tcs:Lbolts/Task$TaskCompletionSource;
        //    49: aload_1        
        //    50: invokevirtual   bolts/Task$TaskCompletionSource.setError:(Ljava/lang/Exception;)V
        //    53: return         
        //    Exceptions:
        //  Try           Handler
        //  Start  End    Start  End    Type                 
        //  -----  -----  -----  -----  ---------------------
        //  0      17     44     54     Ljava/lang/Exception;
        //  21     29     44     54     Ljava/lang/Exception;
        //  30     43     44     54     Ljava/lang/Exception;
        // 
        // The error that occurred was:
        // 
        // java.lang.IllegalArgumentException: Argument 'typeArguments' must not have any null elements.
        //     at com.strobel.core.VerifyArgument.noNullElementsAndNotEmpty(VerifyArgument.java:145)
        //     at com.strobel.assembler.metadata.CoreMetadataFactory$UnresolvedType.makeGenericType(CoreMetadataFactory.java:570)
        //     at com.strobel.assembler.metadata.CoreMetadataFactory.makeParameterizedType(CoreMetadataFactory.java:156)
        //     at com.strobel.assembler.metadata.signatures.Reifier.visitClassTypeSignature(Reifier.java:125)
        //     at com.strobel.assembler.metadata.signatures.ClassTypeSignature.accept(ClassTypeSignature.java:46)
        //     at com.strobel.assembler.metadata.MetadataParser.parseClassSignature(MetadataParser.java:404)
        //     at com.strobel.assembler.metadata.ClassFileReader.populateBaseTypes(ClassFileReader.java:665)
        //     at com.strobel.assembler.metadata.ClassFileReader.readClass(ClassFileReader.java:438)
        //     at com.strobel.assembler.metadata.ClassFileReader.readClass(ClassFileReader.java:366)
        //     at com.strobel.assembler.metadata.MetadataSystem.resolveType(MetadataSystem.java:124)
        //     at com.strobel.decompiler.NoRetryMetadataSystem.resolveType(DecompilerDriver.java:463)
        //     at com.strobel.assembler.metadata.MetadataSystem.resolveCore(MetadataSystem.java:76)
        //     at com.strobel.assembler.metadata.MetadataResolver.resolve(MetadataResolver.java:104)
        //     at com.strobel.assembler.metadata.CoreMetadataFactory$UnresolvedType.resolve(CoreMetadataFactory.java:589)
        //     at com.strobel.assembler.metadata.MetadataResolver.resolve(MetadataResolver.java:128)
        //     at com.strobel.assembler.metadata.CoreMetadataFactory$UnresolvedType.resolve(CoreMetadataFactory.java:599)
        //     at com.strobel.assembler.metadata.MethodReference.resolve(MethodReference.java:172)
        //     at com.strobel.decompiler.ast.TypeAnalysis.inferCall(TypeAnalysis.java:2428)
        //     at com.strobel.decompiler.ast.TypeAnalysis.doInferTypeForExpression(TypeAnalysis.java:1029)
        //     at com.strobel.decompiler.ast.TypeAnalysis.inferTypeForExpression(TypeAnalysis.java:803)
        //     at com.strobel.decompiler.ast.TypeAnalysis.runInference(TypeAnalysis.java:672)
        //     at com.strobel.decompiler.ast.TypeAnalysis.runInference(TypeAnalysis.java:655)
        //     at com.strobel.decompiler.ast.TypeAnalysis.runInference(TypeAnalysis.java:365)
        //     at com.strobel.decompiler.ast.TypeAnalysis.run(TypeAnalysis.java:96)
        //     at com.strobel.decompiler.ast.AstOptimizer.optimize(AstOptimizer.java:109)
        //     at com.strobel.decompiler.ast.AstOptimizer.optimize(AstOptimizer.java:42)
        //     at com.strobel.decompiler.languages.java.ast.AstMethodBodyBuilder.createMethodBody(AstMethodBodyBuilder.java:214)
        //     at com.strobel.decompiler.languages.java.ast.AstMethodBodyBuilder.createMethodBody(AstMethodBodyBuilder.java:99)
        //     at com.strobel.decompiler.languages.java.ast.AstBuilder.createMethodBody(AstBuilder.java:757)
        //     at com.strobel.decompiler.languages.java.ast.AstBuilder.createMethod(AstBuilder.java:655)
        //     at com.strobel.decompiler.languages.java.ast.AstBuilder.addTypeMembers(AstBuilder.java:532)
        //     at com.strobel.decompiler.languages.java.ast.AstBuilder.createTypeCore(AstBuilder.java:499)
        //     at com.strobel.decompiler.languages.java.ast.AstBuilder.createTypeNoCache(AstBuilder.java:141)
        //     at com.strobel.decompiler.languages.java.ast.AstBuilder.createType(AstBuilder.java:130)
        //     at com.strobel.decompiler.languages.java.ast.AstBuilder.addType(AstBuilder.java:105)
        //     at com.strobel.decompiler.languages.java.JavaLanguage.buildAst(JavaLanguage.java:71)
        //     at com.strobel.decompiler.languages.java.JavaLanguage.decompileType(JavaLanguage.java:59)
        //     at com.strobel.decompiler.DecompilerDriver.decompileType(DecompilerDriver.java:317)
        //     at com.strobel.decompiler.DecompilerDriver.decompileJar(DecompilerDriver.java:238)
        //     at com.strobel.decompiler.DecompilerDriver.main(DecompilerDriver.java:138)
        // 
        throw new IllegalStateException("An error occurred while decompiling this method.");
    }
}
