// 
// Decompiled by Procyon v0.5.30
// 

package com.netflix.falkor;

import com.netflix.model.leafs.Video$Bookmark;
import com.netflix.mediaclient.servicemgr.Asset;
import com.netflix.model.leafs.social.IrisNotificationSummary;
import com.netflix.mediaclient.servicemgr.BillboardInteractionType;
import com.netflix.mediaclient.servicemgr.interface_.Video;
import com.netflix.mediaclient.service.NetflixService;
import java.util.LinkedHashSet;
import java.io.IOException;
import java.io.Flushable;
import com.netflix.mediaclient.service.falkor.Falkor$SimilarRequestType;
import com.netflix.mediaclient.servicemgr.interface_.ExpiringContentAction;
import com.netflix.mediaclient.util.StringUtils;
import com.netflix.model.leafs.Video$InQueue;
import com.netflix.model.branches.FalkorVideo;
import android.content.Intent;
import android.support.v4.content.LocalBroadcastManager;
import com.netflix.mediaclient.service.webclient.volley.FalkorParseUtils;
import com.netflix.mediaclient.servicemgr.interface_.JsonPopulator;
import com.netflix.mediaclient.util.JsonUtils;
import com.google.gson.JsonElement;
import com.netflix.mediaclient.android.app.BackgroundTask;
import com.netflix.mediaclient.servicemgr.interface_.genre.GenreList;
import com.netflix.mediaclient.util.DataUtil$StringPair;
import android.text.TextUtils;
import com.netflix.mediaclient.servicemgr.interface_.LoMo;
import java.util.Map;
import com.netflix.mediaclient.service.falkor.Falkor;
import com.netflix.mediaclient.service.webclient.ApiEndpointRegistry$ResponsePathFormat;
import com.netflix.mediaclient.util.FileUtils;
import com.netflix.mediaclient.Log;
import java.util.Iterator;
import java.util.Comparator;
import java.util.Collections;
import com.netflix.mediaclient.util.AlphanumComparator;
import java.util.ArrayList;
import com.netflix.mediaclient.service.browse.PostToHandlerCallbackWrapper;
import com.netflix.mediaclient.util.l10n.LocalizationUtils;
import com.google.gson.JsonObject;
import com.netflix.model.branches.FalkorExpiringContent;
import com.netflix.mediaclient.servicemgr.interface_.VideoType;
import com.netflix.model.branches.FalkorObject;
import android.util.Pair;
import com.netflix.mediaclient.servicemgr.interface_.LoMoType;
import java.util.Collection;
import android.content.Context;
import com.netflix.mediaclient.service.webclient.volley.FalkorVolleyWebClientRequest;
import com.netflix.mediaclient.service.browse.BrowseAgentCallback;
import android.os.Looper;
import com.netflix.mediaclient.service.webclient.volley.FalkorVolleyWebClient;
import android.os.Handler;
import com.google.gson.JsonParser;
import java.util.List;
import android.annotation.SuppressLint;

@SuppressLint({ "DefaultLocale" })
public class CachedModelProxy<T extends BranchNode> implements ModelProxy<T>
{
    public static final String ACTION_NOTIFY_OF_RATINGS_CHANGE = "com.netflix.falkor.ACTION_NOTIFY_OF_RATINGS_CHANGE";
    private static final PQL BB_CURR_EPISODE_PQL;
    private static final PQL BB_VIDEO_LEAF_PQL;
    private static final PQL CW_CURR_EPISODE_PQL;
    private static final PQL CW_VIDEO_LEAF_PQL;
    private static final boolean ENABLE_LOG_TIMING = false;
    public static final String EXTRA_USER_RATING = "extra_user_rating";
    public static final String EXTRA_VIDEO_ID = "extra_video_id";
    public static final int FETCH_EPISODES_REQUEST_BATCH_SIZE = 40;
    private static boolean FORCE_CMP_TO_LOCAL_CACHE = false;
    private static final String JSON_VALUE = "value";
    private static final int MAX_KIDS_CHARACTER_GALLERY_VIDEOS = 100;
    public static final int MAX_SEARCH_RESULTS_PER_SECTION_INDEX = 19;
    private static final int MAX_VIDEO_DETAILS_SIMILARS_COUNT = 12;
    private static final String MS_SUFFIX = "ms";
    private static final String NEWLINE = "\n";
    private static final boolean ORIGINALS_BILLBOARDS_ENABLED = true;
    private static final int PREFETCH_BILLBOARD_VIDEO_INDEX = 9;
    private static final String REQUEST_PARAM_KEY = "param";
    private static final String REQUEST_PATH_SUFFIX_KEY = "pathSuffix";
    private static final List<PQL> SEARCH_LEAF_TYPES;
    private static final List<PQL> SEARCH_RESULT_TYPES;
    private static final String TAG = "CachedModelProxy";
    private static final String TAG_TIMING = "CachedModelProxy_Timing";
    private final JsonParser jsonParser;
    private int lastPrefetchFromVideo;
    private int lastPrefetchToVideo;
    private final Handler mainHandler;
    private final T root;
    private final ServiceProvider serviceProvider;
    private final FalkorVolleyWebClient webClient;
    
    static {
        CachedModelProxy.FORCE_CMP_TO_LOCAL_CACHE = false;
        SEARCH_RESULT_TYPES = PQL.array("videos", "people", "suggestions");
        SEARCH_LEAF_TYPES = PQL.array("summary", "searchTitle");
        CW_VIDEO_LEAF_PQL = PQL.create(PQL.array("summary", "detail", "rating", "inQueue", "bookmark"));
        CW_CURR_EPISODE_PQL = PQL.create("episodes", "current", PQL.array("detail", "bookmark"));
        BB_VIDEO_LEAF_PQL = CachedModelProxy.CW_VIDEO_LEAF_PQL;
        BB_CURR_EPISODE_PQL = CachedModelProxy.CW_CURR_EPISODE_PQL;
    }
    
    public CachedModelProxy(final ServiceProvider serviceProvider, final T root, final FalkorVolleyWebClient webClient) {
        this.jsonParser = new JsonParser();
        this.serviceProvider = serviceProvider;
        this.root = root;
        this.webClient = webClient;
        this.mainHandler = new Handler(Looper.getMainLooper());
    }
    
    private static void buildBillboardPql(final List<PQL> list, final int n, final int n2) {
        list.add(CachedModelProxy.BB_VIDEO_LEAF_PQL.prepend(PQL.create("lolomo", "billboard", "videoEvidence", PQL.range(n, n2))));
        list.add(CachedModelProxy.BB_CURR_EPISODE_PQL.prepend(PQL.create("lolomo", "billboard", "videoEvidence", PQL.range(n, n2))));
        if (!LocalizationUtils.isCurrentLocaleRTL()) {
            list.add(PQL.create("lolomo", "billboard", "billboardData", PQL.range(n, n2), "billboardSummary"));
        }
    }
    
    private static void buildCwPql(final List<PQL> list, final int n, final int n2) {
        list.add(CachedModelProxy.CW_VIDEO_LEAF_PQL.prepend(PQL.create("lolomo", "continueWatching", PQL.range(n, n2))));
        list.add(CachedModelProxy.CW_CURR_EPISODE_PQL.prepend(PQL.create("lolomo", "continueWatching", PQL.range(n, n2))));
    }
    
    public static PQL buildKidsCharacterVideoGalleryPql(final String s) {
        return PQL.create("characters", s, "gallery", PQL.range(100), "summary");
    }
    
    private static PQL buildScenePql(final String s, final String s2, final String s3) {
        return PQL.create(s, s2, "scenes", s3, "summary");
    }
    
    public static PQL buildVideoSimsPql(final boolean b, final String s) {
        String s2;
        if (b) {
            s2 = "movies";
        }
        else {
            s2 = "shows";
        }
        return PQL.create(s2, s, "similars", PQL.range(11), "summary");
    }
    
    private static PQL buildVideoSimsSummaryPql(final boolean b, final String s) {
        String s2;
        if (b) {
            s2 = "movies";
        }
        else {
            s2 = "shows";
        }
        return PQL.create(s2, s, "similars", "summary");
    }
    
    private BrowseAgentCallback createHandlerWrapper(final BrowseAgentCallback browseAgentCallback) {
        return new PostToHandlerCallbackWrapper(this.mainHandler, browseAgentCallback);
    }
    
    private void doDumpCacheToDiskRecursive(final StringBuilder sb, final BranchNode branchNode, final int n, final boolean b) {
        final StringBuilder sb2 = new StringBuilder();
        for (int i = 0; i < n; ++i) {
            String s;
            if (i == n - 1) {
                s = " |-";
            }
            else {
                s = " | ";
            }
            sb2.append(s);
        }
        final String string = sb2.toString();
        final ArrayList<Object> list = new ArrayList<Object>(branchNode.getKeys());
        if (b) {
            Collections.sort(list, (Comparator<? super Object>)new AlphanumComparator());
        }
        for (final String s2 : list) {
            final Object value = branchNode.get(s2);
            if (value instanceof Ref) {
                sb.append(string).append(s2).append(" -> ").append(((Ref)value).getRefPath()).append("\n");
            }
            else if (value instanceof Sentinel) {
                sb.append(string).append(s2).append(" -> [sentinel]").append("\n");
            }
            else {
                sb.append(string).append(s2).append("\n");
            }
            if (value instanceof BranchNode) {
                this.doDumpCacheToDiskRecursive(sb, (BranchNode)value, n + 1, true);
            }
        }
    }
    
    private void dumpCacheToDisk(final String s) {
        final StringBuilder sb = new StringBuilder();
        sb.append("==START OF CACHE==").append("\n");
        if (Log.isLoggable()) {
            this.doDumpCacheToDiskRecursive(sb, this.root, 0, false);
        }
        sb.append("==END OF CACHE==").append("\n");
        FileUtils.writeStringToFile("CachedModelProxy", sb.toString(), s);
    }
    
    private void executeRequest(final FalkorVolleyWebClientRequest<?> falkorVolleyWebClientRequest) {
        this.webClient.sendRequest(falkorVolleyWebClientRequest, ApiEndpointRegistry$ResponsePathFormat.GRAPH);
    }
    
    private void get(final PQL pql, Object o, final int n, final CachedModelProxy$GetResult cachedModelProxy$GetResult) {
        while (true) {
            int i = 0;
            final PQL pql2;
            Label_0125: {
                Label_0110: {
                    synchronized (this) {
                        if (Falkor.ENABLE_VERBOSE_LOGGING) {
                            Log.v("CachedModelProxy", "get from path: " + pql + ", offset: " + n);
                        }
                        i = pql.getKeySegments().size();
                        if (n < i && o == null) {
                            cachedModelProxy$GetResult.missingPqls.add(pql);
                        }
                        else {
                            if (n != i) {
                                break Label_0125;
                            }
                            if (o == null) {
                                break Label_0110;
                            }
                            cachedModelProxy$GetResult.foundPqls.add(pql);
                        }
                        return;
                    }
                }
                cachedModelProxy$GetResult.missingPqls.add(pql2);
                return;
            }
            if (n > i) {
                throw new IllegalStateException("Offset is invalid");
            }
            if (o instanceof Ref) {
                o = o;
                final Object hardValue = ((Ref)o).getHardValue();
                if (hardValue != null) {
                    this.get(((Ref)o).getRefPath().append(pql2.slice(n)), hardValue, ((Ref)o).getRefPath().getKeySegments().size(), cachedModelProxy$GetResult);
                    return;
                }
                if (((Ref)o).getRefPath() != null) {
                    this.get(((Ref)o).getRefPath().append(pql2.slice(n)), this.root, 0, cachedModelProxy$GetResult);
                    return;
                }
                if (Falkor.ENABLE_VERBOSE_LOGGING) {
                    Log.v("CachedModelProxy", "Ref path is null: " + ((Ref)o).getPath());
                }
            }
            else {
                if (o instanceof Exception || o instanceof Undefined) {
                    cachedModelProxy$GetResult.ignoredPqls.add(pql2);
                    return;
                }
                final BranchNode branchNode = (BranchNode)o;
                final Map<K, Integer> value = pql2.getKeySegments().get(n);
                if (value instanceof List) {
                    for (final Map<K, Integer> next : (List<Object>)value) {
                        if (next instanceof Map) {
                            final Map<K, Integer> map = next;
                            final Integer n2 = map.get("from");
                            final Integer n3 = map.get("to");
                            Integer value2;
                            if ((value2 = n2) == null) {
                                value2 = 0;
                            }
                            if (n3 == null) {
                                throw new IllegalStateException("No 'to' param");
                            }
                            for (int i = value2; i <= n3; ++i) {
                                this.get(pql2.replaceKeySegment(n, String.valueOf(i)), o, n, cachedModelProxy$GetResult);
                            }
                        }
                        else {
                            this.get(pql2, branchNode.get(next.toString()), n + 1, cachedModelProxy$GetResult);
                        }
                    }
                    return;
                }
                if (!(value instanceof Map)) {
                    this.get(pql2, branchNode.get(value.toString()), n + 1, cachedModelProxy$GetResult);
                    return;
                }
                final Map<K, Integer> map2 = value;
                final Integer n4 = map2.get("from");
                final Integer n5 = map2.get("to");
                Integer value3;
                if ((value3 = n4) == null) {
                    value3 = 0;
                }
                if (n5 == null) {
                    throw new IllegalStateException("No 'to' param");
                }
                for (int i = value3; i <= n5; ++i) {
                    this.get(pql2.replaceKeySegment(n, String.valueOf(i)), o, n, cachedModelProxy$GetResult);
                }
            }
        }
    }
    
    private String getCurrLolomoId() {
        while (true) {
            synchronized (this) {
                final Ref ref = (Ref)this.getValue(PQL.create("lolomo"));
                String s;
                if (ref == null) {
                    s = null;
                }
                else {
                    final PQL refPath = ref.getRefPath();
                    if (refPath == null) {
                        return null;
                    }
                    if (refPath.getNumKeySegments() < 2) {
                        return null;
                    }
                    s = (String)refPath.getKeySegments().get(1);
                }
                return s;
            }
            return null;
        }
    }
    
    private Pair<LoMo, String> getCurrLomoByType(final LoMoType loMoType) {
        while (true) {
            synchronized (this) {
                final Ref ref = (Ref)this.getValue(PQL.create("lolomo"));
                Pair pair;
                if (ref == null) {
                    pair = null;
                }
                else {
                    final BranchMap branchMap = (BranchMap)this.getValue(ref.getRefPath());
                    if (branchMap == null) {
                        pair = null;
                    }
                    else {
                        LoMo loMo = null;
                        Block_8: {
                            for (final String s : branchMap.keySet()) {
                                if (TextUtils.isDigitsOnly((CharSequence)s)) {
                                    loMo = (LoMo)this.getValue(ref.getRefPath().append(PQL.create(s, "summary")));
                                    if (loMo != null && loMo.getType() == loMoType) {
                                        break Block_8;
                                    }
                                    continue;
                                }
                            }
                            return null;
                        }
                        final String s;
                        pair = new Pair((Object)loMo, (Object)s);
                    }
                }
                return (Pair<LoMo, String>)pair;
            }
            Pair pair = null;
            return (Pair<LoMo, String>)pair;
        }
    }
    
    private DataUtil$StringPair getCurrLomoInfo(final LoMoType loMoType) {
        final Pair<LoMo, String> currLomoByType = this.getCurrLomoByType(loMoType);
        String id;
        if (currLomoByType == null) {
            id = null;
        }
        else {
            id = ((LoMo)currLomoByType.first).getId();
        }
        String value;
        if (currLomoByType == null) {
            value = String.valueOf(-1);
        }
        else {
            value = (String)currLomoByType.second;
        }
        if (Log.isLoggable()) {
            Log.v("CachedModelProxy", "Got curr lomo ID: " + id + ", list index: " + value + ", lomo type: " + loMoType);
        }
        return new DataUtil$StringPair(id, value);
    }
    
    private FalkorExpiringContent getExpiringContent(final PQL pql) {
        synchronized (this) {
            final Iterator<PQL> iterator = pql.explode().iterator();
            while (iterator.hasNext()) {
                final Object value = this.getValue(iterator.next());
                if (value instanceof FalkorExpiringContent) {
                    return (FalkorExpiringContent)value;
                }
            }
            if (Log.isLoggable()) {
                Log.d("CachedModelProxy", "Couldn't find video in cache: " + pql);
            }
            return null;
        }
    }
    
    private List<GenreList> getGenreList() {
        return (List<GenreList>)this.getValue(PQL.create("genreList"));
    }
    
    private <LT extends LoMo> List<LT> getLists(final Collection<PQL> collection) {
        while (true) {
            // monitorenter(this)
            int n = 0;
            while (true) {
                Label_0238: {
                    int listPos = 0;
                    Label_0234: {
                        Label_0231: {
                            try {
                                final ArrayList<LT> list = new ArrayList<LT>();
                                final Iterator<PQL> iterator = collection.iterator();
                                while (iterator.hasNext()) {
                                    final Iterator<Object> iterator2 = iterator.next().explode().iterator();
                                    listPos = n;
                                    n = listPos;
                                    if (iterator2.hasNext()) {
                                        final PQL pql = iterator2.next();
                                        final Object value = this.getValue(pql);
                                        if (!(value instanceof LoMo)) {
                                            break Label_0231;
                                        }
                                        final LoMo loMo = (LT)value;
                                        loMo.setListPos(listPos);
                                        list.add((LT)loMo);
                                        if (Falkor.ENABLE_VERBOSE_LOGGING) {
                                            Log.v("CachedModelProxy", "got lomo - pql: " + pql + ", lomo: " + loMo.getTitle() + ", order: " + loMo.getListPos());
                                        }
                                        break Label_0234;
                                    }
                                }
                                if (Falkor.ENABLE_VERBOSE_LOGGING) {
                                    Log.v("CachedModelProxy", "Lomos size: " + list.size());
                                }
                                return list;
                            }
                            finally {
                            }
                            // monitorexit(this)
                        }
                        break Label_0238;
                    }
                    ++listPos;
                }
                continue;
            }
        }
    }
    
    private FalkorObject getVideo(final PQL pql) {
        synchronized (this) {
            for (final PQL pql2 : pql.explode()) {
                final Object value = this.getValue(pql2);
                if (value instanceof FalkorObject) {
                    FalkorObject falkorObject2;
                    final FalkorObject falkorObject = falkorObject2 = (FalkorObject)value;
                    if (Falkor.ENABLE_VERBOSE_LOGGING) {
                        Log.v("CachedModelProxy", "got video - pql: " + pql2 + ", video: " + falkorObject);
                        falkorObject2 = falkorObject;
                    }
                    return falkorObject2;
                }
            }
            if (Log.isLoggable()) {
                Log.d("CachedModelProxy", "Couldn't find video in cache: " + pql);
            }
            return null;
        }
    }
    
    private void invalidate(final PQL pql) {
        while (true) {
            final Object value;
            Label_0146: {
                synchronized (this) {
                    value = this.getValue(pql.slice(0, pql.getNumKeySegments() - 1));
                    if (value == null) {
                        if (Log.isLoggable()) {
                            Log.d("CachedModelProxy", "Can't invalidate node because it is null: " + pql);
                        }
                    }
                    else {
                        if (!(value instanceof BranchNode)) {
                            break Label_0146;
                        }
                        final String value2 = String.valueOf(pql.getKeySegments().get(pql.getNumKeySegments() - 1));
                        if (Log.isLoggable()) {
                            Log.d("CachedModelProxy", "Invalidating at BranchNode: " + ((BranchNode)value).getClass() + ", node key: " + value2);
                        }
                        ((BranchNode)value).remove(value2);
                    }
                    return;
                }
            }
            final Throwable t;
            if (value instanceof Ref) {
                if (Log.isLoggable()) {
                    Log.d("CachedModelProxy", "Invalidating ref path for pql: " + t);
                }
                ((Ref)value).setRefPath(null);
                return;
            }
            if (Log.isLoggable()) {
                Log.w("CachedModelProxy", "Don't know how to invalidate node: " + ((Ref)value).getClass() + ", pql: " + t);
            }
        }
    }
    
    private void launchTask(final Runnable runnable) {
        if (Log.isLoggable()) {
            Log.v("CachedModelProxy", "Launching task: " + runnable.getClass().getSimpleName());
        }
        new BackgroundTask().execute(runnable);
    }
    
    private void merge(final JsonObject jsonObject, final BranchNode branchNode) {
    Label_0142_Outer:
        while (true) {
            while (true) {
            Label_0527:
                while (true) {
                    Map.Entry<String, JsonElement> entry = null;
                    String s = null;
                    Object orCreate = null;
                    Label_0227: {
                        synchronized (this) {
                            final Iterator<Map.Entry<String, JsonElement>> iterator = jsonObject.entrySet().iterator();
                            while (iterator.hasNext()) {
                                entry = (Map.Entry<String, JsonElement>)iterator.next();
                                s = entry.getKey();
                                if (!(branchNode.getOrCreate(s) instanceof Sentinel) || JsonUtils.isNull(entry.getValue())) {
                                    break Label_0527;
                                }
                                if (Log.isLoggable()) {
                                    Log.d("CachedModelProxy", "Found sentinel at key: " + s + ", will replace with json data: " + entry.getValue());
                                }
                                branchNode.remove(s);
                                orCreate = branchNode.getOrCreate(s);
                                if (Falkor.ENABLE_VERBOSE_LOGGING) {
                                    Log.v("CachedModelProxy", "Curr node: " + branchNode.getClass().getSimpleName() + ", merging: " + s);
                                }
                                if (!(orCreate instanceof BranchNode)) {
                                    break Label_0227;
                                }
                                this.merge(entry.getValue().getAsJsonObject(), (BranchNode)orCreate);
                            }
                            break;
                        }
                    }
                    if (orCreate instanceof Ref) {
                        final Ref ref = (Ref)orCreate;
                        final JsonElement jsonElement = entry.getValue();
                        if (jsonElement.isJsonArray()) {
                            ref.setRefPath(PQL.fromJsonArray(jsonElement.getAsJsonArray()));
                            continue Label_0142_Outer;
                        }
                        if (!jsonElement.isJsonObject()) {
                            continue Label_0142_Outer;
                        }
                        if (jsonElement.getAsJsonObject().has("_sentinel")) {
                            if (Falkor.ENABLE_VERBOSE_LOGGING) {
                                Log.v("CachedModelProxy", "key points to sentinel: " + Undefined.getInstance());
                            }
                            branchNode.set(s, Undefined.getInstance());
                            continue Label_0142_Outer;
                        }
                        if ("current".equals(s)) {
                            if (Falkor.ENABLE_VERBOSE_LOGGING) {
                                Log.v("CachedModelProxy", "json ref points to an ignored 'current' object: " + entry);
                                continue Label_0142_Outer;
                            }
                            continue Label_0142_Outer;
                        }
                        else {
                            if (Log.isLoggable()) {
                                Log.w("CachedModelProxy", "Don't know how to handle json: " + entry);
                                continue Label_0142_Outer;
                            }
                            continue Label_0142_Outer;
                        }
                    }
                    else {
                        if (orCreate == null) {
                            continue Label_0142_Outer;
                        }
                        if (orCreate instanceof JsonPopulator) {
                            ((JsonPopulator)orCreate).populate(entry.getValue());
                            continue Label_0142_Outer;
                        }
                        if (Log.isLoggable()) {
                            Log.w("CachedModelProxy", "Creating duplicate Leaf object. JsonPopulator should be implemented by: " + ((JsonPopulator)orCreate).getClass());
                        }
                        branchNode.set(s, FalkorParseUtils.createObjectFromJson("CachedModelProxy", entry.getValue(), ((JsonPopulator)orCreate).getClass()));
                        continue Label_0142_Outer;
                    }
                    break;
                }
                continue;
            }
        }
    }
    // monitorexit(this)
    
    private void sendDetailPageReloadBroadcast(final Context context) {
        LocalBroadcastManager.getInstance(context).sendBroadcast(new Intent("com.netflix.mediaclient.intent.action.DETAIL_PAGE_REFRESH"));
        Log.v("CachedModelProxy", "Intent DETAIL_PAGE_REFRESH sent");
    }
    
    private void updateInQueueStatus(final VideoType videoType, final String s, final boolean b) {
        synchronized (this) {
            final FalkorVideo falkorVideo = (FalkorVideo)this.getValue(PQL.create(videoType.getValue(), s, "summary"));
            if (falkorVideo != null) {
                if (Log.isLoggable()) {
                    Log.v("CachedModelProxy", "Setting cached inQueue value to: " + b + ", for video: " + s);
                }
                falkorVideo.set("inQueue", new Video$InQueue(b));
            }
        }
    }
    
    public void addToQueue(final String p0, final VideoType p1, final int p2, final boolean p3, final String p4, final BrowseAgentCallback p5) {
        // 
        // This method could not be decompiled.
        // 
        // Original Bytecode:
        // 
        //     0: aload_0        
        //     1: invokespecial   com/netflix/falkor/CachedModelProxy.getCurrLolomoId:()Ljava/lang/String;
        //     4: astore          7
        //     6: aload_0        
        //     7: getstatic       com/netflix/mediaclient/servicemgr/interface_/LoMoType.INSTANT_QUEUE:Lcom/netflix/mediaclient/servicemgr/interface_/LoMoType;
        //    10: invokespecial   com/netflix/falkor/CachedModelProxy.getCurrLomoInfo:(Lcom/netflix/mediaclient/servicemgr/interface_/LoMoType;)Lcom/netflix/mediaclient/util/DataUtil$StringPair;
        //    13: astore          8
        //    15: aload_0        
        //    16: new             new            !!! ERROR
        //    19: dup            
        //    20: aload_0        
        //    21: aload_1        
        //    22: aload_2        
        //    23: aload           7
        //    25: aload           8
        //    27: getfield        com/netflix/mediaclient/util/DataUtil$StringPair.first:Ljava/lang/Object;
        //    30: checkcast       Ljava/lang/String;
        //    33: aload           8
        //    35: getfield        com/netflix/mediaclient/util/DataUtil$StringPair.second:Ljava/lang/Object;
        //    38: checkcast       Ljava/lang/String;
        //    41: iload_3        
        //    42: iload           4
        //    44: aload           5
        //    46: aload           6
        //    48: invokespecial   invokespecial  !!! ERROR
        //    51: invokespecial   com/netflix/falkor/CachedModelProxy.launchTask:(Ljava/lang/Runnable;)V
        //    54: return         
        // 
        // The error that occurred was:
        // 
        // java.lang.IllegalArgumentException: Argument 'typeArguments' must not have any null elements.
        //     at com.strobel.core.VerifyArgument.noNullElementsAndNotEmpty(VerifyArgument.java:145)
        //     at com.strobel.assembler.metadata.CoreMetadataFactory$UnresolvedType.makeGenericType(CoreMetadataFactory.java:570)
        //     at com.strobel.assembler.metadata.CoreMetadataFactory.makeParameterizedType(CoreMetadataFactory.java:156)
        //     at com.strobel.assembler.metadata.signatures.Reifier.visitClassTypeSignature(Reifier.java:125)
        //     at com.strobel.assembler.metadata.signatures.ClassTypeSignature.accept(ClassTypeSignature.java:46)
        //     at com.strobel.assembler.metadata.MetadataParser.parseClassSignature(MetadataParser.java:394)
        //     at com.strobel.assembler.metadata.ClassFileReader.populateBaseTypes(ClassFileReader.java:665)
        //     at com.strobel.assembler.metadata.ClassFileReader.readClass(ClassFileReader.java:438)
        //     at com.strobel.assembler.metadata.ClassFileReader.readClass(ClassFileReader.java:366)
        //     at com.strobel.assembler.metadata.MetadataSystem.resolveType(MetadataSystem.java:124)
        //     at com.strobel.decompiler.NoRetryMetadataSystem.resolveType(DecompilerDriver.java:463)
        //     at com.strobel.assembler.metadata.MetadataSystem.resolveCore(MetadataSystem.java:76)
        //     at com.strobel.assembler.metadata.MetadataResolver.resolve(MetadataResolver.java:104)
        //     at com.strobel.assembler.metadata.CoreMetadataFactory$UnresolvedType.resolve(CoreMetadataFactory.java:589)
        //     at com.strobel.assembler.metadata.MetadataResolver.resolve(MetadataResolver.java:128)
        //     at com.strobel.assembler.metadata.CoreMetadataFactory$UnresolvedType.resolve(CoreMetadataFactory.java:599)
        //     at com.strobel.assembler.metadata.MethodReference.resolve(MethodReference.java:172)
        //     at com.strobel.decompiler.ast.TypeAnalysis.inferCall(TypeAnalysis.java:2428)
        //     at com.strobel.decompiler.ast.TypeAnalysis.doInferTypeForExpression(TypeAnalysis.java:1029)
        //     at com.strobel.decompiler.ast.TypeAnalysis.inferTypeForExpression(TypeAnalysis.java:803)
        //     at com.strobel.decompiler.ast.TypeAnalysis.runInference(TypeAnalysis.java:672)
        //     at com.strobel.decompiler.ast.TypeAnalysis.runInference(TypeAnalysis.java:655)
        //     at com.strobel.decompiler.ast.TypeAnalysis.runInference(TypeAnalysis.java:365)
        //     at com.strobel.decompiler.ast.TypeAnalysis.run(TypeAnalysis.java:96)
        //     at com.strobel.decompiler.ast.AstOptimizer.optimize(AstOptimizer.java:109)
        //     at com.strobel.decompiler.ast.AstOptimizer.optimize(AstOptimizer.java:42)
        //     at com.strobel.decompiler.languages.java.ast.AstMethodBodyBuilder.createMethodBody(AstMethodBodyBuilder.java:214)
        //     at com.strobel.decompiler.languages.java.ast.AstMethodBodyBuilder.createMethodBody(AstMethodBodyBuilder.java:99)
        //     at com.strobel.decompiler.languages.java.ast.AstBuilder.createMethodBody(AstBuilder.java:757)
        //     at com.strobel.decompiler.languages.java.ast.AstBuilder.createMethod(AstBuilder.java:655)
        //     at com.strobel.decompiler.languages.java.ast.AstBuilder.addTypeMembers(AstBuilder.java:532)
        //     at com.strobel.decompiler.languages.java.ast.AstBuilder.createTypeCore(AstBuilder.java:499)
        //     at com.strobel.decompiler.languages.java.ast.AstBuilder.createTypeNoCache(AstBuilder.java:141)
        //     at com.strobel.decompiler.languages.java.ast.AstBuilder.createType(AstBuilder.java:130)
        //     at com.strobel.decompiler.languages.java.ast.AstBuilder.addType(AstBuilder.java:105)
        //     at com.strobel.decompiler.languages.java.JavaLanguage.buildAst(JavaLanguage.java:71)
        //     at com.strobel.decompiler.languages.java.JavaLanguage.decompileType(JavaLanguage.java:59)
        //     at com.strobel.decompiler.DecompilerDriver.decompileType(DecompilerDriver.java:317)
        //     at com.strobel.decompiler.DecompilerDriver.decompileJar(DecompilerDriver.java:238)
        //     at com.strobel.decompiler.DecompilerDriver.main(DecompilerDriver.java:138)
        // 
        throw new IllegalStateException("An error occurred while decompiling this method.");
    }
    
    public boolean doesCwExist() {
        final String currLolomoId = this.getCurrLolomoId();
        final DataUtil$StringPair currLomoInfo = this.getCurrLomoInfo(LoMoType.CONTINUE_WATCHING);
        if (StringUtils.isEmpty(currLolomoId)) {
            Log.d("CachedModelProxy", "CW doesn't exist - lolomoId is empty");
            return false;
        }
        if (StringUtils.isEmpty((String)currLomoInfo.first)) {
            Log.d("CachedModelProxy", "CW doesn't exist - lomo id is empty");
            return false;
        }
        if (String.valueOf(-1).equals(currLomoInfo.second)) {
            Log.d("CachedModelProxy", "CW doesn't exist - lomo index is invalid");
            return false;
        }
        return true;
    }
    
    public void dumpCacheToDisk() {
        this.dumpCacheToDisk("cache.txt");
    }
    
    public void endBrowsePlaySession(final long p0, final int p1, final int p2, final int p3, final BrowseAgentCallback p4) {
        // 
        // This method could not be decompiled.
        // 
        // Original Bytecode:
        // 
        //     0: aload_0        
        //     1: new             new            !!! ERROR
        //     4: dup            
        //     5: aload_0        
        //     6: lload_1        
        //     7: iload_3        
        //     8: iload           4
        //    10: iload           5
        //    12: aload           6
        //    14: invokespecial   invokespecial  !!! ERROR
        //    17: invokespecial   com/netflix/falkor/CachedModelProxy.launchTask:(Ljava/lang/Runnable;)V
        //    20: return         
        // 
        // The error that occurred was:
        // 
        // java.lang.IllegalArgumentException: Argument 'typeArguments' must not have any null elements.
        //     at com.strobel.core.VerifyArgument.noNullElementsAndNotEmpty(VerifyArgument.java:145)
        //     at com.strobel.assembler.metadata.CoreMetadataFactory$UnresolvedType.makeGenericType(CoreMetadataFactory.java:570)
        //     at com.strobel.assembler.metadata.CoreMetadataFactory.makeParameterizedType(CoreMetadataFactory.java:156)
        //     at com.strobel.assembler.metadata.signatures.Reifier.visitClassTypeSignature(Reifier.java:125)
        //     at com.strobel.assembler.metadata.signatures.ClassTypeSignature.accept(ClassTypeSignature.java:46)
        //     at com.strobel.assembler.metadata.MetadataParser.parseClassSignature(MetadataParser.java:394)
        //     at com.strobel.assembler.metadata.ClassFileReader.populateBaseTypes(ClassFileReader.java:665)
        //     at com.strobel.assembler.metadata.ClassFileReader.readClass(ClassFileReader.java:438)
        //     at com.strobel.assembler.metadata.ClassFileReader.readClass(ClassFileReader.java:366)
        //     at com.strobel.assembler.metadata.MetadataSystem.resolveType(MetadataSystem.java:124)
        //     at com.strobel.decompiler.NoRetryMetadataSystem.resolveType(DecompilerDriver.java:463)
        //     at com.strobel.assembler.metadata.MetadataSystem.resolveCore(MetadataSystem.java:76)
        //     at com.strobel.assembler.metadata.MetadataResolver.resolve(MetadataResolver.java:104)
        //     at com.strobel.assembler.metadata.CoreMetadataFactory$UnresolvedType.resolve(CoreMetadataFactory.java:589)
        //     at com.strobel.assembler.metadata.MetadataResolver.resolve(MetadataResolver.java:128)
        //     at com.strobel.assembler.metadata.CoreMetadataFactory$UnresolvedType.resolve(CoreMetadataFactory.java:599)
        //     at com.strobel.assembler.metadata.MethodReference.resolve(MethodReference.java:172)
        //     at com.strobel.decompiler.ast.TypeAnalysis.inferCall(TypeAnalysis.java:2428)
        //     at com.strobel.decompiler.ast.TypeAnalysis.doInferTypeForExpression(TypeAnalysis.java:1029)
        //     at com.strobel.decompiler.ast.TypeAnalysis.inferTypeForExpression(TypeAnalysis.java:803)
        //     at com.strobel.decompiler.ast.TypeAnalysis.runInference(TypeAnalysis.java:672)
        //     at com.strobel.decompiler.ast.TypeAnalysis.runInference(TypeAnalysis.java:655)
        //     at com.strobel.decompiler.ast.TypeAnalysis.runInference(TypeAnalysis.java:365)
        //     at com.strobel.decompiler.ast.TypeAnalysis.run(TypeAnalysis.java:96)
        //     at com.strobel.decompiler.ast.AstOptimizer.optimize(AstOptimizer.java:109)
        //     at com.strobel.decompiler.ast.AstOptimizer.optimize(AstOptimizer.java:42)
        //     at com.strobel.decompiler.languages.java.ast.AstMethodBodyBuilder.createMethodBody(AstMethodBodyBuilder.java:214)
        //     at com.strobel.decompiler.languages.java.ast.AstMethodBodyBuilder.createMethodBody(AstMethodBodyBuilder.java:99)
        //     at com.strobel.decompiler.languages.java.ast.AstBuilder.createMethodBody(AstBuilder.java:757)
        //     at com.strobel.decompiler.languages.java.ast.AstBuilder.createMethod(AstBuilder.java:655)
        //     at com.strobel.decompiler.languages.java.ast.AstBuilder.addTypeMembers(AstBuilder.java:532)
        //     at com.strobel.decompiler.languages.java.ast.AstBuilder.createTypeCore(AstBuilder.java:499)
        //     at com.strobel.decompiler.languages.java.ast.AstBuilder.createTypeNoCache(AstBuilder.java:141)
        //     at com.strobel.decompiler.languages.java.ast.AstBuilder.createType(AstBuilder.java:130)
        //     at com.strobel.decompiler.languages.java.ast.AstBuilder.addType(AstBuilder.java:105)
        //     at com.strobel.decompiler.languages.java.JavaLanguage.buildAst(JavaLanguage.java:71)
        //     at com.strobel.decompiler.languages.java.JavaLanguage.decompileType(JavaLanguage.java:59)
        //     at com.strobel.decompiler.DecompilerDriver.decompileType(DecompilerDriver.java:317)
        //     at com.strobel.decompiler.DecompilerDriver.decompileJar(DecompilerDriver.java:238)
        //     at com.strobel.decompiler.DecompilerDriver.main(DecompilerDriver.java:138)
        // 
        throw new IllegalStateException("An error occurred while decompiling this method.");
    }
    
    public void expiringContent(final String p0, final BrowseAgentCallback p1, final ExpiringContentAction p2) {
        // 
        // This method could not be decompiled.
        // 
        // Original Bytecode:
        // 
        //     0: aload_0        
        //     1: new             new            !!! ERROR
        //     4: dup            
        //     5: aload_0        
        //     6: aload_1        
        //     7: aload_3        
        //     8: aload_2        
        //     9: invokespecial   invokespecial  !!! ERROR
        //    12: invokespecial   com/netflix/falkor/CachedModelProxy.launchTask:(Ljava/lang/Runnable;)V
        //    15: return         
        // 
        // The error that occurred was:
        // 
        // java.lang.IllegalArgumentException: Argument 'typeArguments' must not have any null elements.
        //     at com.strobel.core.VerifyArgument.noNullElementsAndNotEmpty(VerifyArgument.java:145)
        //     at com.strobel.assembler.metadata.CoreMetadataFactory$UnresolvedType.makeGenericType(CoreMetadataFactory.java:570)
        //     at com.strobel.assembler.metadata.CoreMetadataFactory.makeParameterizedType(CoreMetadataFactory.java:156)
        //     at com.strobel.assembler.metadata.signatures.Reifier.visitClassTypeSignature(Reifier.java:125)
        //     at com.strobel.assembler.metadata.signatures.ClassTypeSignature.accept(ClassTypeSignature.java:46)
        //     at com.strobel.assembler.metadata.MetadataParser.parseClassSignature(MetadataParser.java:394)
        //     at com.strobel.assembler.metadata.ClassFileReader.populateBaseTypes(ClassFileReader.java:665)
        //     at com.strobel.assembler.metadata.ClassFileReader.readClass(ClassFileReader.java:438)
        //     at com.strobel.assembler.metadata.ClassFileReader.readClass(ClassFileReader.java:366)
        //     at com.strobel.assembler.metadata.MetadataSystem.resolveType(MetadataSystem.java:124)
        //     at com.strobel.decompiler.NoRetryMetadataSystem.resolveType(DecompilerDriver.java:463)
        //     at com.strobel.assembler.metadata.MetadataSystem.resolveCore(MetadataSystem.java:76)
        //     at com.strobel.assembler.metadata.MetadataResolver.resolve(MetadataResolver.java:104)
        //     at com.strobel.assembler.metadata.CoreMetadataFactory$UnresolvedType.resolve(CoreMetadataFactory.java:589)
        //     at com.strobel.assembler.metadata.MetadataResolver.resolve(MetadataResolver.java:128)
        //     at com.strobel.assembler.metadata.CoreMetadataFactory$UnresolvedType.resolve(CoreMetadataFactory.java:599)
        //     at com.strobel.assembler.metadata.MethodReference.resolve(MethodReference.java:172)
        //     at com.strobel.decompiler.ast.TypeAnalysis.inferCall(TypeAnalysis.java:2428)
        //     at com.strobel.decompiler.ast.TypeAnalysis.doInferTypeForExpression(TypeAnalysis.java:1029)
        //     at com.strobel.decompiler.ast.TypeAnalysis.inferTypeForExpression(TypeAnalysis.java:803)
        //     at com.strobel.decompiler.ast.TypeAnalysis.runInference(TypeAnalysis.java:672)
        //     at com.strobel.decompiler.ast.TypeAnalysis.runInference(TypeAnalysis.java:655)
        //     at com.strobel.decompiler.ast.TypeAnalysis.runInference(TypeAnalysis.java:365)
        //     at com.strobel.decompiler.ast.TypeAnalysis.run(TypeAnalysis.java:96)
        //     at com.strobel.decompiler.ast.AstOptimizer.optimize(AstOptimizer.java:109)
        //     at com.strobel.decompiler.ast.AstOptimizer.optimize(AstOptimizer.java:42)
        //     at com.strobel.decompiler.languages.java.ast.AstMethodBodyBuilder.createMethodBody(AstMethodBodyBuilder.java:214)
        //     at com.strobel.decompiler.languages.java.ast.AstMethodBodyBuilder.createMethodBody(AstMethodBodyBuilder.java:99)
        //     at com.strobel.decompiler.languages.java.ast.AstBuilder.createMethodBody(AstBuilder.java:757)
        //     at com.strobel.decompiler.languages.java.ast.AstBuilder.createMethod(AstBuilder.java:655)
        //     at com.strobel.decompiler.languages.java.ast.AstBuilder.addTypeMembers(AstBuilder.java:532)
        //     at com.strobel.decompiler.languages.java.ast.AstBuilder.createTypeCore(AstBuilder.java:499)
        //     at com.strobel.decompiler.languages.java.ast.AstBuilder.createTypeNoCache(AstBuilder.java:141)
        //     at com.strobel.decompiler.languages.java.ast.AstBuilder.createType(AstBuilder.java:130)
        //     at com.strobel.decompiler.languages.java.ast.AstBuilder.addType(AstBuilder.java:105)
        //     at com.strobel.decompiler.languages.java.JavaLanguage.buildAst(JavaLanguage.java:71)
        //     at com.strobel.decompiler.languages.java.JavaLanguage.decompileType(JavaLanguage.java:59)
        //     at com.strobel.decompiler.DecompilerDriver.decompileType(DecompilerDriver.java:317)
        //     at com.strobel.decompiler.DecompilerDriver.decompileJar(DecompilerDriver.java:238)
        //     at com.strobel.decompiler.DecompilerDriver.main(DecompilerDriver.java:138)
        // 
        throw new IllegalStateException("An error occurred while decompiling this method.");
    }
    
    public void fetchBBVideos(final int p0, final int p1, final boolean p2, final BrowseAgentCallback p3) {
        // 
        // This method could not be decompiled.
        // 
        // Original Bytecode:
        // 
        //     0: aload_0        
        //     1: new             new            !!! ERROR
        //     4: dup            
        //     5: aload_0        
        //     6: iload_1        
        //     7: iload_2        
        //     8: iload_3        
        //     9: aload           4
        //    11: invokespecial   invokespecial  !!! ERROR
        //    14: invokespecial   com/netflix/falkor/CachedModelProxy.launchTask:(Ljava/lang/Runnable;)V
        //    17: return         
        // 
        // The error that occurred was:
        // 
        // java.lang.IllegalArgumentException: Argument 'typeArguments' must not have any null elements.
        //     at com.strobel.core.VerifyArgument.noNullElementsAndNotEmpty(VerifyArgument.java:145)
        //     at com.strobel.assembler.metadata.CoreMetadataFactory$UnresolvedType.makeGenericType(CoreMetadataFactory.java:570)
        //     at com.strobel.assembler.metadata.CoreMetadataFactory.makeParameterizedType(CoreMetadataFactory.java:156)
        //     at com.strobel.assembler.metadata.signatures.Reifier.visitClassTypeSignature(Reifier.java:125)
        //     at com.strobel.assembler.metadata.signatures.ClassTypeSignature.accept(ClassTypeSignature.java:46)
        //     at com.strobel.assembler.metadata.MetadataParser.parseClassSignature(MetadataParser.java:394)
        //     at com.strobel.assembler.metadata.ClassFileReader.populateBaseTypes(ClassFileReader.java:665)
        //     at com.strobel.assembler.metadata.ClassFileReader.readClass(ClassFileReader.java:438)
        //     at com.strobel.assembler.metadata.ClassFileReader.readClass(ClassFileReader.java:366)
        //     at com.strobel.assembler.metadata.MetadataSystem.resolveType(MetadataSystem.java:124)
        //     at com.strobel.decompiler.NoRetryMetadataSystem.resolveType(DecompilerDriver.java:463)
        //     at com.strobel.assembler.metadata.MetadataSystem.resolveCore(MetadataSystem.java:76)
        //     at com.strobel.assembler.metadata.MetadataResolver.resolve(MetadataResolver.java:104)
        //     at com.strobel.assembler.metadata.CoreMetadataFactory$UnresolvedType.resolve(CoreMetadataFactory.java:589)
        //     at com.strobel.assembler.metadata.MetadataResolver.resolve(MetadataResolver.java:128)
        //     at com.strobel.assembler.metadata.CoreMetadataFactory$UnresolvedType.resolve(CoreMetadataFactory.java:599)
        //     at com.strobel.assembler.metadata.MethodReference.resolve(MethodReference.java:172)
        //     at com.strobel.decompiler.ast.TypeAnalysis.inferCall(TypeAnalysis.java:2428)
        //     at com.strobel.decompiler.ast.TypeAnalysis.doInferTypeForExpression(TypeAnalysis.java:1029)
        //     at com.strobel.decompiler.ast.TypeAnalysis.inferTypeForExpression(TypeAnalysis.java:803)
        //     at com.strobel.decompiler.ast.TypeAnalysis.runInference(TypeAnalysis.java:672)
        //     at com.strobel.decompiler.ast.TypeAnalysis.runInference(TypeAnalysis.java:655)
        //     at com.strobel.decompiler.ast.TypeAnalysis.runInference(TypeAnalysis.java:365)
        //     at com.strobel.decompiler.ast.TypeAnalysis.run(TypeAnalysis.java:96)
        //     at com.strobel.decompiler.ast.AstOptimizer.optimize(AstOptimizer.java:109)
        //     at com.strobel.decompiler.ast.AstOptimizer.optimize(AstOptimizer.java:42)
        //     at com.strobel.decompiler.languages.java.ast.AstMethodBodyBuilder.createMethodBody(AstMethodBodyBuilder.java:214)
        //     at com.strobel.decompiler.languages.java.ast.AstMethodBodyBuilder.createMethodBody(AstMethodBodyBuilder.java:99)
        //     at com.strobel.decompiler.languages.java.ast.AstBuilder.createMethodBody(AstBuilder.java:757)
        //     at com.strobel.decompiler.languages.java.ast.AstBuilder.createMethod(AstBuilder.java:655)
        //     at com.strobel.decompiler.languages.java.ast.AstBuilder.addTypeMembers(AstBuilder.java:532)
        //     at com.strobel.decompiler.languages.java.ast.AstBuilder.createTypeCore(AstBuilder.java:499)
        //     at com.strobel.decompiler.languages.java.ast.AstBuilder.createTypeNoCache(AstBuilder.java:141)
        //     at com.strobel.decompiler.languages.java.ast.AstBuilder.createType(AstBuilder.java:130)
        //     at com.strobel.decompiler.languages.java.ast.AstBuilder.addType(AstBuilder.java:105)
        //     at com.strobel.decompiler.languages.java.JavaLanguage.buildAst(JavaLanguage.java:71)
        //     at com.strobel.decompiler.languages.java.JavaLanguage.decompileType(JavaLanguage.java:59)
        //     at com.strobel.decompiler.DecompilerDriver.decompileType(DecompilerDriver.java:317)
        //     at com.strobel.decompiler.DecompilerDriver.decompileJar(DecompilerDriver.java:238)
        //     at com.strobel.decompiler.DecompilerDriver.main(DecompilerDriver.java:138)
        // 
        throw new IllegalStateException("An error occurred while decompiling this method.");
    }
    
    public void fetchCWVideos(final int p0, final int p1, final boolean p2, final BrowseAgentCallback p3) {
        // 
        // This method could not be decompiled.
        // 
        // Original Bytecode:
        // 
        //     0: aload_0        
        //     1: new             new            !!! ERROR
        //     4: dup            
        //     5: aload_0        
        //     6: iload_1        
        //     7: iload_2        
        //     8: iload_3        
        //     9: aload           4
        //    11: invokespecial   invokespecial  !!! ERROR
        //    14: invokespecial   com/netflix/falkor/CachedModelProxy.launchTask:(Ljava/lang/Runnable;)V
        //    17: return         
        // 
        // The error that occurred was:
        // 
        // java.lang.IllegalArgumentException: Argument 'typeArguments' must not have any null elements.
        //     at com.strobel.core.VerifyArgument.noNullElementsAndNotEmpty(VerifyArgument.java:145)
        //     at com.strobel.assembler.metadata.CoreMetadataFactory$UnresolvedType.makeGenericType(CoreMetadataFactory.java:570)
        //     at com.strobel.assembler.metadata.CoreMetadataFactory.makeParameterizedType(CoreMetadataFactory.java:156)
        //     at com.strobel.assembler.metadata.signatures.Reifier.visitClassTypeSignature(Reifier.java:125)
        //     at com.strobel.assembler.metadata.signatures.ClassTypeSignature.accept(ClassTypeSignature.java:46)
        //     at com.strobel.assembler.metadata.MetadataParser.parseClassSignature(MetadataParser.java:394)
        //     at com.strobel.assembler.metadata.ClassFileReader.populateBaseTypes(ClassFileReader.java:665)
        //     at com.strobel.assembler.metadata.ClassFileReader.readClass(ClassFileReader.java:438)
        //     at com.strobel.assembler.metadata.ClassFileReader.readClass(ClassFileReader.java:366)
        //     at com.strobel.assembler.metadata.MetadataSystem.resolveType(MetadataSystem.java:124)
        //     at com.strobel.decompiler.NoRetryMetadataSystem.resolveType(DecompilerDriver.java:463)
        //     at com.strobel.assembler.metadata.MetadataSystem.resolveCore(MetadataSystem.java:76)
        //     at com.strobel.assembler.metadata.MetadataResolver.resolve(MetadataResolver.java:104)
        //     at com.strobel.assembler.metadata.CoreMetadataFactory$UnresolvedType.resolve(CoreMetadataFactory.java:589)
        //     at com.strobel.assembler.metadata.MetadataResolver.resolve(MetadataResolver.java:128)
        //     at com.strobel.assembler.metadata.CoreMetadataFactory$UnresolvedType.resolve(CoreMetadataFactory.java:599)
        //     at com.strobel.assembler.metadata.MethodReference.resolve(MethodReference.java:172)
        //     at com.strobel.decompiler.ast.TypeAnalysis.inferCall(TypeAnalysis.java:2428)
        //     at com.strobel.decompiler.ast.TypeAnalysis.doInferTypeForExpression(TypeAnalysis.java:1029)
        //     at com.strobel.decompiler.ast.TypeAnalysis.inferTypeForExpression(TypeAnalysis.java:803)
        //     at com.strobel.decompiler.ast.TypeAnalysis.runInference(TypeAnalysis.java:672)
        //     at com.strobel.decompiler.ast.TypeAnalysis.runInference(TypeAnalysis.java:655)
        //     at com.strobel.decompiler.ast.TypeAnalysis.runInference(TypeAnalysis.java:365)
        //     at com.strobel.decompiler.ast.TypeAnalysis.run(TypeAnalysis.java:96)
        //     at com.strobel.decompiler.ast.AstOptimizer.optimize(AstOptimizer.java:109)
        //     at com.strobel.decompiler.ast.AstOptimizer.optimize(AstOptimizer.java:42)
        //     at com.strobel.decompiler.languages.java.ast.AstMethodBodyBuilder.createMethodBody(AstMethodBodyBuilder.java:214)
        //     at com.strobel.decompiler.languages.java.ast.AstMethodBodyBuilder.createMethodBody(AstMethodBodyBuilder.java:99)
        //     at com.strobel.decompiler.languages.java.ast.AstBuilder.createMethodBody(AstBuilder.java:757)
        //     at com.strobel.decompiler.languages.java.ast.AstBuilder.createMethod(AstBuilder.java:655)
        //     at com.strobel.decompiler.languages.java.ast.AstBuilder.addTypeMembers(AstBuilder.java:532)
        //     at com.strobel.decompiler.languages.java.ast.AstBuilder.createTypeCore(AstBuilder.java:499)
        //     at com.strobel.decompiler.languages.java.ast.AstBuilder.createTypeNoCache(AstBuilder.java:141)
        //     at com.strobel.decompiler.languages.java.ast.AstBuilder.createType(AstBuilder.java:130)
        //     at com.strobel.decompiler.languages.java.ast.AstBuilder.addType(AstBuilder.java:105)
        //     at com.strobel.decompiler.languages.java.JavaLanguage.buildAst(JavaLanguage.java:71)
        //     at com.strobel.decompiler.languages.java.JavaLanguage.decompileType(JavaLanguage.java:59)
        //     at com.strobel.decompiler.DecompilerDriver.decompileType(DecompilerDriver.java:317)
        //     at com.strobel.decompiler.DecompilerDriver.decompileJar(DecompilerDriver.java:238)
        //     at com.strobel.decompiler.DecompilerDriver.main(DecompilerDriver.java:138)
        // 
        throw new IllegalStateException("An error occurred while decompiling this method.");
    }
    
    public void fetchEpisodeDetails(final String p0, final String p1, final BrowseAgentCallback p2) {
        // 
        // This method could not be decompiled.
        // 
        // Original Bytecode:
        // 
        //     0: aload_0        
        //     1: new             new            !!! ERROR
        //     4: dup            
        //     5: aload_0        
        //     6: aload_1        
        //     7: aload_2        
        //     8: aload_3        
        //     9: invokespecial   invokespecial  !!! ERROR
        //    12: invokespecial   com/netflix/falkor/CachedModelProxy.launchTask:(Ljava/lang/Runnable;)V
        //    15: return         
        // 
        // The error that occurred was:
        // 
        // java.lang.IllegalArgumentException: Argument 'typeArguments' must not have any null elements.
        //     at com.strobel.core.VerifyArgument.noNullElementsAndNotEmpty(VerifyArgument.java:145)
        //     at com.strobel.assembler.metadata.CoreMetadataFactory$UnresolvedType.makeGenericType(CoreMetadataFactory.java:570)
        //     at com.strobel.assembler.metadata.CoreMetadataFactory.makeParameterizedType(CoreMetadataFactory.java:156)
        //     at com.strobel.assembler.metadata.signatures.Reifier.visitClassTypeSignature(Reifier.java:125)
        //     at com.strobel.assembler.metadata.signatures.ClassTypeSignature.accept(ClassTypeSignature.java:46)
        //     at com.strobel.assembler.metadata.MetadataParser.parseClassSignature(MetadataParser.java:394)
        //     at com.strobel.assembler.metadata.ClassFileReader.populateBaseTypes(ClassFileReader.java:665)
        //     at com.strobel.assembler.metadata.ClassFileReader.readClass(ClassFileReader.java:438)
        //     at com.strobel.assembler.metadata.ClassFileReader.readClass(ClassFileReader.java:366)
        //     at com.strobel.assembler.metadata.MetadataSystem.resolveType(MetadataSystem.java:124)
        //     at com.strobel.decompiler.NoRetryMetadataSystem.resolveType(DecompilerDriver.java:463)
        //     at com.strobel.assembler.metadata.MetadataSystem.resolveCore(MetadataSystem.java:76)
        //     at com.strobel.assembler.metadata.MetadataResolver.resolve(MetadataResolver.java:104)
        //     at com.strobel.assembler.metadata.CoreMetadataFactory$UnresolvedType.resolve(CoreMetadataFactory.java:589)
        //     at com.strobel.assembler.metadata.MetadataResolver.resolve(MetadataResolver.java:128)
        //     at com.strobel.assembler.metadata.CoreMetadataFactory$UnresolvedType.resolve(CoreMetadataFactory.java:599)
        //     at com.strobel.assembler.metadata.MethodReference.resolve(MethodReference.java:172)
        //     at com.strobel.decompiler.ast.TypeAnalysis.inferCall(TypeAnalysis.java:2428)
        //     at com.strobel.decompiler.ast.TypeAnalysis.doInferTypeForExpression(TypeAnalysis.java:1029)
        //     at com.strobel.decompiler.ast.TypeAnalysis.inferTypeForExpression(TypeAnalysis.java:803)
        //     at com.strobel.decompiler.ast.TypeAnalysis.runInference(TypeAnalysis.java:672)
        //     at com.strobel.decompiler.ast.TypeAnalysis.runInference(TypeAnalysis.java:655)
        //     at com.strobel.decompiler.ast.TypeAnalysis.runInference(TypeAnalysis.java:365)
        //     at com.strobel.decompiler.ast.TypeAnalysis.run(TypeAnalysis.java:96)
        //     at com.strobel.decompiler.ast.AstOptimizer.optimize(AstOptimizer.java:109)
        //     at com.strobel.decompiler.ast.AstOptimizer.optimize(AstOptimizer.java:42)
        //     at com.strobel.decompiler.languages.java.ast.AstMethodBodyBuilder.createMethodBody(AstMethodBodyBuilder.java:214)
        //     at com.strobel.decompiler.languages.java.ast.AstMethodBodyBuilder.createMethodBody(AstMethodBodyBuilder.java:99)
        //     at com.strobel.decompiler.languages.java.ast.AstBuilder.createMethodBody(AstBuilder.java:757)
        //     at com.strobel.decompiler.languages.java.ast.AstBuilder.createMethod(AstBuilder.java:655)
        //     at com.strobel.decompiler.languages.java.ast.AstBuilder.addTypeMembers(AstBuilder.java:532)
        //     at com.strobel.decompiler.languages.java.ast.AstBuilder.createTypeCore(AstBuilder.java:499)
        //     at com.strobel.decompiler.languages.java.ast.AstBuilder.createTypeNoCache(AstBuilder.java:141)
        //     at com.strobel.decompiler.languages.java.ast.AstBuilder.createType(AstBuilder.java:130)
        //     at com.strobel.decompiler.languages.java.ast.AstBuilder.addType(AstBuilder.java:105)
        //     at com.strobel.decompiler.languages.java.JavaLanguage.buildAst(JavaLanguage.java:71)
        //     at com.strobel.decompiler.languages.java.JavaLanguage.decompileType(JavaLanguage.java:59)
        //     at com.strobel.decompiler.DecompilerDriver.decompileType(DecompilerDriver.java:317)
        //     at com.strobel.decompiler.DecompilerDriver.decompileJar(DecompilerDriver.java:238)
        //     at com.strobel.decompiler.DecompilerDriver.main(DecompilerDriver.java:138)
        // 
        throw new IllegalStateException("An error occurred while decompiling this method.");
    }
    
    public void fetchEpisodes(final String p0, final VideoType p1, final int p2, final int p3, final BrowseAgentCallback p4) {
        // 
        // This method could not be decompiled.
        // 
        // Original Bytecode:
        // 
        //     0: aload_0        
        //     1: new             new            !!! ERROR
        //     4: dup            
        //     5: aload_0        
        //     6: aload_1        
        //     7: aload_2        
        //     8: iload_3        
        //     9: iload           4
        //    11: aload           5
        //    13: invokespecial   invokespecial  !!! ERROR
        //    16: invokespecial   com/netflix/falkor/CachedModelProxy.launchTask:(Ljava/lang/Runnable;)V
        //    19: return         
        // 
        // The error that occurred was:
        // 
        // java.lang.IllegalArgumentException: Argument 'typeArguments' must not have any null elements.
        //     at com.strobel.core.VerifyArgument.noNullElementsAndNotEmpty(VerifyArgument.java:145)
        //     at com.strobel.assembler.metadata.CoreMetadataFactory$UnresolvedType.makeGenericType(CoreMetadataFactory.java:570)
        //     at com.strobel.assembler.metadata.CoreMetadataFactory.makeParameterizedType(CoreMetadataFactory.java:156)
        //     at com.strobel.assembler.metadata.signatures.Reifier.visitClassTypeSignature(Reifier.java:125)
        //     at com.strobel.assembler.metadata.signatures.ClassTypeSignature.accept(ClassTypeSignature.java:46)
        //     at com.strobel.assembler.metadata.MetadataParser.parseClassSignature(MetadataParser.java:394)
        //     at com.strobel.assembler.metadata.ClassFileReader.populateBaseTypes(ClassFileReader.java:665)
        //     at com.strobel.assembler.metadata.ClassFileReader.readClass(ClassFileReader.java:438)
        //     at com.strobel.assembler.metadata.ClassFileReader.readClass(ClassFileReader.java:366)
        //     at com.strobel.assembler.metadata.MetadataSystem.resolveType(MetadataSystem.java:124)
        //     at com.strobel.decompiler.NoRetryMetadataSystem.resolveType(DecompilerDriver.java:463)
        //     at com.strobel.assembler.metadata.MetadataSystem.resolveCore(MetadataSystem.java:76)
        //     at com.strobel.assembler.metadata.MetadataResolver.resolve(MetadataResolver.java:104)
        //     at com.strobel.assembler.metadata.CoreMetadataFactory$UnresolvedType.resolve(CoreMetadataFactory.java:589)
        //     at com.strobel.assembler.metadata.MetadataResolver.resolve(MetadataResolver.java:128)
        //     at com.strobel.assembler.metadata.CoreMetadataFactory$UnresolvedType.resolve(CoreMetadataFactory.java:599)
        //     at com.strobel.assembler.metadata.MethodReference.resolve(MethodReference.java:172)
        //     at com.strobel.decompiler.ast.TypeAnalysis.inferCall(TypeAnalysis.java:2428)
        //     at com.strobel.decompiler.ast.TypeAnalysis.doInferTypeForExpression(TypeAnalysis.java:1029)
        //     at com.strobel.decompiler.ast.TypeAnalysis.inferTypeForExpression(TypeAnalysis.java:803)
        //     at com.strobel.decompiler.ast.TypeAnalysis.runInference(TypeAnalysis.java:672)
        //     at com.strobel.decompiler.ast.TypeAnalysis.runInference(TypeAnalysis.java:655)
        //     at com.strobel.decompiler.ast.TypeAnalysis.runInference(TypeAnalysis.java:365)
        //     at com.strobel.decompiler.ast.TypeAnalysis.run(TypeAnalysis.java:96)
        //     at com.strobel.decompiler.ast.AstOptimizer.optimize(AstOptimizer.java:109)
        //     at com.strobel.decompiler.ast.AstOptimizer.optimize(AstOptimizer.java:42)
        //     at com.strobel.decompiler.languages.java.ast.AstMethodBodyBuilder.createMethodBody(AstMethodBodyBuilder.java:214)
        //     at com.strobel.decompiler.languages.java.ast.AstMethodBodyBuilder.createMethodBody(AstMethodBodyBuilder.java:99)
        //     at com.strobel.decompiler.languages.java.ast.AstBuilder.createMethodBody(AstBuilder.java:757)
        //     at com.strobel.decompiler.languages.java.ast.AstBuilder.createMethod(AstBuilder.java:655)
        //     at com.strobel.decompiler.languages.java.ast.AstBuilder.addTypeMembers(AstBuilder.java:532)
        //     at com.strobel.decompiler.languages.java.ast.AstBuilder.createTypeCore(AstBuilder.java:499)
        //     at com.strobel.decompiler.languages.java.ast.AstBuilder.createTypeNoCache(AstBuilder.java:141)
        //     at com.strobel.decompiler.languages.java.ast.AstBuilder.createType(AstBuilder.java:130)
        //     at com.strobel.decompiler.languages.java.ast.AstBuilder.addType(AstBuilder.java:105)
        //     at com.strobel.decompiler.languages.java.JavaLanguage.buildAst(JavaLanguage.java:71)
        //     at com.strobel.decompiler.languages.java.JavaLanguage.decompileType(JavaLanguage.java:59)
        //     at com.strobel.decompiler.DecompilerDriver.decompileType(DecompilerDriver.java:317)
        //     at com.strobel.decompiler.DecompilerDriver.decompileJar(DecompilerDriver.java:238)
        //     at com.strobel.decompiler.DecompilerDriver.main(DecompilerDriver.java:138)
        // 
        throw new IllegalStateException("An error occurred while decompiling this method.");
    }
    
    public void fetchGenreList(final BrowseAgentCallback p0) {
        // 
        // This method could not be decompiled.
        // 
        // Original Bytecode:
        // 
        //     0: aload_0        
        //     1: new             new            !!! ERROR
        //     4: dup            
        //     5: aload_0        
        //     6: aload_1        
        //     7: invokespecial   invokespecial  !!! ERROR
        //    10: invokespecial   com/netflix/falkor/CachedModelProxy.launchTask:(Ljava/lang/Runnable;)V
        //    13: return         
        // 
        // The error that occurred was:
        // 
        // java.lang.IllegalArgumentException: Argument 'typeArguments' must not have any null elements.
        //     at com.strobel.core.VerifyArgument.noNullElementsAndNotEmpty(VerifyArgument.java:145)
        //     at com.strobel.assembler.metadata.CoreMetadataFactory$UnresolvedType.makeGenericType(CoreMetadataFactory.java:570)
        //     at com.strobel.assembler.metadata.CoreMetadataFactory.makeParameterizedType(CoreMetadataFactory.java:156)
        //     at com.strobel.assembler.metadata.signatures.Reifier.visitClassTypeSignature(Reifier.java:125)
        //     at com.strobel.assembler.metadata.signatures.ClassTypeSignature.accept(ClassTypeSignature.java:46)
        //     at com.strobel.assembler.metadata.MetadataParser.parseClassSignature(MetadataParser.java:394)
        //     at com.strobel.assembler.metadata.ClassFileReader.populateBaseTypes(ClassFileReader.java:665)
        //     at com.strobel.assembler.metadata.ClassFileReader.readClass(ClassFileReader.java:438)
        //     at com.strobel.assembler.metadata.ClassFileReader.readClass(ClassFileReader.java:366)
        //     at com.strobel.assembler.metadata.MetadataSystem.resolveType(MetadataSystem.java:124)
        //     at com.strobel.decompiler.NoRetryMetadataSystem.resolveType(DecompilerDriver.java:463)
        //     at com.strobel.assembler.metadata.MetadataSystem.resolveCore(MetadataSystem.java:76)
        //     at com.strobel.assembler.metadata.MetadataResolver.resolve(MetadataResolver.java:104)
        //     at com.strobel.assembler.metadata.CoreMetadataFactory$UnresolvedType.resolve(CoreMetadataFactory.java:589)
        //     at com.strobel.assembler.metadata.MetadataResolver.resolve(MetadataResolver.java:128)
        //     at com.strobel.assembler.metadata.CoreMetadataFactory$UnresolvedType.resolve(CoreMetadataFactory.java:599)
        //     at com.strobel.assembler.metadata.MethodReference.resolve(MethodReference.java:172)
        //     at com.strobel.decompiler.ast.TypeAnalysis.inferCall(TypeAnalysis.java:2428)
        //     at com.strobel.decompiler.ast.TypeAnalysis.doInferTypeForExpression(TypeAnalysis.java:1029)
        //     at com.strobel.decompiler.ast.TypeAnalysis.inferTypeForExpression(TypeAnalysis.java:803)
        //     at com.strobel.decompiler.ast.TypeAnalysis.runInference(TypeAnalysis.java:672)
        //     at com.strobel.decompiler.ast.TypeAnalysis.runInference(TypeAnalysis.java:655)
        //     at com.strobel.decompiler.ast.TypeAnalysis.runInference(TypeAnalysis.java:365)
        //     at com.strobel.decompiler.ast.TypeAnalysis.run(TypeAnalysis.java:96)
        //     at com.strobel.decompiler.ast.AstOptimizer.optimize(AstOptimizer.java:109)
        //     at com.strobel.decompiler.ast.AstOptimizer.optimize(AstOptimizer.java:42)
        //     at com.strobel.decompiler.languages.java.ast.AstMethodBodyBuilder.createMethodBody(AstMethodBodyBuilder.java:214)
        //     at com.strobel.decompiler.languages.java.ast.AstMethodBodyBuilder.createMethodBody(AstMethodBodyBuilder.java:99)
        //     at com.strobel.decompiler.languages.java.ast.AstBuilder.createMethodBody(AstBuilder.java:757)
        //     at com.strobel.decompiler.languages.java.ast.AstBuilder.createMethod(AstBuilder.java:655)
        //     at com.strobel.decompiler.languages.java.ast.AstBuilder.addTypeMembers(AstBuilder.java:532)
        //     at com.strobel.decompiler.languages.java.ast.AstBuilder.createTypeCore(AstBuilder.java:499)
        //     at com.strobel.decompiler.languages.java.ast.AstBuilder.createTypeNoCache(AstBuilder.java:141)
        //     at com.strobel.decompiler.languages.java.ast.AstBuilder.createType(AstBuilder.java:130)
        //     at com.strobel.decompiler.languages.java.ast.AstBuilder.addType(AstBuilder.java:105)
        //     at com.strobel.decompiler.languages.java.JavaLanguage.buildAst(JavaLanguage.java:71)
        //     at com.strobel.decompiler.languages.java.JavaLanguage.decompileType(JavaLanguage.java:59)
        //     at com.strobel.decompiler.DecompilerDriver.decompileType(DecompilerDriver.java:317)
        //     at com.strobel.decompiler.DecompilerDriver.decompileJar(DecompilerDriver.java:238)
        //     at com.strobel.decompiler.DecompilerDriver.main(DecompilerDriver.java:138)
        // 
        throw new IllegalStateException("An error occurred while decompiling this method.");
    }
    
    public void fetchGenreLoLoMoSummary(final String p0, final BrowseAgentCallback p1) {
        // 
        // This method could not be decompiled.
        // 
        // Original Bytecode:
        // 
        //     0: aload_0        
        //     1: new             new            !!! ERROR
        //     4: dup            
        //     5: aload_0        
        //     6: aload_1        
        //     7: aload_2        
        //     8: invokespecial   invokespecial  !!! ERROR
        //    11: invokespecial   com/netflix/falkor/CachedModelProxy.launchTask:(Ljava/lang/Runnable;)V
        //    14: return         
        // 
        // The error that occurred was:
        // 
        // java.lang.IllegalArgumentException: Argument 'typeArguments' must not have any null elements.
        //     at com.strobel.core.VerifyArgument.noNullElementsAndNotEmpty(VerifyArgument.java:145)
        //     at com.strobel.assembler.metadata.CoreMetadataFactory$UnresolvedType.makeGenericType(CoreMetadataFactory.java:570)
        //     at com.strobel.assembler.metadata.CoreMetadataFactory.makeParameterizedType(CoreMetadataFactory.java:156)
        //     at com.strobel.assembler.metadata.signatures.Reifier.visitClassTypeSignature(Reifier.java:125)
        //     at com.strobel.assembler.metadata.signatures.ClassTypeSignature.accept(ClassTypeSignature.java:46)
        //     at com.strobel.assembler.metadata.MetadataParser.parseClassSignature(MetadataParser.java:394)
        //     at com.strobel.assembler.metadata.ClassFileReader.populateBaseTypes(ClassFileReader.java:665)
        //     at com.strobel.assembler.metadata.ClassFileReader.readClass(ClassFileReader.java:438)
        //     at com.strobel.assembler.metadata.ClassFileReader.readClass(ClassFileReader.java:366)
        //     at com.strobel.assembler.metadata.MetadataSystem.resolveType(MetadataSystem.java:124)
        //     at com.strobel.decompiler.NoRetryMetadataSystem.resolveType(DecompilerDriver.java:463)
        //     at com.strobel.assembler.metadata.MetadataSystem.resolveCore(MetadataSystem.java:76)
        //     at com.strobel.assembler.metadata.MetadataResolver.resolve(MetadataResolver.java:104)
        //     at com.strobel.assembler.metadata.CoreMetadataFactory$UnresolvedType.resolve(CoreMetadataFactory.java:589)
        //     at com.strobel.assembler.metadata.MetadataResolver.resolve(MetadataResolver.java:128)
        //     at com.strobel.assembler.metadata.CoreMetadataFactory$UnresolvedType.resolve(CoreMetadataFactory.java:599)
        //     at com.strobel.assembler.metadata.MethodReference.resolve(MethodReference.java:172)
        //     at com.strobel.decompiler.ast.TypeAnalysis.inferCall(TypeAnalysis.java:2428)
        //     at com.strobel.decompiler.ast.TypeAnalysis.doInferTypeForExpression(TypeAnalysis.java:1029)
        //     at com.strobel.decompiler.ast.TypeAnalysis.inferTypeForExpression(TypeAnalysis.java:803)
        //     at com.strobel.decompiler.ast.TypeAnalysis.runInference(TypeAnalysis.java:672)
        //     at com.strobel.decompiler.ast.TypeAnalysis.runInference(TypeAnalysis.java:655)
        //     at com.strobel.decompiler.ast.TypeAnalysis.runInference(TypeAnalysis.java:365)
        //     at com.strobel.decompiler.ast.TypeAnalysis.run(TypeAnalysis.java:96)
        //     at com.strobel.decompiler.ast.AstOptimizer.optimize(AstOptimizer.java:109)
        //     at com.strobel.decompiler.ast.AstOptimizer.optimize(AstOptimizer.java:42)
        //     at com.strobel.decompiler.languages.java.ast.AstMethodBodyBuilder.createMethodBody(AstMethodBodyBuilder.java:214)
        //     at com.strobel.decompiler.languages.java.ast.AstMethodBodyBuilder.createMethodBody(AstMethodBodyBuilder.java:99)
        //     at com.strobel.decompiler.languages.java.ast.AstBuilder.createMethodBody(AstBuilder.java:757)
        //     at com.strobel.decompiler.languages.java.ast.AstBuilder.createMethod(AstBuilder.java:655)
        //     at com.strobel.decompiler.languages.java.ast.AstBuilder.addTypeMembers(AstBuilder.java:532)
        //     at com.strobel.decompiler.languages.java.ast.AstBuilder.createTypeCore(AstBuilder.java:499)
        //     at com.strobel.decompiler.languages.java.ast.AstBuilder.createTypeNoCache(AstBuilder.java:141)
        //     at com.strobel.decompiler.languages.java.ast.AstBuilder.createType(AstBuilder.java:130)
        //     at com.strobel.decompiler.languages.java.ast.AstBuilder.addType(AstBuilder.java:105)
        //     at com.strobel.decompiler.languages.java.JavaLanguage.buildAst(JavaLanguage.java:71)
        //     at com.strobel.decompiler.languages.java.JavaLanguage.decompileType(JavaLanguage.java:59)
        //     at com.strobel.decompiler.DecompilerDriver.decompileType(DecompilerDriver.java:317)
        //     at com.strobel.decompiler.DecompilerDriver.decompileJar(DecompilerDriver.java:238)
        //     at com.strobel.decompiler.DecompilerDriver.main(DecompilerDriver.java:138)
        // 
        throw new IllegalStateException("An error occurred while decompiling this method.");
    }
    
    public void fetchGenres(final String p0, final int p1, final int p2, final BrowseAgentCallback p3) {
        // 
        // This method could not be decompiled.
        // 
        // Original Bytecode:
        // 
        //     0: aload_0        
        //     1: new             new            !!! ERROR
        //     4: dup            
        //     5: aload_0        
        //     6: aload_1        
        //     7: iload_2        
        //     8: iload_3        
        //     9: aload           4
        //    11: invokespecial   invokespecial  !!! ERROR
        //    14: invokespecial   com/netflix/falkor/CachedModelProxy.launchTask:(Ljava/lang/Runnable;)V
        //    17: return         
        // 
        // The error that occurred was:
        // 
        // java.lang.IllegalArgumentException: Argument 'typeArguments' must not have any null elements.
        //     at com.strobel.core.VerifyArgument.noNullElementsAndNotEmpty(VerifyArgument.java:145)
        //     at com.strobel.assembler.metadata.CoreMetadataFactory$UnresolvedType.makeGenericType(CoreMetadataFactory.java:570)
        //     at com.strobel.assembler.metadata.CoreMetadataFactory.makeParameterizedType(CoreMetadataFactory.java:156)
        //     at com.strobel.assembler.metadata.signatures.Reifier.visitClassTypeSignature(Reifier.java:125)
        //     at com.strobel.assembler.metadata.signatures.ClassTypeSignature.accept(ClassTypeSignature.java:46)
        //     at com.strobel.assembler.metadata.MetadataParser.parseClassSignature(MetadataParser.java:394)
        //     at com.strobel.assembler.metadata.ClassFileReader.populateBaseTypes(ClassFileReader.java:665)
        //     at com.strobel.assembler.metadata.ClassFileReader.readClass(ClassFileReader.java:438)
        //     at com.strobel.assembler.metadata.ClassFileReader.readClass(ClassFileReader.java:366)
        //     at com.strobel.assembler.metadata.MetadataSystem.resolveType(MetadataSystem.java:124)
        //     at com.strobel.decompiler.NoRetryMetadataSystem.resolveType(DecompilerDriver.java:463)
        //     at com.strobel.assembler.metadata.MetadataSystem.resolveCore(MetadataSystem.java:76)
        //     at com.strobel.assembler.metadata.MetadataResolver.resolve(MetadataResolver.java:104)
        //     at com.strobel.assembler.metadata.CoreMetadataFactory$UnresolvedType.resolve(CoreMetadataFactory.java:589)
        //     at com.strobel.assembler.metadata.MetadataResolver.resolve(MetadataResolver.java:128)
        //     at com.strobel.assembler.metadata.CoreMetadataFactory$UnresolvedType.resolve(CoreMetadataFactory.java:599)
        //     at com.strobel.assembler.metadata.MethodReference.resolve(MethodReference.java:172)
        //     at com.strobel.decompiler.ast.TypeAnalysis.inferCall(TypeAnalysis.java:2428)
        //     at com.strobel.decompiler.ast.TypeAnalysis.doInferTypeForExpression(TypeAnalysis.java:1029)
        //     at com.strobel.decompiler.ast.TypeAnalysis.inferTypeForExpression(TypeAnalysis.java:803)
        //     at com.strobel.decompiler.ast.TypeAnalysis.runInference(TypeAnalysis.java:672)
        //     at com.strobel.decompiler.ast.TypeAnalysis.runInference(TypeAnalysis.java:655)
        //     at com.strobel.decompiler.ast.TypeAnalysis.runInference(TypeAnalysis.java:365)
        //     at com.strobel.decompiler.ast.TypeAnalysis.run(TypeAnalysis.java:96)
        //     at com.strobel.decompiler.ast.AstOptimizer.optimize(AstOptimizer.java:109)
        //     at com.strobel.decompiler.ast.AstOptimizer.optimize(AstOptimizer.java:42)
        //     at com.strobel.decompiler.languages.java.ast.AstMethodBodyBuilder.createMethodBody(AstMethodBodyBuilder.java:214)
        //     at com.strobel.decompiler.languages.java.ast.AstMethodBodyBuilder.createMethodBody(AstMethodBodyBuilder.java:99)
        //     at com.strobel.decompiler.languages.java.ast.AstBuilder.createMethodBody(AstBuilder.java:757)
        //     at com.strobel.decompiler.languages.java.ast.AstBuilder.createMethod(AstBuilder.java:655)
        //     at com.strobel.decompiler.languages.java.ast.AstBuilder.addTypeMembers(AstBuilder.java:532)
        //     at com.strobel.decompiler.languages.java.ast.AstBuilder.createTypeCore(AstBuilder.java:499)
        //     at com.strobel.decompiler.languages.java.ast.AstBuilder.createTypeNoCache(AstBuilder.java:141)
        //     at com.strobel.decompiler.languages.java.ast.AstBuilder.createType(AstBuilder.java:130)
        //     at com.strobel.decompiler.languages.java.ast.AstBuilder.addType(AstBuilder.java:105)
        //     at com.strobel.decompiler.languages.java.JavaLanguage.buildAst(JavaLanguage.java:71)
        //     at com.strobel.decompiler.languages.java.JavaLanguage.decompileType(JavaLanguage.java:59)
        //     at com.strobel.decompiler.DecompilerDriver.decompileType(DecompilerDriver.java:317)
        //     at com.strobel.decompiler.DecompilerDriver.decompileJar(DecompilerDriver.java:238)
        //     at com.strobel.decompiler.DecompilerDriver.main(DecompilerDriver.java:138)
        // 
        throw new IllegalStateException("An error occurred while decompiling this method.");
    }
    
    public void fetchIQVideos(final int p0, final int p1, final boolean p2, final boolean p3, final BrowseAgentCallback p4) {
        // 
        // This method could not be decompiled.
        // 
        // Original Bytecode:
        // 
        //     0: aload_0        
        //     1: getstatic       com/netflix/mediaclient/servicemgr/interface_/LoMoType.INSTANT_QUEUE:Lcom/netflix/mediaclient/servicemgr/interface_/LoMoType;
        //     4: invokespecial   com/netflix/falkor/CachedModelProxy.getCurrLomoByType:(Lcom/netflix/mediaclient/servicemgr/interface_/LoMoType;)Landroid/util/Pair;
        //     7: astore          6
        //     9: aload           6
        //    11: ifnull          22
        //    14: aload           6
        //    16: getfield        android/util/Pair.first:Ljava/lang/Object;
        //    19: ifnonnull       43
        //    22: ldc             "CachedModelProxy"
        //    24: ldc_w           "Asked to fetch IQ videos but no IQ lomo currently exists in cache!"
        //    27: invokestatic    com/netflix/mediaclient/Log.d:(Ljava/lang/String;Ljava/lang/String;)I
        //    30: pop            
        //    31: aload           5
        //    33: aconst_null    
        //    34: getstatic       com/netflix/mediaclient/android/app/CommonStatus.NOT_VALID:Lcom/netflix/mediaclient/android/app/NetflixImmutableStatus;
        //    37: invokeinterface com/netflix/mediaclient/service/browse/BrowseAgentCallback.onVideosFetched:(Ljava/util/List;Lcom/netflix/mediaclient/android/app/Status;)V
        //    42: return         
        //    43: aload_0        
        //    44: new             new            !!! ERROR
        //    47: dup            
        //    48: aload_0        
        //    49: aload           6
        //    51: getfield        android/util/Pair.first:Ljava/lang/Object;
        //    54: checkcast       Lcom/netflix/mediaclient/servicemgr/interface_/LoMo;
        //    57: iload_1        
        //    58: iload_2        
        //    59: iload_3        
        //    60: iload           4
        //    62: iconst_0       
        //    63: aload           5
        //    65: invokespecial   invokespecial  !!! ERROR
        //    68: invokespecial   com/netflix/falkor/CachedModelProxy.launchTask:(Ljava/lang/Runnable;)V
        //    71: return         
        // 
        // The error that occurred was:
        // 
        // java.lang.IllegalArgumentException: Argument 'typeArguments' must not have any null elements.
        //     at com.strobel.core.VerifyArgument.noNullElementsAndNotEmpty(VerifyArgument.java:145)
        //     at com.strobel.assembler.metadata.CoreMetadataFactory$UnresolvedType.makeGenericType(CoreMetadataFactory.java:570)
        //     at com.strobel.assembler.metadata.CoreMetadataFactory.makeParameterizedType(CoreMetadataFactory.java:156)
        //     at com.strobel.assembler.metadata.signatures.Reifier.visitClassTypeSignature(Reifier.java:125)
        //     at com.strobel.assembler.metadata.signatures.ClassTypeSignature.accept(ClassTypeSignature.java:46)
        //     at com.strobel.assembler.metadata.MetadataParser.parseClassSignature(MetadataParser.java:394)
        //     at com.strobel.assembler.metadata.ClassFileReader.populateBaseTypes(ClassFileReader.java:665)
        //     at com.strobel.assembler.metadata.ClassFileReader.readClass(ClassFileReader.java:438)
        //     at com.strobel.assembler.metadata.ClassFileReader.readClass(ClassFileReader.java:366)
        //     at com.strobel.assembler.metadata.MetadataSystem.resolveType(MetadataSystem.java:124)
        //     at com.strobel.decompiler.NoRetryMetadataSystem.resolveType(DecompilerDriver.java:463)
        //     at com.strobel.assembler.metadata.MetadataSystem.resolveCore(MetadataSystem.java:76)
        //     at com.strobel.assembler.metadata.MetadataResolver.resolve(MetadataResolver.java:104)
        //     at com.strobel.assembler.metadata.CoreMetadataFactory$UnresolvedType.resolve(CoreMetadataFactory.java:589)
        //     at com.strobel.assembler.metadata.MetadataResolver.resolve(MetadataResolver.java:128)
        //     at com.strobel.assembler.metadata.CoreMetadataFactory$UnresolvedType.resolve(CoreMetadataFactory.java:599)
        //     at com.strobel.assembler.metadata.MethodReference.resolve(MethodReference.java:172)
        //     at com.strobel.decompiler.ast.TypeAnalysis.inferCall(TypeAnalysis.java:2428)
        //     at com.strobel.decompiler.ast.TypeAnalysis.doInferTypeForExpression(TypeAnalysis.java:1029)
        //     at com.strobel.decompiler.ast.TypeAnalysis.inferTypeForExpression(TypeAnalysis.java:803)
        //     at com.strobel.decompiler.ast.TypeAnalysis.runInference(TypeAnalysis.java:672)
        //     at com.strobel.decompiler.ast.TypeAnalysis.runInference(TypeAnalysis.java:655)
        //     at com.strobel.decompiler.ast.TypeAnalysis.runInference(TypeAnalysis.java:365)
        //     at com.strobel.decompiler.ast.TypeAnalysis.run(TypeAnalysis.java:96)
        //     at com.strobel.decompiler.ast.AstOptimizer.optimize(AstOptimizer.java:109)
        //     at com.strobel.decompiler.ast.AstOptimizer.optimize(AstOptimizer.java:42)
        //     at com.strobel.decompiler.languages.java.ast.AstMethodBodyBuilder.createMethodBody(AstMethodBodyBuilder.java:214)
        //     at com.strobel.decompiler.languages.java.ast.AstMethodBodyBuilder.createMethodBody(AstMethodBodyBuilder.java:99)
        //     at com.strobel.decompiler.languages.java.ast.AstBuilder.createMethodBody(AstBuilder.java:757)
        //     at com.strobel.decompiler.languages.java.ast.AstBuilder.createMethod(AstBuilder.java:655)
        //     at com.strobel.decompiler.languages.java.ast.AstBuilder.addTypeMembers(AstBuilder.java:532)
        //     at com.strobel.decompiler.languages.java.ast.AstBuilder.createTypeCore(AstBuilder.java:499)
        //     at com.strobel.decompiler.languages.java.ast.AstBuilder.createTypeNoCache(AstBuilder.java:141)
        //     at com.strobel.decompiler.languages.java.ast.AstBuilder.createType(AstBuilder.java:130)
        //     at com.strobel.decompiler.languages.java.ast.AstBuilder.addType(AstBuilder.java:105)
        //     at com.strobel.decompiler.languages.java.JavaLanguage.buildAst(JavaLanguage.java:71)
        //     at com.strobel.decompiler.languages.java.JavaLanguage.decompileType(JavaLanguage.java:59)
        //     at com.strobel.decompiler.DecompilerDriver.decompileType(DecompilerDriver.java:317)
        //     at com.strobel.decompiler.DecompilerDriver.decompileJar(DecompilerDriver.java:238)
        //     at com.strobel.decompiler.DecompilerDriver.main(DecompilerDriver.java:138)
        // 
        throw new IllegalStateException("An error occurred while decompiling this method.");
    }
    
    public void fetchIQVideos(final LoMo p0, final int p1, final int p2, final boolean p3, final boolean p4, final BrowseAgentCallback p5) {
        // 
        // This method could not be decompiled.
        // 
        // Original Bytecode:
        // 
        //     0: aload_0        
        //     1: getstatic       com/netflix/mediaclient/servicemgr/interface_/LoMoType.INSTANT_QUEUE:Lcom/netflix/mediaclient/servicemgr/interface_/LoMoType;
        //     4: invokespecial   com/netflix/falkor/CachedModelProxy.getCurrLomoInfo:(Lcom/netflix/mediaclient/servicemgr/interface_/LoMoType;)Lcom/netflix/mediaclient/util/DataUtil$StringPair;
        //     7: astore          7
        //     9: aload           7
        //    11: ifnonnull       35
        //    14: ldc             "CachedModelProxy"
        //    16: ldc_w           "Asked to fetch IQ videos but no IQ lomo currently exists in cache!"
        //    19: invokestatic    com/netflix/mediaclient/Log.w:(Ljava/lang/String;Ljava/lang/String;)I
        //    22: pop            
        //    23: aload           6
        //    25: aconst_null    
        //    26: getstatic       com/netflix/mediaclient/android/app/CommonStatus.NOT_VALID:Lcom/netflix/mediaclient/android/app/NetflixImmutableStatus;
        //    29: invokeinterface com/netflix/mediaclient/service/browse/BrowseAgentCallback.onVideosFetched:(Ljava/util/List;Lcom/netflix/mediaclient/android/app/Status;)V
        //    34: return         
        //    35: aload           7
        //    37: getfield        com/netflix/mediaclient/util/DataUtil$StringPair.first:Ljava/lang/Object;
        //    40: checkcast       Ljava/lang/String;
        //    43: aload_1        
        //    44: invokeinterface com/netflix/mediaclient/servicemgr/interface_/LoMo.getId:()Ljava/lang/String;
        //    49: invokestatic    com/netflix/mediaclient/util/StringUtils.safeEquals:(Ljava/lang/String;Ljava/lang/String;)Z
        //    52: ifeq            93
        //    55: getstatic       com/netflix/mediaclient/service/falkor/Falkor.ENABLE_VERBOSE_LOGGING:Z
        //    58: ifeq            70
        //    61: ldc             "CachedModelProxy"
        //    63: ldc_w           "Requested IQ lomo ID and cached IQ lomo ID still match"
        //    66: invokestatic    com/netflix/mediaclient/Log.v:(Ljava/lang/String;Ljava/lang/String;)I
        //    69: pop            
        //    70: aload_0        
        //    71: new             new            !!! ERROR
        //    74: dup            
        //    75: aload_0        
        //    76: aload_1        
        //    77: iload_2        
        //    78: iload_3        
        //    79: iload           4
        //    81: iload           5
        //    83: iconst_0       
        //    84: aload           6
        //    86: invokespecial   invokespecial  !!! ERROR
        //    89: invokespecial   com/netflix/falkor/CachedModelProxy.launchTask:(Ljava/lang/Runnable;)V
        //    92: return         
        //    93: invokestatic    com/netflix/mediaclient/Log.isLoggable:()Z
        //    96: ifeq            156
        //    99: ldc             "CachedModelProxy"
        //   101: new             Ljava/lang/StringBuilder;
        //   104: dup            
        //   105: invokespecial   java/lang/StringBuilder.<init>:()V
        //   108: ldc_w           "Requested IQ videos for lomo id: "
        //   111: invokevirtual   java/lang/StringBuilder.append:(Ljava/lang/String;)Ljava/lang/StringBuilder;
        //   114: aload_1        
        //   115: invokeinterface com/netflix/mediaclient/servicemgr/interface_/LoMo.getId:()Ljava/lang/String;
        //   120: invokevirtual   java/lang/StringBuilder.append:(Ljava/lang/String;)Ljava/lang/StringBuilder;
        //   123: ldc_w           " but cache IQ lomo id is: "
        //   126: invokevirtual   java/lang/StringBuilder.append:(Ljava/lang/String;)Ljava/lang/StringBuilder;
        //   129: aload           7
        //   131: getfield        com/netflix/mediaclient/util/DataUtil$StringPair.first:Ljava/lang/Object;
        //   134: checkcast       Ljava/lang/String;
        //   137: invokevirtual   java/lang/StringBuilder.append:(Ljava/lang/String;)Ljava/lang/StringBuilder;
        //   140: invokevirtual   java/lang/StringBuilder.toString:()Ljava/lang/String;
        //   143: invokestatic    com/netflix/mediaclient/Log.v:(Ljava/lang/String;Ljava/lang/String;)I
        //   146: pop            
        //   147: ldc             "CachedModelProxy"
        //   149: ldc_w           "Updating existing lomo IQ id to cache id value"
        //   152: invokestatic    com/netflix/mediaclient/Log.d:(Ljava/lang/String;Ljava/lang/String;)I
        //   155: pop            
        //   156: aload_1        
        //   157: aload           7
        //   159: getfield        com/netflix/mediaclient/util/DataUtil$StringPair.first:Ljava/lang/Object;
        //   162: checkcast       Ljava/lang/String;
        //   165: invokeinterface com/netflix/mediaclient/servicemgr/interface_/LoMo.setId:(Ljava/lang/String;)V
        //   170: goto            70
        // 
        // The error that occurred was:
        // 
        // java.lang.IllegalArgumentException: Argument 'typeArguments' must not have any null elements.
        //     at com.strobel.core.VerifyArgument.noNullElementsAndNotEmpty(VerifyArgument.java:145)
        //     at com.strobel.assembler.metadata.CoreMetadataFactory$UnresolvedType.makeGenericType(CoreMetadataFactory.java:570)
        //     at com.strobel.assembler.metadata.CoreMetadataFactory.makeParameterizedType(CoreMetadataFactory.java:156)
        //     at com.strobel.assembler.metadata.signatures.Reifier.visitClassTypeSignature(Reifier.java:125)
        //     at com.strobel.assembler.metadata.signatures.ClassTypeSignature.accept(ClassTypeSignature.java:46)
        //     at com.strobel.assembler.metadata.MetadataParser.parseClassSignature(MetadataParser.java:394)
        //     at com.strobel.assembler.metadata.ClassFileReader.populateBaseTypes(ClassFileReader.java:665)
        //     at com.strobel.assembler.metadata.ClassFileReader.readClass(ClassFileReader.java:438)
        //     at com.strobel.assembler.metadata.ClassFileReader.readClass(ClassFileReader.java:366)
        //     at com.strobel.assembler.metadata.MetadataSystem.resolveType(MetadataSystem.java:124)
        //     at com.strobel.decompiler.NoRetryMetadataSystem.resolveType(DecompilerDriver.java:463)
        //     at com.strobel.assembler.metadata.MetadataSystem.resolveCore(MetadataSystem.java:76)
        //     at com.strobel.assembler.metadata.MetadataResolver.resolve(MetadataResolver.java:104)
        //     at com.strobel.assembler.metadata.CoreMetadataFactory$UnresolvedType.resolve(CoreMetadataFactory.java:589)
        //     at com.strobel.assembler.metadata.MetadataResolver.resolve(MetadataResolver.java:128)
        //     at com.strobel.assembler.metadata.CoreMetadataFactory$UnresolvedType.resolve(CoreMetadataFactory.java:599)
        //     at com.strobel.assembler.metadata.MethodReference.resolve(MethodReference.java:172)
        //     at com.strobel.decompiler.ast.TypeAnalysis.inferCall(TypeAnalysis.java:2428)
        //     at com.strobel.decompiler.ast.TypeAnalysis.doInferTypeForExpression(TypeAnalysis.java:1029)
        //     at com.strobel.decompiler.ast.TypeAnalysis.inferTypeForExpression(TypeAnalysis.java:803)
        //     at com.strobel.decompiler.ast.TypeAnalysis.runInference(TypeAnalysis.java:672)
        //     at com.strobel.decompiler.ast.TypeAnalysis.runInference(TypeAnalysis.java:655)
        //     at com.strobel.decompiler.ast.TypeAnalysis.runInference(TypeAnalysis.java:365)
        //     at com.strobel.decompiler.ast.TypeAnalysis.run(TypeAnalysis.java:96)
        //     at com.strobel.decompiler.ast.AstOptimizer.optimize(AstOptimizer.java:109)
        //     at com.strobel.decompiler.ast.AstOptimizer.optimize(AstOptimizer.java:42)
        //     at com.strobel.decompiler.languages.java.ast.AstMethodBodyBuilder.createMethodBody(AstMethodBodyBuilder.java:214)
        //     at com.strobel.decompiler.languages.java.ast.AstMethodBodyBuilder.createMethodBody(AstMethodBodyBuilder.java:99)
        //     at com.strobel.decompiler.languages.java.ast.AstBuilder.createMethodBody(AstBuilder.java:757)
        //     at com.strobel.decompiler.languages.java.ast.AstBuilder.createMethod(AstBuilder.java:655)
        //     at com.strobel.decompiler.languages.java.ast.AstBuilder.addTypeMembers(AstBuilder.java:532)
        //     at com.strobel.decompiler.languages.java.ast.AstBuilder.createTypeCore(AstBuilder.java:499)
        //     at com.strobel.decompiler.languages.java.ast.AstBuilder.createTypeNoCache(AstBuilder.java:141)
        //     at com.strobel.decompiler.languages.java.ast.AstBuilder.createType(AstBuilder.java:130)
        //     at com.strobel.decompiler.languages.java.ast.AstBuilder.addType(AstBuilder.java:105)
        //     at com.strobel.decompiler.languages.java.JavaLanguage.buildAst(JavaLanguage.java:71)
        //     at com.strobel.decompiler.languages.java.JavaLanguage.decompileType(JavaLanguage.java:59)
        //     at com.strobel.decompiler.DecompilerDriver.decompileType(DecompilerDriver.java:317)
        //     at com.strobel.decompiler.DecompilerDriver.decompileJar(DecompilerDriver.java:238)
        //     at com.strobel.decompiler.DecompilerDriver.main(DecompilerDriver.java:138)
        // 
        throw new IllegalStateException("An error occurred while decompiling this method.");
    }
    
    public void fetchInteractiveVideoMoments(final VideoType p0, final String p1, final BrowseAgentCallback p2) {
        // 
        // This method could not be decompiled.
        // 
        // Original Bytecode:
        // 
        //     0: aload_0        
        //     1: new             new            !!! ERROR
        //     4: dup            
        //     5: aload_0        
        //     6: aload_1        
        //     7: aload_2        
        //     8: aload_3        
        //     9: invokespecial   invokespecial  !!! ERROR
        //    12: invokespecial   com/netflix/falkor/CachedModelProxy.launchTask:(Ljava/lang/Runnable;)V
        //    15: return         
        // 
        // The error that occurred was:
        // 
        // java.lang.IllegalArgumentException: Argument 'typeArguments' must not have any null elements.
        //     at com.strobel.core.VerifyArgument.noNullElementsAndNotEmpty(VerifyArgument.java:145)
        //     at com.strobel.assembler.metadata.CoreMetadataFactory$UnresolvedType.makeGenericType(CoreMetadataFactory.java:570)
        //     at com.strobel.assembler.metadata.CoreMetadataFactory.makeParameterizedType(CoreMetadataFactory.java:156)
        //     at com.strobel.assembler.metadata.signatures.Reifier.visitClassTypeSignature(Reifier.java:125)
        //     at com.strobel.assembler.metadata.signatures.ClassTypeSignature.accept(ClassTypeSignature.java:46)
        //     at com.strobel.assembler.metadata.MetadataParser.parseClassSignature(MetadataParser.java:394)
        //     at com.strobel.assembler.metadata.ClassFileReader.populateBaseTypes(ClassFileReader.java:665)
        //     at com.strobel.assembler.metadata.ClassFileReader.readClass(ClassFileReader.java:438)
        //     at com.strobel.assembler.metadata.ClassFileReader.readClass(ClassFileReader.java:366)
        //     at com.strobel.assembler.metadata.MetadataSystem.resolveType(MetadataSystem.java:124)
        //     at com.strobel.decompiler.NoRetryMetadataSystem.resolveType(DecompilerDriver.java:463)
        //     at com.strobel.assembler.metadata.MetadataSystem.resolveCore(MetadataSystem.java:76)
        //     at com.strobel.assembler.metadata.MetadataResolver.resolve(MetadataResolver.java:104)
        //     at com.strobel.assembler.metadata.CoreMetadataFactory$UnresolvedType.resolve(CoreMetadataFactory.java:589)
        //     at com.strobel.assembler.metadata.MetadataResolver.resolve(MetadataResolver.java:128)
        //     at com.strobel.assembler.metadata.CoreMetadataFactory$UnresolvedType.resolve(CoreMetadataFactory.java:599)
        //     at com.strobel.assembler.metadata.MethodReference.resolve(MethodReference.java:172)
        //     at com.strobel.decompiler.ast.TypeAnalysis.inferCall(TypeAnalysis.java:2428)
        //     at com.strobel.decompiler.ast.TypeAnalysis.doInferTypeForExpression(TypeAnalysis.java:1029)
        //     at com.strobel.decompiler.ast.TypeAnalysis.inferTypeForExpression(TypeAnalysis.java:803)
        //     at com.strobel.decompiler.ast.TypeAnalysis.runInference(TypeAnalysis.java:672)
        //     at com.strobel.decompiler.ast.TypeAnalysis.runInference(TypeAnalysis.java:655)
        //     at com.strobel.decompiler.ast.TypeAnalysis.runInference(TypeAnalysis.java:365)
        //     at com.strobel.decompiler.ast.TypeAnalysis.run(TypeAnalysis.java:96)
        //     at com.strobel.decompiler.ast.AstOptimizer.optimize(AstOptimizer.java:109)
        //     at com.strobel.decompiler.ast.AstOptimizer.optimize(AstOptimizer.java:42)
        //     at com.strobel.decompiler.languages.java.ast.AstMethodBodyBuilder.createMethodBody(AstMethodBodyBuilder.java:214)
        //     at com.strobel.decompiler.languages.java.ast.AstMethodBodyBuilder.createMethodBody(AstMethodBodyBuilder.java:99)
        //     at com.strobel.decompiler.languages.java.ast.AstBuilder.createMethodBody(AstBuilder.java:757)
        //     at com.strobel.decompiler.languages.java.ast.AstBuilder.createMethod(AstBuilder.java:655)
        //     at com.strobel.decompiler.languages.java.ast.AstBuilder.addTypeMembers(AstBuilder.java:532)
        //     at com.strobel.decompiler.languages.java.ast.AstBuilder.createTypeCore(AstBuilder.java:499)
        //     at com.strobel.decompiler.languages.java.ast.AstBuilder.createTypeNoCache(AstBuilder.java:141)
        //     at com.strobel.decompiler.languages.java.ast.AstBuilder.createType(AstBuilder.java:130)
        //     at com.strobel.decompiler.languages.java.ast.AstBuilder.addType(AstBuilder.java:105)
        //     at com.strobel.decompiler.languages.java.JavaLanguage.buildAst(JavaLanguage.java:71)
        //     at com.strobel.decompiler.languages.java.JavaLanguage.decompileType(JavaLanguage.java:59)
        //     at com.strobel.decompiler.DecompilerDriver.decompileType(DecompilerDriver.java:317)
        //     at com.strobel.decompiler.DecompilerDriver.decompileJar(DecompilerDriver.java:238)
        //     at com.strobel.decompiler.DecompilerDriver.main(DecompilerDriver.java:138)
        // 
        throw new IllegalStateException("An error occurred while decompiling this method.");
    }
    
    public void fetchKidsCharacterDetails(final String p0, final BrowseAgentCallback p1) {
        // 
        // This method could not be decompiled.
        // 
        // Original Bytecode:
        // 
        //     0: aload_0        
        //     1: new             new            !!! ERROR
        //     4: dup            
        //     5: aload_0        
        //     6: aload_1        
        //     7: aload_2        
        //     8: invokespecial   invokespecial  !!! ERROR
        //    11: invokespecial   com/netflix/falkor/CachedModelProxy.launchTask:(Ljava/lang/Runnable;)V
        //    14: return         
        // 
        // The error that occurred was:
        // 
        // java.lang.IllegalArgumentException: Argument 'typeArguments' must not have any null elements.
        //     at com.strobel.core.VerifyArgument.noNullElementsAndNotEmpty(VerifyArgument.java:145)
        //     at com.strobel.assembler.metadata.CoreMetadataFactory$UnresolvedType.makeGenericType(CoreMetadataFactory.java:570)
        //     at com.strobel.assembler.metadata.CoreMetadataFactory.makeParameterizedType(CoreMetadataFactory.java:156)
        //     at com.strobel.assembler.metadata.signatures.Reifier.visitClassTypeSignature(Reifier.java:125)
        //     at com.strobel.assembler.metadata.signatures.ClassTypeSignature.accept(ClassTypeSignature.java:46)
        //     at com.strobel.assembler.metadata.MetadataParser.parseClassSignature(MetadataParser.java:394)
        //     at com.strobel.assembler.metadata.ClassFileReader.populateBaseTypes(ClassFileReader.java:665)
        //     at com.strobel.assembler.metadata.ClassFileReader.readClass(ClassFileReader.java:438)
        //     at com.strobel.assembler.metadata.ClassFileReader.readClass(ClassFileReader.java:366)
        //     at com.strobel.assembler.metadata.MetadataSystem.resolveType(MetadataSystem.java:124)
        //     at com.strobel.decompiler.NoRetryMetadataSystem.resolveType(DecompilerDriver.java:463)
        //     at com.strobel.assembler.metadata.MetadataSystem.resolveCore(MetadataSystem.java:76)
        //     at com.strobel.assembler.metadata.MetadataResolver.resolve(MetadataResolver.java:104)
        //     at com.strobel.assembler.metadata.CoreMetadataFactory$UnresolvedType.resolve(CoreMetadataFactory.java:589)
        //     at com.strobel.assembler.metadata.MetadataResolver.resolve(MetadataResolver.java:128)
        //     at com.strobel.assembler.metadata.CoreMetadataFactory$UnresolvedType.resolve(CoreMetadataFactory.java:599)
        //     at com.strobel.assembler.metadata.MethodReference.resolve(MethodReference.java:172)
        //     at com.strobel.decompiler.ast.TypeAnalysis.inferCall(TypeAnalysis.java:2428)
        //     at com.strobel.decompiler.ast.TypeAnalysis.doInferTypeForExpression(TypeAnalysis.java:1029)
        //     at com.strobel.decompiler.ast.TypeAnalysis.inferTypeForExpression(TypeAnalysis.java:803)
        //     at com.strobel.decompiler.ast.TypeAnalysis.runInference(TypeAnalysis.java:672)
        //     at com.strobel.decompiler.ast.TypeAnalysis.runInference(TypeAnalysis.java:655)
        //     at com.strobel.decompiler.ast.TypeAnalysis.runInference(TypeAnalysis.java:365)
        //     at com.strobel.decompiler.ast.TypeAnalysis.run(TypeAnalysis.java:96)
        //     at com.strobel.decompiler.ast.AstOptimizer.optimize(AstOptimizer.java:109)
        //     at com.strobel.decompiler.ast.AstOptimizer.optimize(AstOptimizer.java:42)
        //     at com.strobel.decompiler.languages.java.ast.AstMethodBodyBuilder.createMethodBody(AstMethodBodyBuilder.java:214)
        //     at com.strobel.decompiler.languages.java.ast.AstMethodBodyBuilder.createMethodBody(AstMethodBodyBuilder.java:99)
        //     at com.strobel.decompiler.languages.java.ast.AstBuilder.createMethodBody(AstBuilder.java:757)
        //     at com.strobel.decompiler.languages.java.ast.AstBuilder.createMethod(AstBuilder.java:655)
        //     at com.strobel.decompiler.languages.java.ast.AstBuilder.addTypeMembers(AstBuilder.java:532)
        //     at com.strobel.decompiler.languages.java.ast.AstBuilder.createTypeCore(AstBuilder.java:499)
        //     at com.strobel.decompiler.languages.java.ast.AstBuilder.createTypeNoCache(AstBuilder.java:141)
        //     at com.strobel.decompiler.languages.java.ast.AstBuilder.createType(AstBuilder.java:130)
        //     at com.strobel.decompiler.languages.java.ast.AstBuilder.addType(AstBuilder.java:105)
        //     at com.strobel.decompiler.languages.java.JavaLanguage.buildAst(JavaLanguage.java:71)
        //     at com.strobel.decompiler.languages.java.JavaLanguage.decompileType(JavaLanguage.java:59)
        //     at com.strobel.decompiler.DecompilerDriver.decompileType(DecompilerDriver.java:317)
        //     at com.strobel.decompiler.DecompilerDriver.decompileJar(DecompilerDriver.java:238)
        //     at com.strobel.decompiler.DecompilerDriver.main(DecompilerDriver.java:138)
        // 
        throw new IllegalStateException("An error occurred while decompiling this method.");
    }
    
    public void fetchLoMos(final int p0, final int p1, final BrowseAgentCallback p2) {
        // 
        // This method could not be decompiled.
        // 
        // Original Bytecode:
        // 
        //     0: aload_0        
        //     1: new             new            !!! ERROR
        //     4: dup            
        //     5: aload_0        
        //     6: iload_1        
        //     7: iload_2        
        //     8: aload_3        
        //     9: invokespecial   invokespecial  !!! ERROR
        //    12: invokespecial   com/netflix/falkor/CachedModelProxy.launchTask:(Ljava/lang/Runnable;)V
        //    15: return         
        // 
        // The error that occurred was:
        // 
        // java.lang.IllegalArgumentException: Argument 'typeArguments' must not have any null elements.
        //     at com.strobel.core.VerifyArgument.noNullElementsAndNotEmpty(VerifyArgument.java:145)
        //     at com.strobel.assembler.metadata.CoreMetadataFactory$UnresolvedType.makeGenericType(CoreMetadataFactory.java:570)
        //     at com.strobel.assembler.metadata.CoreMetadataFactory.makeParameterizedType(CoreMetadataFactory.java:156)
        //     at com.strobel.assembler.metadata.signatures.Reifier.visitClassTypeSignature(Reifier.java:125)
        //     at com.strobel.assembler.metadata.signatures.ClassTypeSignature.accept(ClassTypeSignature.java:46)
        //     at com.strobel.assembler.metadata.MetadataParser.parseClassSignature(MetadataParser.java:394)
        //     at com.strobel.assembler.metadata.ClassFileReader.populateBaseTypes(ClassFileReader.java:665)
        //     at com.strobel.assembler.metadata.ClassFileReader.readClass(ClassFileReader.java:438)
        //     at com.strobel.assembler.metadata.ClassFileReader.readClass(ClassFileReader.java:366)
        //     at com.strobel.assembler.metadata.MetadataSystem.resolveType(MetadataSystem.java:124)
        //     at com.strobel.decompiler.NoRetryMetadataSystem.resolveType(DecompilerDriver.java:463)
        //     at com.strobel.assembler.metadata.MetadataSystem.resolveCore(MetadataSystem.java:76)
        //     at com.strobel.assembler.metadata.MetadataResolver.resolve(MetadataResolver.java:104)
        //     at com.strobel.assembler.metadata.CoreMetadataFactory$UnresolvedType.resolve(CoreMetadataFactory.java:589)
        //     at com.strobel.assembler.metadata.MetadataResolver.resolve(MetadataResolver.java:128)
        //     at com.strobel.assembler.metadata.CoreMetadataFactory$UnresolvedType.resolve(CoreMetadataFactory.java:599)
        //     at com.strobel.assembler.metadata.MethodReference.resolve(MethodReference.java:172)
        //     at com.strobel.decompiler.ast.TypeAnalysis.inferCall(TypeAnalysis.java:2428)
        //     at com.strobel.decompiler.ast.TypeAnalysis.doInferTypeForExpression(TypeAnalysis.java:1029)
        //     at com.strobel.decompiler.ast.TypeAnalysis.inferTypeForExpression(TypeAnalysis.java:803)
        //     at com.strobel.decompiler.ast.TypeAnalysis.runInference(TypeAnalysis.java:672)
        //     at com.strobel.decompiler.ast.TypeAnalysis.runInference(TypeAnalysis.java:655)
        //     at com.strobel.decompiler.ast.TypeAnalysis.runInference(TypeAnalysis.java:365)
        //     at com.strobel.decompiler.ast.TypeAnalysis.run(TypeAnalysis.java:96)
        //     at com.strobel.decompiler.ast.AstOptimizer.optimize(AstOptimizer.java:109)
        //     at com.strobel.decompiler.ast.AstOptimizer.optimize(AstOptimizer.java:42)
        //     at com.strobel.decompiler.languages.java.ast.AstMethodBodyBuilder.createMethodBody(AstMethodBodyBuilder.java:214)
        //     at com.strobel.decompiler.languages.java.ast.AstMethodBodyBuilder.createMethodBody(AstMethodBodyBuilder.java:99)
        //     at com.strobel.decompiler.languages.java.ast.AstBuilder.createMethodBody(AstBuilder.java:757)
        //     at com.strobel.decompiler.languages.java.ast.AstBuilder.createMethod(AstBuilder.java:655)
        //     at com.strobel.decompiler.languages.java.ast.AstBuilder.addTypeMembers(AstBuilder.java:532)
        //     at com.strobel.decompiler.languages.java.ast.AstBuilder.createTypeCore(AstBuilder.java:499)
        //     at com.strobel.decompiler.languages.java.ast.AstBuilder.createTypeNoCache(AstBuilder.java:141)
        //     at com.strobel.decompiler.languages.java.ast.AstBuilder.createType(AstBuilder.java:130)
        //     at com.strobel.decompiler.languages.java.ast.AstBuilder.addType(AstBuilder.java:105)
        //     at com.strobel.decompiler.languages.java.JavaLanguage.buildAst(JavaLanguage.java:71)
        //     at com.strobel.decompiler.languages.java.JavaLanguage.decompileType(JavaLanguage.java:59)
        //     at com.strobel.decompiler.DecompilerDriver.decompileType(DecompilerDriver.java:317)
        //     at com.strobel.decompiler.DecompilerDriver.decompileJar(DecompilerDriver.java:238)
        //     at com.strobel.decompiler.DecompilerDriver.main(DecompilerDriver.java:138)
        // 
        throw new IllegalStateException("An error occurred while decompiling this method.");
    }
    
    public void fetchMovieDetails(final String p0, final String p1, final BrowseAgentCallback p2) {
        // 
        // This method could not be decompiled.
        // 
        // Original Bytecode:
        // 
        //     0: aload_0        
        //     1: new             new            !!! ERROR
        //     4: dup            
        //     5: aload_0        
        //     6: aload_1        
        //     7: aload_2        
        //     8: aload_3        
        //     9: invokespecial   invokespecial  !!! ERROR
        //    12: invokespecial   com/netflix/falkor/CachedModelProxy.launchTask:(Ljava/lang/Runnable;)V
        //    15: return         
        // 
        // The error that occurred was:
        // 
        // java.lang.IllegalArgumentException: Argument 'typeArguments' must not have any null elements.
        //     at com.strobel.core.VerifyArgument.noNullElementsAndNotEmpty(VerifyArgument.java:145)
        //     at com.strobel.assembler.metadata.CoreMetadataFactory$UnresolvedType.makeGenericType(CoreMetadataFactory.java:570)
        //     at com.strobel.assembler.metadata.CoreMetadataFactory.makeParameterizedType(CoreMetadataFactory.java:156)
        //     at com.strobel.assembler.metadata.signatures.Reifier.visitClassTypeSignature(Reifier.java:125)
        //     at com.strobel.assembler.metadata.signatures.ClassTypeSignature.accept(ClassTypeSignature.java:46)
        //     at com.strobel.assembler.metadata.MetadataParser.parseClassSignature(MetadataParser.java:394)
        //     at com.strobel.assembler.metadata.ClassFileReader.populateBaseTypes(ClassFileReader.java:665)
        //     at com.strobel.assembler.metadata.ClassFileReader.readClass(ClassFileReader.java:438)
        //     at com.strobel.assembler.metadata.ClassFileReader.readClass(ClassFileReader.java:366)
        //     at com.strobel.assembler.metadata.MetadataSystem.resolveType(MetadataSystem.java:124)
        //     at com.strobel.decompiler.NoRetryMetadataSystem.resolveType(DecompilerDriver.java:463)
        //     at com.strobel.assembler.metadata.MetadataSystem.resolveCore(MetadataSystem.java:76)
        //     at com.strobel.assembler.metadata.MetadataResolver.resolve(MetadataResolver.java:104)
        //     at com.strobel.assembler.metadata.CoreMetadataFactory$UnresolvedType.resolve(CoreMetadataFactory.java:589)
        //     at com.strobel.assembler.metadata.MetadataResolver.resolve(MetadataResolver.java:128)
        //     at com.strobel.assembler.metadata.CoreMetadataFactory$UnresolvedType.resolve(CoreMetadataFactory.java:599)
        //     at com.strobel.assembler.metadata.MethodReference.resolve(MethodReference.java:172)
        //     at com.strobel.decompiler.ast.TypeAnalysis.inferCall(TypeAnalysis.java:2428)
        //     at com.strobel.decompiler.ast.TypeAnalysis.doInferTypeForExpression(TypeAnalysis.java:1029)
        //     at com.strobel.decompiler.ast.TypeAnalysis.inferTypeForExpression(TypeAnalysis.java:803)
        //     at com.strobel.decompiler.ast.TypeAnalysis.runInference(TypeAnalysis.java:672)
        //     at com.strobel.decompiler.ast.TypeAnalysis.runInference(TypeAnalysis.java:655)
        //     at com.strobel.decompiler.ast.TypeAnalysis.runInference(TypeAnalysis.java:365)
        //     at com.strobel.decompiler.ast.TypeAnalysis.run(TypeAnalysis.java:96)
        //     at com.strobel.decompiler.ast.AstOptimizer.optimize(AstOptimizer.java:109)
        //     at com.strobel.decompiler.ast.AstOptimizer.optimize(AstOptimizer.java:42)
        //     at com.strobel.decompiler.languages.java.ast.AstMethodBodyBuilder.createMethodBody(AstMethodBodyBuilder.java:214)
        //     at com.strobel.decompiler.languages.java.ast.AstMethodBodyBuilder.createMethodBody(AstMethodBodyBuilder.java:99)
        //     at com.strobel.decompiler.languages.java.ast.AstBuilder.createMethodBody(AstBuilder.java:757)
        //     at com.strobel.decompiler.languages.java.ast.AstBuilder.createMethod(AstBuilder.java:655)
        //     at com.strobel.decompiler.languages.java.ast.AstBuilder.addTypeMembers(AstBuilder.java:532)
        //     at com.strobel.decompiler.languages.java.ast.AstBuilder.createTypeCore(AstBuilder.java:499)
        //     at com.strobel.decompiler.languages.java.ast.AstBuilder.createTypeNoCache(AstBuilder.java:141)
        //     at com.strobel.decompiler.languages.java.ast.AstBuilder.createType(AstBuilder.java:130)
        //     at com.strobel.decompiler.languages.java.ast.AstBuilder.addType(AstBuilder.java:105)
        //     at com.strobel.decompiler.languages.java.JavaLanguage.buildAst(JavaLanguage.java:71)
        //     at com.strobel.decompiler.languages.java.JavaLanguage.decompileType(JavaLanguage.java:59)
        //     at com.strobel.decompiler.DecompilerDriver.decompileType(DecompilerDriver.java:317)
        //     at com.strobel.decompiler.DecompilerDriver.decompileJar(DecompilerDriver.java:238)
        //     at com.strobel.decompiler.DecompilerDriver.main(DecompilerDriver.java:138)
        // 
        throw new IllegalStateException("An error occurred while decompiling this method.");
    }
    
    public void fetchNonMemberVideos(final int p0, final boolean p1, final BrowseAgentCallback p2) {
        // 
        // This method could not be decompiled.
        // 
        // Original Bytecode:
        // 
        //     0: aload_0        
        //     1: new             new            !!! ERROR
        //     4: dup            
        //     5: aload_0        
        //     6: iload_1        
        //     7: iload_2        
        //     8: aload_3        
        //     9: invokespecial   invokespecial  !!! ERROR
        //    12: invokespecial   com/netflix/falkor/CachedModelProxy.launchTask:(Ljava/lang/Runnable;)V
        //    15: return         
        // 
        // The error that occurred was:
        // 
        // java.lang.IllegalArgumentException: Argument 'typeArguments' must not have any null elements.
        //     at com.strobel.core.VerifyArgument.noNullElementsAndNotEmpty(VerifyArgument.java:145)
        //     at com.strobel.assembler.metadata.CoreMetadataFactory$UnresolvedType.makeGenericType(CoreMetadataFactory.java:570)
        //     at com.strobel.assembler.metadata.CoreMetadataFactory.makeParameterizedType(CoreMetadataFactory.java:156)
        //     at com.strobel.assembler.metadata.signatures.Reifier.visitClassTypeSignature(Reifier.java:125)
        //     at com.strobel.assembler.metadata.signatures.ClassTypeSignature.accept(ClassTypeSignature.java:46)
        //     at com.strobel.assembler.metadata.MetadataParser.parseClassSignature(MetadataParser.java:394)
        //     at com.strobel.assembler.metadata.ClassFileReader.populateBaseTypes(ClassFileReader.java:665)
        //     at com.strobel.assembler.metadata.ClassFileReader.readClass(ClassFileReader.java:438)
        //     at com.strobel.assembler.metadata.ClassFileReader.readClass(ClassFileReader.java:366)
        //     at com.strobel.assembler.metadata.MetadataSystem.resolveType(MetadataSystem.java:124)
        //     at com.strobel.decompiler.NoRetryMetadataSystem.resolveType(DecompilerDriver.java:463)
        //     at com.strobel.assembler.metadata.MetadataSystem.resolveCore(MetadataSystem.java:76)
        //     at com.strobel.assembler.metadata.MetadataResolver.resolve(MetadataResolver.java:104)
        //     at com.strobel.assembler.metadata.CoreMetadataFactory$UnresolvedType.resolve(CoreMetadataFactory.java:589)
        //     at com.strobel.assembler.metadata.MetadataResolver.resolve(MetadataResolver.java:128)
        //     at com.strobel.assembler.metadata.CoreMetadataFactory$UnresolvedType.resolve(CoreMetadataFactory.java:599)
        //     at com.strobel.assembler.metadata.MethodReference.resolve(MethodReference.java:172)
        //     at com.strobel.decompiler.ast.TypeAnalysis.inferCall(TypeAnalysis.java:2428)
        //     at com.strobel.decompiler.ast.TypeAnalysis.doInferTypeForExpression(TypeAnalysis.java:1029)
        //     at com.strobel.decompiler.ast.TypeAnalysis.inferTypeForExpression(TypeAnalysis.java:803)
        //     at com.strobel.decompiler.ast.TypeAnalysis.runInference(TypeAnalysis.java:672)
        //     at com.strobel.decompiler.ast.TypeAnalysis.runInference(TypeAnalysis.java:655)
        //     at com.strobel.decompiler.ast.TypeAnalysis.runInference(TypeAnalysis.java:365)
        //     at com.strobel.decompiler.ast.TypeAnalysis.run(TypeAnalysis.java:96)
        //     at com.strobel.decompiler.ast.AstOptimizer.optimize(AstOptimizer.java:109)
        //     at com.strobel.decompiler.ast.AstOptimizer.optimize(AstOptimizer.java:42)
        //     at com.strobel.decompiler.languages.java.ast.AstMethodBodyBuilder.createMethodBody(AstMethodBodyBuilder.java:214)
        //     at com.strobel.decompiler.languages.java.ast.AstMethodBodyBuilder.createMethodBody(AstMethodBodyBuilder.java:99)
        //     at com.strobel.decompiler.languages.java.ast.AstBuilder.createMethodBody(AstBuilder.java:757)
        //     at com.strobel.decompiler.languages.java.ast.AstBuilder.createMethod(AstBuilder.java:655)
        //     at com.strobel.decompiler.languages.java.ast.AstBuilder.addTypeMembers(AstBuilder.java:532)
        //     at com.strobel.decompiler.languages.java.ast.AstBuilder.createTypeCore(AstBuilder.java:499)
        //     at com.strobel.decompiler.languages.java.ast.AstBuilder.createTypeNoCache(AstBuilder.java:141)
        //     at com.strobel.decompiler.languages.java.ast.AstBuilder.createType(AstBuilder.java:130)
        //     at com.strobel.decompiler.languages.java.ast.AstBuilder.addType(AstBuilder.java:105)
        //     at com.strobel.decompiler.languages.java.JavaLanguage.buildAst(JavaLanguage.java:71)
        //     at com.strobel.decompiler.languages.java.JavaLanguage.decompileType(JavaLanguage.java:59)
        //     at com.strobel.decompiler.DecompilerDriver.decompileType(DecompilerDriver.java:317)
        //     at com.strobel.decompiler.DecompilerDriver.decompileJar(DecompilerDriver.java:238)
        //     at com.strobel.decompiler.DecompilerDriver.main(DecompilerDriver.java:138)
        // 
        throw new IllegalStateException("An error occurred while decompiling this method.");
    }
    
    public void fetchNotifications(final int p0, final int p1, final boolean p2, final BrowseAgentCallback p3) {
        // 
        // This method could not be decompiled.
        // 
        // Original Bytecode:
        // 
        //     0: aload_0        
        //     1: new             new            !!! ERROR
        //     4: dup            
        //     5: aload_0        
        //     6: iload_1        
        //     7: iload_2        
        //     8: iload_3        
        //     9: aload           4
        //    11: invokespecial   invokespecial  !!! ERROR
        //    14: invokespecial   com/netflix/falkor/CachedModelProxy.launchTask:(Ljava/lang/Runnable;)V
        //    17: return         
        // 
        // The error that occurred was:
        // 
        // java.lang.IllegalArgumentException: Argument 'typeArguments' must not have any null elements.
        //     at com.strobel.core.VerifyArgument.noNullElementsAndNotEmpty(VerifyArgument.java:145)
        //     at com.strobel.assembler.metadata.CoreMetadataFactory$UnresolvedType.makeGenericType(CoreMetadataFactory.java:570)
        //     at com.strobel.assembler.metadata.CoreMetadataFactory.makeParameterizedType(CoreMetadataFactory.java:156)
        //     at com.strobel.assembler.metadata.signatures.Reifier.visitClassTypeSignature(Reifier.java:125)
        //     at com.strobel.assembler.metadata.signatures.ClassTypeSignature.accept(ClassTypeSignature.java:46)
        //     at com.strobel.assembler.metadata.MetadataParser.parseClassSignature(MetadataParser.java:394)
        //     at com.strobel.assembler.metadata.ClassFileReader.populateBaseTypes(ClassFileReader.java:665)
        //     at com.strobel.assembler.metadata.ClassFileReader.readClass(ClassFileReader.java:438)
        //     at com.strobel.assembler.metadata.ClassFileReader.readClass(ClassFileReader.java:366)
        //     at com.strobel.assembler.metadata.MetadataSystem.resolveType(MetadataSystem.java:124)
        //     at com.strobel.decompiler.NoRetryMetadataSystem.resolveType(DecompilerDriver.java:463)
        //     at com.strobel.assembler.metadata.MetadataSystem.resolveCore(MetadataSystem.java:76)
        //     at com.strobel.assembler.metadata.MetadataResolver.resolve(MetadataResolver.java:104)
        //     at com.strobel.assembler.metadata.CoreMetadataFactory$UnresolvedType.resolve(CoreMetadataFactory.java:589)
        //     at com.strobel.assembler.metadata.MetadataResolver.resolve(MetadataResolver.java:128)
        //     at com.strobel.assembler.metadata.CoreMetadataFactory$UnresolvedType.resolve(CoreMetadataFactory.java:599)
        //     at com.strobel.assembler.metadata.MethodReference.resolve(MethodReference.java:172)
        //     at com.strobel.decompiler.ast.TypeAnalysis.inferCall(TypeAnalysis.java:2428)
        //     at com.strobel.decompiler.ast.TypeAnalysis.doInferTypeForExpression(TypeAnalysis.java:1029)
        //     at com.strobel.decompiler.ast.TypeAnalysis.inferTypeForExpression(TypeAnalysis.java:803)
        //     at com.strobel.decompiler.ast.TypeAnalysis.runInference(TypeAnalysis.java:672)
        //     at com.strobel.decompiler.ast.TypeAnalysis.runInference(TypeAnalysis.java:655)
        //     at com.strobel.decompiler.ast.TypeAnalysis.runInference(TypeAnalysis.java:365)
        //     at com.strobel.decompiler.ast.TypeAnalysis.run(TypeAnalysis.java:96)
        //     at com.strobel.decompiler.ast.AstOptimizer.optimize(AstOptimizer.java:109)
        //     at com.strobel.decompiler.ast.AstOptimizer.optimize(AstOptimizer.java:42)
        //     at com.strobel.decompiler.languages.java.ast.AstMethodBodyBuilder.createMethodBody(AstMethodBodyBuilder.java:214)
        //     at com.strobel.decompiler.languages.java.ast.AstMethodBodyBuilder.createMethodBody(AstMethodBodyBuilder.java:99)
        //     at com.strobel.decompiler.languages.java.ast.AstBuilder.createMethodBody(AstBuilder.java:757)
        //     at com.strobel.decompiler.languages.java.ast.AstBuilder.createMethod(AstBuilder.java:655)
        //     at com.strobel.decompiler.languages.java.ast.AstBuilder.addTypeMembers(AstBuilder.java:532)
        //     at com.strobel.decompiler.languages.java.ast.AstBuilder.createTypeCore(AstBuilder.java:499)
        //     at com.strobel.decompiler.languages.java.ast.AstBuilder.createTypeNoCache(AstBuilder.java:141)
        //     at com.strobel.decompiler.languages.java.ast.AstBuilder.createType(AstBuilder.java:130)
        //     at com.strobel.decompiler.languages.java.ast.AstBuilder.addType(AstBuilder.java:105)
        //     at com.strobel.decompiler.languages.java.JavaLanguage.buildAst(JavaLanguage.java:71)
        //     at com.strobel.decompiler.languages.java.JavaLanguage.decompileType(JavaLanguage.java:59)
        //     at com.strobel.decompiler.DecompilerDriver.decompileType(DecompilerDriver.java:317)
        //     at com.strobel.decompiler.DecompilerDriver.decompileJar(DecompilerDriver.java:238)
        //     at com.strobel.decompiler.DecompilerDriver.main(DecompilerDriver.java:138)
        // 
        throw new IllegalStateException("An error occurred while decompiling this method.");
    }
    
    public void fetchPostPlayVideos(final String p0, final VideoType p1, final BrowseAgentCallback p2) {
        // 
        // This method could not be decompiled.
        // 
        // Original Bytecode:
        // 
        //     0: aload_0        
        //     1: new             new            !!! ERROR
        //     4: dup            
        //     5: aload_0        
        //     6: aload_1        
        //     7: aload_2        
        //     8: aload_3        
        //     9: invokespecial   invokespecial  !!! ERROR
        //    12: invokespecial   com/netflix/falkor/CachedModelProxy.launchTask:(Ljava/lang/Runnable;)V
        //    15: return         
        // 
        // The error that occurred was:
        // 
        // java.lang.IllegalArgumentException: Argument 'typeArguments' must not have any null elements.
        //     at com.strobel.core.VerifyArgument.noNullElementsAndNotEmpty(VerifyArgument.java:145)
        //     at com.strobel.assembler.metadata.CoreMetadataFactory$UnresolvedType.makeGenericType(CoreMetadataFactory.java:570)
        //     at com.strobel.assembler.metadata.CoreMetadataFactory.makeParameterizedType(CoreMetadataFactory.java:156)
        //     at com.strobel.assembler.metadata.signatures.Reifier.visitClassTypeSignature(Reifier.java:125)
        //     at com.strobel.assembler.metadata.signatures.ClassTypeSignature.accept(ClassTypeSignature.java:46)
        //     at com.strobel.assembler.metadata.MetadataParser.parseClassSignature(MetadataParser.java:394)
        //     at com.strobel.assembler.metadata.ClassFileReader.populateBaseTypes(ClassFileReader.java:665)
        //     at com.strobel.assembler.metadata.ClassFileReader.readClass(ClassFileReader.java:438)
        //     at com.strobel.assembler.metadata.ClassFileReader.readClass(ClassFileReader.java:366)
        //     at com.strobel.assembler.metadata.MetadataSystem.resolveType(MetadataSystem.java:124)
        //     at com.strobel.decompiler.NoRetryMetadataSystem.resolveType(DecompilerDriver.java:463)
        //     at com.strobel.assembler.metadata.MetadataSystem.resolveCore(MetadataSystem.java:76)
        //     at com.strobel.assembler.metadata.MetadataResolver.resolve(MetadataResolver.java:104)
        //     at com.strobel.assembler.metadata.CoreMetadataFactory$UnresolvedType.resolve(CoreMetadataFactory.java:589)
        //     at com.strobel.assembler.metadata.MetadataResolver.resolve(MetadataResolver.java:128)
        //     at com.strobel.assembler.metadata.CoreMetadataFactory$UnresolvedType.resolve(CoreMetadataFactory.java:599)
        //     at com.strobel.assembler.metadata.MethodReference.resolve(MethodReference.java:172)
        //     at com.strobel.decompiler.ast.TypeAnalysis.inferCall(TypeAnalysis.java:2428)
        //     at com.strobel.decompiler.ast.TypeAnalysis.doInferTypeForExpression(TypeAnalysis.java:1029)
        //     at com.strobel.decompiler.ast.TypeAnalysis.inferTypeForExpression(TypeAnalysis.java:803)
        //     at com.strobel.decompiler.ast.TypeAnalysis.runInference(TypeAnalysis.java:672)
        //     at com.strobel.decompiler.ast.TypeAnalysis.runInference(TypeAnalysis.java:655)
        //     at com.strobel.decompiler.ast.TypeAnalysis.runInference(TypeAnalysis.java:365)
        //     at com.strobel.decompiler.ast.TypeAnalysis.run(TypeAnalysis.java:96)
        //     at com.strobel.decompiler.ast.AstOptimizer.optimize(AstOptimizer.java:109)
        //     at com.strobel.decompiler.ast.AstOptimizer.optimize(AstOptimizer.java:42)
        //     at com.strobel.decompiler.languages.java.ast.AstMethodBodyBuilder.createMethodBody(AstMethodBodyBuilder.java:214)
        //     at com.strobel.decompiler.languages.java.ast.AstMethodBodyBuilder.createMethodBody(AstMethodBodyBuilder.java:99)
        //     at com.strobel.decompiler.languages.java.ast.AstBuilder.createMethodBody(AstBuilder.java:757)
        //     at com.strobel.decompiler.languages.java.ast.AstBuilder.createMethod(AstBuilder.java:655)
        //     at com.strobel.decompiler.languages.java.ast.AstBuilder.addTypeMembers(AstBuilder.java:532)
        //     at com.strobel.decompiler.languages.java.ast.AstBuilder.createTypeCore(AstBuilder.java:499)
        //     at com.strobel.decompiler.languages.java.ast.AstBuilder.createTypeNoCache(AstBuilder.java:141)
        //     at com.strobel.decompiler.languages.java.ast.AstBuilder.createType(AstBuilder.java:130)
        //     at com.strobel.decompiler.languages.java.ast.AstBuilder.addType(AstBuilder.java:105)
        //     at com.strobel.decompiler.languages.java.JavaLanguage.buildAst(JavaLanguage.java:71)
        //     at com.strobel.decompiler.languages.java.JavaLanguage.decompileType(JavaLanguage.java:59)
        //     at com.strobel.decompiler.DecompilerDriver.decompileType(DecompilerDriver.java:317)
        //     at com.strobel.decompiler.DecompilerDriver.decompileJar(DecompilerDriver.java:238)
        //     at com.strobel.decompiler.DecompilerDriver.main(DecompilerDriver.java:138)
        // 
        throw new IllegalStateException("An error occurred while decompiling this method.");
    }
    
    public void fetchScenePosition(final VideoType p0, final String p1, final String p2, final BrowseAgentCallback p3) {
        // 
        // This method could not be decompiled.
        // 
        // Original Bytecode:
        // 
        //     0: aload_0        
        //     1: new             new            !!! ERROR
        //     4: dup            
        //     5: aload_0        
        //     6: aload_1        
        //     7: aload_2        
        //     8: aload_3        
        //     9: aload           4
        //    11: invokespecial   invokespecial  !!! ERROR
        //    14: invokespecial   com/netflix/falkor/CachedModelProxy.launchTask:(Ljava/lang/Runnable;)V
        //    17: return         
        // 
        // The error that occurred was:
        // 
        // java.lang.IllegalArgumentException: Argument 'typeArguments' must not have any null elements.
        //     at com.strobel.core.VerifyArgument.noNullElementsAndNotEmpty(VerifyArgument.java:145)
        //     at com.strobel.assembler.metadata.CoreMetadataFactory$UnresolvedType.makeGenericType(CoreMetadataFactory.java:570)
        //     at com.strobel.assembler.metadata.CoreMetadataFactory.makeParameterizedType(CoreMetadataFactory.java:156)
        //     at com.strobel.assembler.metadata.signatures.Reifier.visitClassTypeSignature(Reifier.java:125)
        //     at com.strobel.assembler.metadata.signatures.ClassTypeSignature.accept(ClassTypeSignature.java:46)
        //     at com.strobel.assembler.metadata.MetadataParser.parseClassSignature(MetadataParser.java:394)
        //     at com.strobel.assembler.metadata.ClassFileReader.populateBaseTypes(ClassFileReader.java:665)
        //     at com.strobel.assembler.metadata.ClassFileReader.readClass(ClassFileReader.java:438)
        //     at com.strobel.assembler.metadata.ClassFileReader.readClass(ClassFileReader.java:366)
        //     at com.strobel.assembler.metadata.MetadataSystem.resolveType(MetadataSystem.java:124)
        //     at com.strobel.decompiler.NoRetryMetadataSystem.resolveType(DecompilerDriver.java:463)
        //     at com.strobel.assembler.metadata.MetadataSystem.resolveCore(MetadataSystem.java:76)
        //     at com.strobel.assembler.metadata.MetadataResolver.resolve(MetadataResolver.java:104)
        //     at com.strobel.assembler.metadata.CoreMetadataFactory$UnresolvedType.resolve(CoreMetadataFactory.java:589)
        //     at com.strobel.assembler.metadata.MetadataResolver.resolve(MetadataResolver.java:128)
        //     at com.strobel.assembler.metadata.CoreMetadataFactory$UnresolvedType.resolve(CoreMetadataFactory.java:599)
        //     at com.strobel.assembler.metadata.MethodReference.resolve(MethodReference.java:172)
        //     at com.strobel.decompiler.ast.TypeAnalysis.inferCall(TypeAnalysis.java:2428)
        //     at com.strobel.decompiler.ast.TypeAnalysis.doInferTypeForExpression(TypeAnalysis.java:1029)
        //     at com.strobel.decompiler.ast.TypeAnalysis.inferTypeForExpression(TypeAnalysis.java:803)
        //     at com.strobel.decompiler.ast.TypeAnalysis.runInference(TypeAnalysis.java:672)
        //     at com.strobel.decompiler.ast.TypeAnalysis.runInference(TypeAnalysis.java:655)
        //     at com.strobel.decompiler.ast.TypeAnalysis.runInference(TypeAnalysis.java:365)
        //     at com.strobel.decompiler.ast.TypeAnalysis.run(TypeAnalysis.java:96)
        //     at com.strobel.decompiler.ast.AstOptimizer.optimize(AstOptimizer.java:109)
        //     at com.strobel.decompiler.ast.AstOptimizer.optimize(AstOptimizer.java:42)
        //     at com.strobel.decompiler.languages.java.ast.AstMethodBodyBuilder.createMethodBody(AstMethodBodyBuilder.java:214)
        //     at com.strobel.decompiler.languages.java.ast.AstMethodBodyBuilder.createMethodBody(AstMethodBodyBuilder.java:99)
        //     at com.strobel.decompiler.languages.java.ast.AstBuilder.createMethodBody(AstBuilder.java:757)
        //     at com.strobel.decompiler.languages.java.ast.AstBuilder.createMethod(AstBuilder.java:655)
        //     at com.strobel.decompiler.languages.java.ast.AstBuilder.addTypeMembers(AstBuilder.java:532)
        //     at com.strobel.decompiler.languages.java.ast.AstBuilder.createTypeCore(AstBuilder.java:499)
        //     at com.strobel.decompiler.languages.java.ast.AstBuilder.createTypeNoCache(AstBuilder.java:141)
        //     at com.strobel.decompiler.languages.java.ast.AstBuilder.createType(AstBuilder.java:130)
        //     at com.strobel.decompiler.languages.java.ast.AstBuilder.addType(AstBuilder.java:105)
        //     at com.strobel.decompiler.languages.java.JavaLanguage.buildAst(JavaLanguage.java:71)
        //     at com.strobel.decompiler.languages.java.JavaLanguage.decompileType(JavaLanguage.java:59)
        //     at com.strobel.decompiler.DecompilerDriver.decompileType(DecompilerDriver.java:317)
        //     at com.strobel.decompiler.DecompilerDriver.decompileJar(DecompilerDriver.java:238)
        //     at com.strobel.decompiler.DecompilerDriver.main(DecompilerDriver.java:138)
        // 
        throw new IllegalStateException("An error occurred while decompiling this method.");
    }
    
    public void fetchSeasonDetails(final String p0, final BrowseAgentCallback p1) {
        // 
        // This method could not be decompiled.
        // 
        // Original Bytecode:
        // 
        //     0: aload_0        
        //     1: new             new            !!! ERROR
        //     4: dup            
        //     5: aload_0        
        //     6: aload_1        
        //     7: aload_2        
        //     8: invokespecial   invokespecial  !!! ERROR
        //    11: invokespecial   com/netflix/falkor/CachedModelProxy.launchTask:(Ljava/lang/Runnable;)V
        //    14: return         
        // 
        // The error that occurred was:
        // 
        // java.lang.IllegalArgumentException: Argument 'typeArguments' must not have any null elements.
        //     at com.strobel.core.VerifyArgument.noNullElementsAndNotEmpty(VerifyArgument.java:145)
        //     at com.strobel.assembler.metadata.CoreMetadataFactory$UnresolvedType.makeGenericType(CoreMetadataFactory.java:570)
        //     at com.strobel.assembler.metadata.CoreMetadataFactory.makeParameterizedType(CoreMetadataFactory.java:156)
        //     at com.strobel.assembler.metadata.signatures.Reifier.visitClassTypeSignature(Reifier.java:125)
        //     at com.strobel.assembler.metadata.signatures.ClassTypeSignature.accept(ClassTypeSignature.java:46)
        //     at com.strobel.assembler.metadata.MetadataParser.parseClassSignature(MetadataParser.java:394)
        //     at com.strobel.assembler.metadata.ClassFileReader.populateBaseTypes(ClassFileReader.java:665)
        //     at com.strobel.assembler.metadata.ClassFileReader.readClass(ClassFileReader.java:438)
        //     at com.strobel.assembler.metadata.ClassFileReader.readClass(ClassFileReader.java:366)
        //     at com.strobel.assembler.metadata.MetadataSystem.resolveType(MetadataSystem.java:124)
        //     at com.strobel.decompiler.NoRetryMetadataSystem.resolveType(DecompilerDriver.java:463)
        //     at com.strobel.assembler.metadata.MetadataSystem.resolveCore(MetadataSystem.java:76)
        //     at com.strobel.assembler.metadata.MetadataResolver.resolve(MetadataResolver.java:104)
        //     at com.strobel.assembler.metadata.CoreMetadataFactory$UnresolvedType.resolve(CoreMetadataFactory.java:589)
        //     at com.strobel.assembler.metadata.MetadataResolver.resolve(MetadataResolver.java:128)
        //     at com.strobel.assembler.metadata.CoreMetadataFactory$UnresolvedType.resolve(CoreMetadataFactory.java:599)
        //     at com.strobel.assembler.metadata.MethodReference.resolve(MethodReference.java:172)
        //     at com.strobel.decompiler.ast.TypeAnalysis.inferCall(TypeAnalysis.java:2428)
        //     at com.strobel.decompiler.ast.TypeAnalysis.doInferTypeForExpression(TypeAnalysis.java:1029)
        //     at com.strobel.decompiler.ast.TypeAnalysis.inferTypeForExpression(TypeAnalysis.java:803)
        //     at com.strobel.decompiler.ast.TypeAnalysis.runInference(TypeAnalysis.java:672)
        //     at com.strobel.decompiler.ast.TypeAnalysis.runInference(TypeAnalysis.java:655)
        //     at com.strobel.decompiler.ast.TypeAnalysis.runInference(TypeAnalysis.java:365)
        //     at com.strobel.decompiler.ast.TypeAnalysis.run(TypeAnalysis.java:96)
        //     at com.strobel.decompiler.ast.AstOptimizer.optimize(AstOptimizer.java:109)
        //     at com.strobel.decompiler.ast.AstOptimizer.optimize(AstOptimizer.java:42)
        //     at com.strobel.decompiler.languages.java.ast.AstMethodBodyBuilder.createMethodBody(AstMethodBodyBuilder.java:214)
        //     at com.strobel.decompiler.languages.java.ast.AstMethodBodyBuilder.createMethodBody(AstMethodBodyBuilder.java:99)
        //     at com.strobel.decompiler.languages.java.ast.AstBuilder.createMethodBody(AstBuilder.java:757)
        //     at com.strobel.decompiler.languages.java.ast.AstBuilder.createMethod(AstBuilder.java:655)
        //     at com.strobel.decompiler.languages.java.ast.AstBuilder.addTypeMembers(AstBuilder.java:532)
        //     at com.strobel.decompiler.languages.java.ast.AstBuilder.createTypeCore(AstBuilder.java:499)
        //     at com.strobel.decompiler.languages.java.ast.AstBuilder.createTypeNoCache(AstBuilder.java:141)
        //     at com.strobel.decompiler.languages.java.ast.AstBuilder.createType(AstBuilder.java:130)
        //     at com.strobel.decompiler.languages.java.ast.AstBuilder.addType(AstBuilder.java:105)
        //     at com.strobel.decompiler.languages.java.JavaLanguage.buildAst(JavaLanguage.java:71)
        //     at com.strobel.decompiler.languages.java.JavaLanguage.decompileType(JavaLanguage.java:59)
        //     at com.strobel.decompiler.DecompilerDriver.decompileType(DecompilerDriver.java:317)
        //     at com.strobel.decompiler.DecompilerDriver.decompileJar(DecompilerDriver.java:238)
        //     at com.strobel.decompiler.DecompilerDriver.main(DecompilerDriver.java:138)
        // 
        throw new IllegalStateException("An error occurred while decompiling this method.");
    }
    
    public void fetchSeasons(final String p0, final int p1, final int p2, final BrowseAgentCallback p3) {
        // 
        // This method could not be decompiled.
        // 
        // Original Bytecode:
        // 
        //     0: aload_0        
        //     1: new             new            !!! ERROR
        //     4: dup            
        //     5: aload_0        
        //     6: aload_1        
        //     7: iload_2        
        //     8: iload_3        
        //     9: aload           4
        //    11: invokespecial   invokespecial  !!! ERROR
        //    14: invokespecial   com/netflix/falkor/CachedModelProxy.launchTask:(Ljava/lang/Runnable;)V
        //    17: return         
        // 
        // The error that occurred was:
        // 
        // java.lang.IllegalArgumentException: Argument 'typeArguments' must not have any null elements.
        //     at com.strobel.core.VerifyArgument.noNullElementsAndNotEmpty(VerifyArgument.java:145)
        //     at com.strobel.assembler.metadata.CoreMetadataFactory$UnresolvedType.makeGenericType(CoreMetadataFactory.java:570)
        //     at com.strobel.assembler.metadata.CoreMetadataFactory.makeParameterizedType(CoreMetadataFactory.java:156)
        //     at com.strobel.assembler.metadata.signatures.Reifier.visitClassTypeSignature(Reifier.java:125)
        //     at com.strobel.assembler.metadata.signatures.ClassTypeSignature.accept(ClassTypeSignature.java:46)
        //     at com.strobel.assembler.metadata.MetadataParser.parseClassSignature(MetadataParser.java:394)
        //     at com.strobel.assembler.metadata.ClassFileReader.populateBaseTypes(ClassFileReader.java:665)
        //     at com.strobel.assembler.metadata.ClassFileReader.readClass(ClassFileReader.java:438)
        //     at com.strobel.assembler.metadata.ClassFileReader.readClass(ClassFileReader.java:366)
        //     at com.strobel.assembler.metadata.MetadataSystem.resolveType(MetadataSystem.java:124)
        //     at com.strobel.decompiler.NoRetryMetadataSystem.resolveType(DecompilerDriver.java:463)
        //     at com.strobel.assembler.metadata.MetadataSystem.resolveCore(MetadataSystem.java:76)
        //     at com.strobel.assembler.metadata.MetadataResolver.resolve(MetadataResolver.java:104)
        //     at com.strobel.assembler.metadata.CoreMetadataFactory$UnresolvedType.resolve(CoreMetadataFactory.java:589)
        //     at com.strobel.assembler.metadata.MetadataResolver.resolve(MetadataResolver.java:128)
        //     at com.strobel.assembler.metadata.CoreMetadataFactory$UnresolvedType.resolve(CoreMetadataFactory.java:599)
        //     at com.strobel.assembler.metadata.MethodReference.resolve(MethodReference.java:172)
        //     at com.strobel.decompiler.ast.TypeAnalysis.inferCall(TypeAnalysis.java:2428)
        //     at com.strobel.decompiler.ast.TypeAnalysis.doInferTypeForExpression(TypeAnalysis.java:1029)
        //     at com.strobel.decompiler.ast.TypeAnalysis.inferTypeForExpression(TypeAnalysis.java:803)
        //     at com.strobel.decompiler.ast.TypeAnalysis.runInference(TypeAnalysis.java:672)
        //     at com.strobel.decompiler.ast.TypeAnalysis.runInference(TypeAnalysis.java:655)
        //     at com.strobel.decompiler.ast.TypeAnalysis.runInference(TypeAnalysis.java:365)
        //     at com.strobel.decompiler.ast.TypeAnalysis.run(TypeAnalysis.java:96)
        //     at com.strobel.decompiler.ast.AstOptimizer.optimize(AstOptimizer.java:109)
        //     at com.strobel.decompiler.ast.AstOptimizer.optimize(AstOptimizer.java:42)
        //     at com.strobel.decompiler.languages.java.ast.AstMethodBodyBuilder.createMethodBody(AstMethodBodyBuilder.java:214)
        //     at com.strobel.decompiler.languages.java.ast.AstMethodBodyBuilder.createMethodBody(AstMethodBodyBuilder.java:99)
        //     at com.strobel.decompiler.languages.java.ast.AstBuilder.createMethodBody(AstBuilder.java:757)
        //     at com.strobel.decompiler.languages.java.ast.AstBuilder.createMethod(AstBuilder.java:655)
        //     at com.strobel.decompiler.languages.java.ast.AstBuilder.addTypeMembers(AstBuilder.java:532)
        //     at com.strobel.decompiler.languages.java.ast.AstBuilder.createTypeCore(AstBuilder.java:499)
        //     at com.strobel.decompiler.languages.java.ast.AstBuilder.createTypeNoCache(AstBuilder.java:141)
        //     at com.strobel.decompiler.languages.java.ast.AstBuilder.createType(AstBuilder.java:130)
        //     at com.strobel.decompiler.languages.java.ast.AstBuilder.addType(AstBuilder.java:105)
        //     at com.strobel.decompiler.languages.java.JavaLanguage.buildAst(JavaLanguage.java:71)
        //     at com.strobel.decompiler.languages.java.JavaLanguage.decompileType(JavaLanguage.java:59)
        //     at com.strobel.decompiler.DecompilerDriver.decompileType(DecompilerDriver.java:317)
        //     at com.strobel.decompiler.DecompilerDriver.decompileJar(DecompilerDriver.java:238)
        //     at com.strobel.decompiler.DecompilerDriver.main(DecompilerDriver.java:138)
        // 
        throw new IllegalStateException("An error occurred while decompiling this method.");
    }
    
    public void fetchShowDetails(final String p0, final String p1, final boolean p2, final boolean p3, final BrowseAgentCallback p4) {
        // 
        // This method could not be decompiled.
        // 
        // Original Bytecode:
        // 
        //     0: aload_0        
        //     1: new             new            !!! ERROR
        //     4: dup            
        //     5: aload_0        
        //     6: aload_1        
        //     7: aload_2        
        //     8: iload_3        
        //     9: iload           4
        //    11: aload           5
        //    13: invokespecial   invokespecial  !!! ERROR
        //    16: invokespecial   com/netflix/falkor/CachedModelProxy.launchTask:(Ljava/lang/Runnable;)V
        //    19: return         
        // 
        // The error that occurred was:
        // 
        // java.lang.IllegalArgumentException: Argument 'typeArguments' must not have any null elements.
        //     at com.strobel.core.VerifyArgument.noNullElementsAndNotEmpty(VerifyArgument.java:145)
        //     at com.strobel.assembler.metadata.CoreMetadataFactory$UnresolvedType.makeGenericType(CoreMetadataFactory.java:570)
        //     at com.strobel.assembler.metadata.CoreMetadataFactory.makeParameterizedType(CoreMetadataFactory.java:156)
        //     at com.strobel.assembler.metadata.signatures.Reifier.visitClassTypeSignature(Reifier.java:125)
        //     at com.strobel.assembler.metadata.signatures.ClassTypeSignature.accept(ClassTypeSignature.java:46)
        //     at com.strobel.assembler.metadata.MetadataParser.parseClassSignature(MetadataParser.java:394)
        //     at com.strobel.assembler.metadata.ClassFileReader.populateBaseTypes(ClassFileReader.java:665)
        //     at com.strobel.assembler.metadata.ClassFileReader.readClass(ClassFileReader.java:438)
        //     at com.strobel.assembler.metadata.ClassFileReader.readClass(ClassFileReader.java:366)
        //     at com.strobel.assembler.metadata.MetadataSystem.resolveType(MetadataSystem.java:124)
        //     at com.strobel.decompiler.NoRetryMetadataSystem.resolveType(DecompilerDriver.java:463)
        //     at com.strobel.assembler.metadata.MetadataSystem.resolveCore(MetadataSystem.java:76)
        //     at com.strobel.assembler.metadata.MetadataResolver.resolve(MetadataResolver.java:104)
        //     at com.strobel.assembler.metadata.CoreMetadataFactory$UnresolvedType.resolve(CoreMetadataFactory.java:589)
        //     at com.strobel.assembler.metadata.MetadataResolver.resolve(MetadataResolver.java:128)
        //     at com.strobel.assembler.metadata.CoreMetadataFactory$UnresolvedType.resolve(CoreMetadataFactory.java:599)
        //     at com.strobel.assembler.metadata.MethodReference.resolve(MethodReference.java:172)
        //     at com.strobel.decompiler.ast.TypeAnalysis.inferCall(TypeAnalysis.java:2428)
        //     at com.strobel.decompiler.ast.TypeAnalysis.doInferTypeForExpression(TypeAnalysis.java:1029)
        //     at com.strobel.decompiler.ast.TypeAnalysis.inferTypeForExpression(TypeAnalysis.java:803)
        //     at com.strobel.decompiler.ast.TypeAnalysis.runInference(TypeAnalysis.java:672)
        //     at com.strobel.decompiler.ast.TypeAnalysis.runInference(TypeAnalysis.java:655)
        //     at com.strobel.decompiler.ast.TypeAnalysis.runInference(TypeAnalysis.java:365)
        //     at com.strobel.decompiler.ast.TypeAnalysis.run(TypeAnalysis.java:96)
        //     at com.strobel.decompiler.ast.AstOptimizer.optimize(AstOptimizer.java:109)
        //     at com.strobel.decompiler.ast.AstOptimizer.optimize(AstOptimizer.java:42)
        //     at com.strobel.decompiler.languages.java.ast.AstMethodBodyBuilder.createMethodBody(AstMethodBodyBuilder.java:214)
        //     at com.strobel.decompiler.languages.java.ast.AstMethodBodyBuilder.createMethodBody(AstMethodBodyBuilder.java:99)
        //     at com.strobel.decompiler.languages.java.ast.AstBuilder.createMethodBody(AstBuilder.java:757)
        //     at com.strobel.decompiler.languages.java.ast.AstBuilder.createMethod(AstBuilder.java:655)
        //     at com.strobel.decompiler.languages.java.ast.AstBuilder.addTypeMembers(AstBuilder.java:532)
        //     at com.strobel.decompiler.languages.java.ast.AstBuilder.createTypeCore(AstBuilder.java:499)
        //     at com.strobel.decompiler.languages.java.ast.AstBuilder.createTypeNoCache(AstBuilder.java:141)
        //     at com.strobel.decompiler.languages.java.ast.AstBuilder.createType(AstBuilder.java:130)
        //     at com.strobel.decompiler.languages.java.ast.AstBuilder.addType(AstBuilder.java:105)
        //     at com.strobel.decompiler.languages.java.JavaLanguage.buildAst(JavaLanguage.java:71)
        //     at com.strobel.decompiler.languages.java.JavaLanguage.decompileType(JavaLanguage.java:59)
        //     at com.strobel.decompiler.DecompilerDriver.decompileType(DecompilerDriver.java:317)
        //     at com.strobel.decompiler.DecompilerDriver.decompileJar(DecompilerDriver.java:238)
        //     at com.strobel.decompiler.DecompilerDriver.main(DecompilerDriver.java:138)
        // 
        throw new IllegalStateException("An error occurred while decompiling this method.");
    }
    
    public void fetchSimilarVideos(final Falkor$SimilarRequestType p0, final String p1, final int p2, final String p3, final BrowseAgentCallback p4) {
        // 
        // This method could not be decompiled.
        // 
        // Original Bytecode:
        // 
        //     0: aload_0        
        //     1: new             new            !!! ERROR
        //     4: dup            
        //     5: aload_0        
        //     6: aload_1        
        //     7: aload_2        
        //     8: iload_3        
        //     9: aload           4
        //    11: aload           5
        //    13: invokespecial   invokespecial  !!! ERROR
        //    16: invokespecial   com/netflix/falkor/CachedModelProxy.launchTask:(Ljava/lang/Runnable;)V
        //    19: return         
        // 
        // The error that occurred was:
        // 
        // java.lang.IllegalArgumentException: Argument 'typeArguments' must not have any null elements.
        //     at com.strobel.core.VerifyArgument.noNullElementsAndNotEmpty(VerifyArgument.java:145)
        //     at com.strobel.assembler.metadata.CoreMetadataFactory$UnresolvedType.makeGenericType(CoreMetadataFactory.java:570)
        //     at com.strobel.assembler.metadata.CoreMetadataFactory.makeParameterizedType(CoreMetadataFactory.java:156)
        //     at com.strobel.assembler.metadata.signatures.Reifier.visitClassTypeSignature(Reifier.java:125)
        //     at com.strobel.assembler.metadata.signatures.ClassTypeSignature.accept(ClassTypeSignature.java:46)
        //     at com.strobel.assembler.metadata.MetadataParser.parseClassSignature(MetadataParser.java:394)
        //     at com.strobel.assembler.metadata.ClassFileReader.populateBaseTypes(ClassFileReader.java:665)
        //     at com.strobel.assembler.metadata.ClassFileReader.readClass(ClassFileReader.java:438)
        //     at com.strobel.assembler.metadata.ClassFileReader.readClass(ClassFileReader.java:366)
        //     at com.strobel.assembler.metadata.MetadataSystem.resolveType(MetadataSystem.java:124)
        //     at com.strobel.decompiler.NoRetryMetadataSystem.resolveType(DecompilerDriver.java:463)
        //     at com.strobel.assembler.metadata.MetadataSystem.resolveCore(MetadataSystem.java:76)
        //     at com.strobel.assembler.metadata.MetadataResolver.resolve(MetadataResolver.java:104)
        //     at com.strobel.assembler.metadata.CoreMetadataFactory$UnresolvedType.resolve(CoreMetadataFactory.java:589)
        //     at com.strobel.assembler.metadata.MetadataResolver.resolve(MetadataResolver.java:128)
        //     at com.strobel.assembler.metadata.CoreMetadataFactory$UnresolvedType.resolve(CoreMetadataFactory.java:599)
        //     at com.strobel.assembler.metadata.MethodReference.resolve(MethodReference.java:172)
        //     at com.strobel.decompiler.ast.TypeAnalysis.inferCall(TypeAnalysis.java:2428)
        //     at com.strobel.decompiler.ast.TypeAnalysis.doInferTypeForExpression(TypeAnalysis.java:1029)
        //     at com.strobel.decompiler.ast.TypeAnalysis.inferTypeForExpression(TypeAnalysis.java:803)
        //     at com.strobel.decompiler.ast.TypeAnalysis.runInference(TypeAnalysis.java:672)
        //     at com.strobel.decompiler.ast.TypeAnalysis.runInference(TypeAnalysis.java:655)
        //     at com.strobel.decompiler.ast.TypeAnalysis.runInference(TypeAnalysis.java:365)
        //     at com.strobel.decompiler.ast.TypeAnalysis.run(TypeAnalysis.java:96)
        //     at com.strobel.decompiler.ast.AstOptimizer.optimize(AstOptimizer.java:109)
        //     at com.strobel.decompiler.ast.AstOptimizer.optimize(AstOptimizer.java:42)
        //     at com.strobel.decompiler.languages.java.ast.AstMethodBodyBuilder.createMethodBody(AstMethodBodyBuilder.java:214)
        //     at com.strobel.decompiler.languages.java.ast.AstMethodBodyBuilder.createMethodBody(AstMethodBodyBuilder.java:99)
        //     at com.strobel.decompiler.languages.java.ast.AstBuilder.createMethodBody(AstBuilder.java:757)
        //     at com.strobel.decompiler.languages.java.ast.AstBuilder.createMethod(AstBuilder.java:655)
        //     at com.strobel.decompiler.languages.java.ast.AstBuilder.addTypeMembers(AstBuilder.java:532)
        //     at com.strobel.decompiler.languages.java.ast.AstBuilder.createTypeCore(AstBuilder.java:499)
        //     at com.strobel.decompiler.languages.java.ast.AstBuilder.createTypeNoCache(AstBuilder.java:141)
        //     at com.strobel.decompiler.languages.java.ast.AstBuilder.createType(AstBuilder.java:130)
        //     at com.strobel.decompiler.languages.java.ast.AstBuilder.addType(AstBuilder.java:105)
        //     at com.strobel.decompiler.languages.java.JavaLanguage.buildAst(JavaLanguage.java:71)
        //     at com.strobel.decompiler.languages.java.JavaLanguage.decompileType(JavaLanguage.java:59)
        //     at com.strobel.decompiler.DecompilerDriver.decompileType(DecompilerDriver.java:317)
        //     at com.strobel.decompiler.DecompilerDriver.decompileJar(DecompilerDriver.java:238)
        //     at com.strobel.decompiler.DecompilerDriver.main(DecompilerDriver.java:138)
        // 
        throw new IllegalStateException("An error occurred while decompiling this method.");
    }
    
    public void fetchVideoSummary(final String p0, final BrowseAgentCallback p1) {
        // 
        // This method could not be decompiled.
        // 
        // Original Bytecode:
        // 
        //     0: aload_0        
        //     1: new             new            !!! ERROR
        //     4: dup            
        //     5: aload_0        
        //     6: aload_1        
        //     7: aload_2        
        //     8: invokespecial   invokespecial  !!! ERROR
        //    11: invokespecial   com/netflix/falkor/CachedModelProxy.launchTask:(Ljava/lang/Runnable;)V
        //    14: return         
        // 
        // The error that occurred was:
        // 
        // java.lang.IllegalArgumentException: Argument 'typeArguments' must not have any null elements.
        //     at com.strobel.core.VerifyArgument.noNullElementsAndNotEmpty(VerifyArgument.java:145)
        //     at com.strobel.assembler.metadata.CoreMetadataFactory$UnresolvedType.makeGenericType(CoreMetadataFactory.java:570)
        //     at com.strobel.assembler.metadata.CoreMetadataFactory.makeParameterizedType(CoreMetadataFactory.java:156)
        //     at com.strobel.assembler.metadata.signatures.Reifier.visitClassTypeSignature(Reifier.java:125)
        //     at com.strobel.assembler.metadata.signatures.ClassTypeSignature.accept(ClassTypeSignature.java:46)
        //     at com.strobel.assembler.metadata.MetadataParser.parseClassSignature(MetadataParser.java:394)
        //     at com.strobel.assembler.metadata.ClassFileReader.populateBaseTypes(ClassFileReader.java:665)
        //     at com.strobel.assembler.metadata.ClassFileReader.readClass(ClassFileReader.java:438)
        //     at com.strobel.assembler.metadata.ClassFileReader.readClass(ClassFileReader.java:366)
        //     at com.strobel.assembler.metadata.MetadataSystem.resolveType(MetadataSystem.java:124)
        //     at com.strobel.decompiler.NoRetryMetadataSystem.resolveType(DecompilerDriver.java:463)
        //     at com.strobel.assembler.metadata.MetadataSystem.resolveCore(MetadataSystem.java:76)
        //     at com.strobel.assembler.metadata.MetadataResolver.resolve(MetadataResolver.java:104)
        //     at com.strobel.assembler.metadata.CoreMetadataFactory$UnresolvedType.resolve(CoreMetadataFactory.java:589)
        //     at com.strobel.assembler.metadata.MetadataResolver.resolve(MetadataResolver.java:128)
        //     at com.strobel.assembler.metadata.CoreMetadataFactory$UnresolvedType.resolve(CoreMetadataFactory.java:599)
        //     at com.strobel.assembler.metadata.MethodReference.resolve(MethodReference.java:172)
        //     at com.strobel.decompiler.ast.TypeAnalysis.inferCall(TypeAnalysis.java:2428)
        //     at com.strobel.decompiler.ast.TypeAnalysis.doInferTypeForExpression(TypeAnalysis.java:1029)
        //     at com.strobel.decompiler.ast.TypeAnalysis.inferTypeForExpression(TypeAnalysis.java:803)
        //     at com.strobel.decompiler.ast.TypeAnalysis.runInference(TypeAnalysis.java:672)
        //     at com.strobel.decompiler.ast.TypeAnalysis.runInference(TypeAnalysis.java:655)
        //     at com.strobel.decompiler.ast.TypeAnalysis.runInference(TypeAnalysis.java:365)
        //     at com.strobel.decompiler.ast.TypeAnalysis.run(TypeAnalysis.java:96)
        //     at com.strobel.decompiler.ast.AstOptimizer.optimize(AstOptimizer.java:109)
        //     at com.strobel.decompiler.ast.AstOptimizer.optimize(AstOptimizer.java:42)
        //     at com.strobel.decompiler.languages.java.ast.AstMethodBodyBuilder.createMethodBody(AstMethodBodyBuilder.java:214)
        //     at com.strobel.decompiler.languages.java.ast.AstMethodBodyBuilder.createMethodBody(AstMethodBodyBuilder.java:99)
        //     at com.strobel.decompiler.languages.java.ast.AstBuilder.createMethodBody(AstBuilder.java:757)
        //     at com.strobel.decompiler.languages.java.ast.AstBuilder.createMethod(AstBuilder.java:655)
        //     at com.strobel.decompiler.languages.java.ast.AstBuilder.addTypeMembers(AstBuilder.java:532)
        //     at com.strobel.decompiler.languages.java.ast.AstBuilder.createTypeCore(AstBuilder.java:499)
        //     at com.strobel.decompiler.languages.java.ast.AstBuilder.createTypeNoCache(AstBuilder.java:141)
        //     at com.strobel.decompiler.languages.java.ast.AstBuilder.createType(AstBuilder.java:130)
        //     at com.strobel.decompiler.languages.java.ast.AstBuilder.addType(AstBuilder.java:105)
        //     at com.strobel.decompiler.languages.java.JavaLanguage.buildAst(JavaLanguage.java:71)
        //     at com.strobel.decompiler.languages.java.JavaLanguage.decompileType(JavaLanguage.java:59)
        //     at com.strobel.decompiler.DecompilerDriver.decompileType(DecompilerDriver.java:317)
        //     at com.strobel.decompiler.DecompilerDriver.decompileJar(DecompilerDriver.java:238)
        //     at com.strobel.decompiler.DecompilerDriver.main(DecompilerDriver.java:138)
        // 
        throw new IllegalStateException("An error occurred while decompiling this method.");
    }
    
    public void fetchVideos(final LoMo p0, final int p1, final int p2, final boolean p3, final boolean p4, final boolean p5, final BrowseAgentCallback p6) {
        // 
        // This method could not be decompiled.
        // 
        // Original Bytecode:
        // 
        //     0: getstatic       com/netflix/mediaclient/servicemgr/interface_/LoMoType.BILLBOARD:Lcom/netflix/mediaclient/servicemgr/interface_/LoMoType;
        //     3: aload_1        
        //     4: invokeinterface com/netflix/mediaclient/servicemgr/interface_/LoMo.getType:()Lcom/netflix/mediaclient/servicemgr/interface_/LoMoType;
        //     9: invokevirtual   com/netflix/mediaclient/servicemgr/interface_/LoMoType.equals:(Ljava/lang/Object;)Z
        //    12: ifeq            34
        //    15: aload_0        
        //    16: new             new            !!! ERROR
        //    19: dup            
        //    20: aload_0        
        //    21: iload_2        
        //    22: iload_3        
        //    23: iload           4
        //    25: aload           7
        //    27: invokespecial   invokespecial  !!! ERROR
        //    30: invokespecial   com/netflix/falkor/CachedModelProxy.launchTask:(Ljava/lang/Runnable;)V
        //    33: return         
        //    34: aload_0        
        //    35: new             new            !!! ERROR
        //    38: dup            
        //    39: aload_0        
        //    40: aload_1        
        //    41: iload_2        
        //    42: iload_3        
        //    43: iload           4
        //    45: iload           5
        //    47: iload           6
        //    49: aload           7
        //    51: invokespecial   invokespecial  !!! ERROR
        //    54: invokespecial   com/netflix/falkor/CachedModelProxy.launchTask:(Ljava/lang/Runnable;)V
        //    57: return         
        // 
        // The error that occurred was:
        // 
        // java.lang.IllegalArgumentException: Argument 'typeArguments' must not have any null elements.
        //     at com.strobel.core.VerifyArgument.noNullElementsAndNotEmpty(VerifyArgument.java:145)
        //     at com.strobel.assembler.metadata.CoreMetadataFactory$UnresolvedType.makeGenericType(CoreMetadataFactory.java:570)
        //     at com.strobel.assembler.metadata.CoreMetadataFactory.makeParameterizedType(CoreMetadataFactory.java:156)
        //     at com.strobel.assembler.metadata.signatures.Reifier.visitClassTypeSignature(Reifier.java:125)
        //     at com.strobel.assembler.metadata.signatures.ClassTypeSignature.accept(ClassTypeSignature.java:46)
        //     at com.strobel.assembler.metadata.MetadataParser.parseClassSignature(MetadataParser.java:394)
        //     at com.strobel.assembler.metadata.ClassFileReader.populateBaseTypes(ClassFileReader.java:665)
        //     at com.strobel.assembler.metadata.ClassFileReader.readClass(ClassFileReader.java:438)
        //     at com.strobel.assembler.metadata.ClassFileReader.readClass(ClassFileReader.java:366)
        //     at com.strobel.assembler.metadata.MetadataSystem.resolveType(MetadataSystem.java:124)
        //     at com.strobel.decompiler.NoRetryMetadataSystem.resolveType(DecompilerDriver.java:463)
        //     at com.strobel.assembler.metadata.MetadataSystem.resolveCore(MetadataSystem.java:76)
        //     at com.strobel.assembler.metadata.MetadataResolver.resolve(MetadataResolver.java:104)
        //     at com.strobel.assembler.metadata.CoreMetadataFactory$UnresolvedType.resolve(CoreMetadataFactory.java:589)
        //     at com.strobel.assembler.metadata.MetadataResolver.resolve(MetadataResolver.java:128)
        //     at com.strobel.assembler.metadata.CoreMetadataFactory$UnresolvedType.resolve(CoreMetadataFactory.java:599)
        //     at com.strobel.assembler.metadata.MethodReference.resolve(MethodReference.java:172)
        //     at com.strobel.decompiler.ast.TypeAnalysis.inferCall(TypeAnalysis.java:2428)
        //     at com.strobel.decompiler.ast.TypeAnalysis.doInferTypeForExpression(TypeAnalysis.java:1029)
        //     at com.strobel.decompiler.ast.TypeAnalysis.inferTypeForExpression(TypeAnalysis.java:803)
        //     at com.strobel.decompiler.ast.TypeAnalysis.runInference(TypeAnalysis.java:672)
        //     at com.strobel.decompiler.ast.TypeAnalysis.runInference(TypeAnalysis.java:655)
        //     at com.strobel.decompiler.ast.TypeAnalysis.runInference(TypeAnalysis.java:365)
        //     at com.strobel.decompiler.ast.TypeAnalysis.run(TypeAnalysis.java:96)
        //     at com.strobel.decompiler.ast.AstOptimizer.optimize(AstOptimizer.java:109)
        //     at com.strobel.decompiler.ast.AstOptimizer.optimize(AstOptimizer.java:42)
        //     at com.strobel.decompiler.languages.java.ast.AstMethodBodyBuilder.createMethodBody(AstMethodBodyBuilder.java:214)
        //     at com.strobel.decompiler.languages.java.ast.AstMethodBodyBuilder.createMethodBody(AstMethodBodyBuilder.java:99)
        //     at com.strobel.decompiler.languages.java.ast.AstBuilder.createMethodBody(AstBuilder.java:757)
        //     at com.strobel.decompiler.languages.java.ast.AstBuilder.createMethod(AstBuilder.java:655)
        //     at com.strobel.decompiler.languages.java.ast.AstBuilder.addTypeMembers(AstBuilder.java:532)
        //     at com.strobel.decompiler.languages.java.ast.AstBuilder.createTypeCore(AstBuilder.java:499)
        //     at com.strobel.decompiler.languages.java.ast.AstBuilder.createTypeNoCache(AstBuilder.java:141)
        //     at com.strobel.decompiler.languages.java.ast.AstBuilder.createType(AstBuilder.java:130)
        //     at com.strobel.decompiler.languages.java.ast.AstBuilder.addType(AstBuilder.java:105)
        //     at com.strobel.decompiler.languages.java.JavaLanguage.buildAst(JavaLanguage.java:71)
        //     at com.strobel.decompiler.languages.java.JavaLanguage.decompileType(JavaLanguage.java:59)
        //     at com.strobel.decompiler.DecompilerDriver.decompileType(DecompilerDriver.java:317)
        //     at com.strobel.decompiler.DecompilerDriver.decompileJar(DecompilerDriver.java:238)
        //     at com.strobel.decompiler.DecompilerDriver.main(DecompilerDriver.java:138)
        // 
        throw new IllegalStateException("An error occurred while decompiling this method.");
    }
    
    public void flushCaches() {
        synchronized (this) {
            if (Log.isLoggable()) {
                Log.v("CachedModelProxy", "Flushing caches...");
            }
            this.lastPrefetchFromVideo = -1;
            this.lastPrefetchToVideo = -1;
            if (!(this.root instanceof Flushable)) {
                return;
            }
            final Flushable flushable = (Flushable)this.root;
            try {
                if (Log.isLoggable()) {
                    Log.v("CachedModelProxy", "Flushing root");
                }
                flushable.flush();
            }
            catch (IOException ex) {
                Log.handleException("CachedModelProxy", ex);
            }
        }
    }
    
    public void forceFetchFromLocalCache(final boolean force_CMP_TO_LOCAL_CACHE) {
        Log.w("CachedModelProxy", String.format("forcing CMP fetch behavior to useLocalCacheOnly:%b", force_CMP_TO_LOCAL_CACHE));
        CachedModelProxy.FORCE_CMP_TO_LOCAL_CACHE = force_CMP_TO_LOCAL_CACHE;
    }
    
    @Override
    public CachedModelProxy$GetResult get(final Collection<PQL> collection) {
        final CachedModelProxy$GetResult cachedModelProxy$GetResult;
        synchronized (this) {
            cachedModelProxy$GetResult = new CachedModelProxy$GetResult(collection);
            final Iterator<PQL> iterator = collection.iterator();
            while (iterator.hasNext()) {
                this.get(iterator.next(), this.root, 0, cachedModelProxy$GetResult);
            }
        }
        // monitorexit(this)
        return cachedModelProxy$GetResult;
    }
    
    @Override
    public <I extends FalkorObject> List<I> getItemsAsList(final PQL pql) {
        return this.getItemsAsList(Collections.singleton(pql));
    }
    
    @Override
    public <I extends FalkorObject> List<I> getItemsAsList(final Collection<PQL> collection) {
        final LinkedHashSet<I> set;
        synchronized (this) {
            set = new LinkedHashSet<I>();
            final Iterator<PQL> iterator = collection.iterator();
            while (iterator.hasNext()) {
                for (final PQL pql : iterator.next().explode()) {
                    final Object value = this.getValue(pql);
                    if (value instanceof FalkorObject) {
                        final FalkorObject falkorObject = (I)value;
                        if (Falkor.ENABLE_VERBOSE_LOGGING) {
                            Log.v("CachedModelProxy", "got falkor object - pql: " + pql + ", item: " + falkorObject);
                        }
                        set.add((I)falkorObject);
                    }
                }
            }
        }
        final ArrayList list = new ArrayList<I>(set.size());
        final Iterator<Object> iterator3 = set.iterator();
        while (iterator3.hasNext()) {
            list.add((I)iterator3.next());
        }
        if (Falkor.ENABLE_VERBOSE_LOGGING) {
            Log.v("CachedModelProxy", "Items size: " + list.size());
        }
        // monitorexit(this)
        return (List<I>)list;
    }
    
    protected NetflixService getService() {
        return this.serviceProvider.getService();
    }
    
    @Override
    public ServiceProvider getServiceProvider() {
        return this.serviceProvider;
    }
    
    @Override
    public Object getValue(final PQL pql) {
        // monitorenter(this)
        Label_0013: {
            if (pql == null) {
                break Label_0013;
            }
            while (true) {
                while (true) {
                    int n = 0;
                    Label_0321: {
                        try {
                            Object o;
                            if (pql.isEmpty()) {
                                if (Log.isLoggable()) {
                                    Log.w("CachedModelProxy", "Empty pql - leaving getValue() early");
                                }
                                o = null;
                            }
                            else {
                                if (Falkor.ENABLE_VERBOSE_LOGGING) {
                                    Log.v("CachedModelProxy", "getValue() pql: " + pql);
                                }
                                Object o2 = this.root;
                                final BranchNode branchNode = (BranchNode)o2;
                                final List<Object> keySegments = pql.getKeySegments();
                                final int size = keySegments.size();
                                n = 0;
                                o = o2;
                                if (n < size) {
                                    final String value = keySegments.get(n);
                                    if (value == null) {
                                        break Label_0321;
                                    }
                                    final Object o3 = o2 = branchNode.get(value);
                                    if (Falkor.ENABLE_VERBOSE_LOGGING) {
                                        o2 = new StringBuilder().append("getValue() for key: ").append(value.toString()).append(" currentValue: ");
                                        String simpleName;
                                        if (o3 == null) {
                                            simpleName = "null";
                                        }
                                        else {
                                            simpleName = ((BranchNode)o3).getClass().getSimpleName();
                                        }
                                        Log.v("CachedModelProxy", ((StringBuilder)o2).append(simpleName).toString());
                                        o2 = o3;
                                    }
                                    while (o2 instanceof Ref) {
                                        o2 = (o = o2);
                                        if (n == size - 1) {
                                            return o;
                                        }
                                        o2 = ((Ref)o2).getValue(this);
                                    }
                                    if (o2 instanceof FalkorObject) {
                                        o = o2;
                                        if (n >= size - 2) {
                                            return o;
                                        }
                                    }
                                    if (o2 instanceof BranchNode) {
                                        final BranchNode branchNode2 = (BranchNode)o2;
                                        break Label_0321;
                                    }
                                    o = o2;
                                    if (!(o2 instanceof Exception)) {
                                        final boolean b = o2 instanceof Undefined;
                                        o = o2;
                                        if (b) {
                                            o = o2;
                                        }
                                    }
                                }
                            }
                            return o;
                        }
                        finally {
                        }
                        // monitorexit(this)
                    }
                    ++n;
                    final BranchNode branchNode3;
                    final BranchNode branchNode = branchNode3;
                    continue;
                }
            }
        }
    }
    
    public void invalidateEpisodes(final String s, final VideoType videoType) {
        this.invalidate(PQL.create(videoType.getValue(), s, "episodes"));
    }
    
    public void logBillboardActivity(final Video p0, final BillboardInteractionType p1, final Map<String, String> p2) {
        // 
        // This method could not be decompiled.
        // 
        // Original Bytecode:
        // 
        //     0: aload_0        
        //     1: new             new            !!! ERROR
        //     4: dup            
        //     5: aload_0        
        //     6: aload_1        
        //     7: aload_2        
        //     8: aload_3        
        //     9: invokespecial   invokespecial  !!! ERROR
        //    12: invokespecial   com/netflix/falkor/CachedModelProxy.launchTask:(Ljava/lang/Runnable;)V
        //    15: return         
        //    Signature:
        //  (Lcom/netflix/mediaclient/servicemgr/interface_/Video;Lcom/netflix/mediaclient/servicemgr/BillboardInteractionType;Ljava/util/Map<Ljava/lang/String;Ljava/lang/String;>;)V
        // 
        // The error that occurred was:
        // 
        // java.lang.IllegalArgumentException: Argument 'typeArguments' must not have any null elements.
        //     at com.strobel.core.VerifyArgument.noNullElementsAndNotEmpty(VerifyArgument.java:145)
        //     at com.strobel.assembler.metadata.CoreMetadataFactory$UnresolvedType.makeGenericType(CoreMetadataFactory.java:570)
        //     at com.strobel.assembler.metadata.CoreMetadataFactory.makeParameterizedType(CoreMetadataFactory.java:156)
        //     at com.strobel.assembler.metadata.signatures.Reifier.visitClassTypeSignature(Reifier.java:125)
        //     at com.strobel.assembler.metadata.signatures.ClassTypeSignature.accept(ClassTypeSignature.java:46)
        //     at com.strobel.assembler.metadata.MetadataParser.parseClassSignature(MetadataParser.java:394)
        //     at com.strobel.assembler.metadata.ClassFileReader.populateBaseTypes(ClassFileReader.java:665)
        //     at com.strobel.assembler.metadata.ClassFileReader.readClass(ClassFileReader.java:438)
        //     at com.strobel.assembler.metadata.ClassFileReader.readClass(ClassFileReader.java:366)
        //     at com.strobel.assembler.metadata.MetadataSystem.resolveType(MetadataSystem.java:124)
        //     at com.strobel.decompiler.NoRetryMetadataSystem.resolveType(DecompilerDriver.java:463)
        //     at com.strobel.assembler.metadata.MetadataSystem.resolveCore(MetadataSystem.java:76)
        //     at com.strobel.assembler.metadata.MetadataResolver.resolve(MetadataResolver.java:104)
        //     at com.strobel.assembler.metadata.CoreMetadataFactory$UnresolvedType.resolve(CoreMetadataFactory.java:589)
        //     at com.strobel.assembler.metadata.MetadataResolver.resolve(MetadataResolver.java:128)
        //     at com.strobel.assembler.metadata.CoreMetadataFactory$UnresolvedType.resolve(CoreMetadataFactory.java:599)
        //     at com.strobel.assembler.metadata.MethodReference.resolve(MethodReference.java:172)
        //     at com.strobel.decompiler.ast.TypeAnalysis.inferCall(TypeAnalysis.java:2428)
        //     at com.strobel.decompiler.ast.TypeAnalysis.doInferTypeForExpression(TypeAnalysis.java:1029)
        //     at com.strobel.decompiler.ast.TypeAnalysis.inferTypeForExpression(TypeAnalysis.java:803)
        //     at com.strobel.decompiler.ast.TypeAnalysis.runInference(TypeAnalysis.java:672)
        //     at com.strobel.decompiler.ast.TypeAnalysis.runInference(TypeAnalysis.java:655)
        //     at com.strobel.decompiler.ast.TypeAnalysis.runInference(TypeAnalysis.java:365)
        //     at com.strobel.decompiler.ast.TypeAnalysis.run(TypeAnalysis.java:96)
        //     at com.strobel.decompiler.ast.AstOptimizer.optimize(AstOptimizer.java:109)
        //     at com.strobel.decompiler.ast.AstOptimizer.optimize(AstOptimizer.java:42)
        //     at com.strobel.decompiler.languages.java.ast.AstMethodBodyBuilder.createMethodBody(AstMethodBodyBuilder.java:214)
        //     at com.strobel.decompiler.languages.java.ast.AstMethodBodyBuilder.createMethodBody(AstMethodBodyBuilder.java:99)
        //     at com.strobel.decompiler.languages.java.ast.AstBuilder.createMethodBody(AstBuilder.java:757)
        //     at com.strobel.decompiler.languages.java.ast.AstBuilder.createMethod(AstBuilder.java:655)
        //     at com.strobel.decompiler.languages.java.ast.AstBuilder.addTypeMembers(AstBuilder.java:532)
        //     at com.strobel.decompiler.languages.java.ast.AstBuilder.createTypeCore(AstBuilder.java:499)
        //     at com.strobel.decompiler.languages.java.ast.AstBuilder.createTypeNoCache(AstBuilder.java:141)
        //     at com.strobel.decompiler.languages.java.ast.AstBuilder.createType(AstBuilder.java:130)
        //     at com.strobel.decompiler.languages.java.ast.AstBuilder.addType(AstBuilder.java:105)
        //     at com.strobel.decompiler.languages.java.JavaLanguage.buildAst(JavaLanguage.java:71)
        //     at com.strobel.decompiler.languages.java.JavaLanguage.decompileType(JavaLanguage.java:59)
        //     at com.strobel.decompiler.DecompilerDriver.decompileType(DecompilerDriver.java:317)
        //     at com.strobel.decompiler.DecompilerDriver.decompileJar(DecompilerDriver.java:238)
        //     at com.strobel.decompiler.DecompilerDriver.main(DecompilerDriver.java:138)
        // 
        throw new IllegalStateException("An error occurred while decompiling this method.");
    }
    
    public void markNotificationAsRead(final IrisNotificationSummary p0, final BrowseAgentCallback p1) {
        // 
        // This method could not be decompiled.
        // 
        // Original Bytecode:
        // 
        //     0: aload_0        
        //     1: new             new            !!! ERROR
        //     4: dup            
        //     5: aload_0        
        //     6: aload_1        
        //     7: aload_2        
        //     8: invokespecial   invokespecial  !!! ERROR
        //    11: invokespecial   com/netflix/falkor/CachedModelProxy.launchTask:(Ljava/lang/Runnable;)V
        //    14: return         
        // 
        // The error that occurred was:
        // 
        // java.lang.IllegalArgumentException: Argument 'typeArguments' must not have any null elements.
        //     at com.strobel.core.VerifyArgument.noNullElementsAndNotEmpty(VerifyArgument.java:145)
        //     at com.strobel.assembler.metadata.CoreMetadataFactory$UnresolvedType.makeGenericType(CoreMetadataFactory.java:570)
        //     at com.strobel.assembler.metadata.CoreMetadataFactory.makeParameterizedType(CoreMetadataFactory.java:156)
        //     at com.strobel.assembler.metadata.signatures.Reifier.visitClassTypeSignature(Reifier.java:125)
        //     at com.strobel.assembler.metadata.signatures.ClassTypeSignature.accept(ClassTypeSignature.java:46)
        //     at com.strobel.assembler.metadata.MetadataParser.parseClassSignature(MetadataParser.java:394)
        //     at com.strobel.assembler.metadata.ClassFileReader.populateBaseTypes(ClassFileReader.java:665)
        //     at com.strobel.assembler.metadata.ClassFileReader.readClass(ClassFileReader.java:438)
        //     at com.strobel.assembler.metadata.ClassFileReader.readClass(ClassFileReader.java:366)
        //     at com.strobel.assembler.metadata.MetadataSystem.resolveType(MetadataSystem.java:124)
        //     at com.strobel.decompiler.NoRetryMetadataSystem.resolveType(DecompilerDriver.java:463)
        //     at com.strobel.assembler.metadata.MetadataSystem.resolveCore(MetadataSystem.java:76)
        //     at com.strobel.assembler.metadata.MetadataResolver.resolve(MetadataResolver.java:104)
        //     at com.strobel.assembler.metadata.CoreMetadataFactory$UnresolvedType.resolve(CoreMetadataFactory.java:589)
        //     at com.strobel.assembler.metadata.MetadataResolver.resolve(MetadataResolver.java:128)
        //     at com.strobel.assembler.metadata.CoreMetadataFactory$UnresolvedType.resolve(CoreMetadataFactory.java:599)
        //     at com.strobel.assembler.metadata.MethodReference.resolve(MethodReference.java:172)
        //     at com.strobel.decompiler.ast.TypeAnalysis.inferCall(TypeAnalysis.java:2428)
        //     at com.strobel.decompiler.ast.TypeAnalysis.doInferTypeForExpression(TypeAnalysis.java:1029)
        //     at com.strobel.decompiler.ast.TypeAnalysis.inferTypeForExpression(TypeAnalysis.java:803)
        //     at com.strobel.decompiler.ast.TypeAnalysis.runInference(TypeAnalysis.java:672)
        //     at com.strobel.decompiler.ast.TypeAnalysis.runInference(TypeAnalysis.java:655)
        //     at com.strobel.decompiler.ast.TypeAnalysis.runInference(TypeAnalysis.java:365)
        //     at com.strobel.decompiler.ast.TypeAnalysis.run(TypeAnalysis.java:96)
        //     at com.strobel.decompiler.ast.AstOptimizer.optimize(AstOptimizer.java:109)
        //     at com.strobel.decompiler.ast.AstOptimizer.optimize(AstOptimizer.java:42)
        //     at com.strobel.decompiler.languages.java.ast.AstMethodBodyBuilder.createMethodBody(AstMethodBodyBuilder.java:214)
        //     at com.strobel.decompiler.languages.java.ast.AstMethodBodyBuilder.createMethodBody(AstMethodBodyBuilder.java:99)
        //     at com.strobel.decompiler.languages.java.ast.AstBuilder.createMethodBody(AstBuilder.java:757)
        //     at com.strobel.decompiler.languages.java.ast.AstBuilder.createMethod(AstBuilder.java:655)
        //     at com.strobel.decompiler.languages.java.ast.AstBuilder.addTypeMembers(AstBuilder.java:532)
        //     at com.strobel.decompiler.languages.java.ast.AstBuilder.createTypeCore(AstBuilder.java:499)
        //     at com.strobel.decompiler.languages.java.ast.AstBuilder.createTypeNoCache(AstBuilder.java:141)
        //     at com.strobel.decompiler.languages.java.ast.AstBuilder.createType(AstBuilder.java:130)
        //     at com.strobel.decompiler.languages.java.ast.AstBuilder.addType(AstBuilder.java:105)
        //     at com.strobel.decompiler.languages.java.JavaLanguage.buildAst(JavaLanguage.java:71)
        //     at com.strobel.decompiler.languages.java.JavaLanguage.decompileType(JavaLanguage.java:59)
        //     at com.strobel.decompiler.DecompilerDriver.decompileType(DecompilerDriver.java:317)
        //     at com.strobel.decompiler.DecompilerDriver.decompileJar(DecompilerDriver.java:238)
        //     at com.strobel.decompiler.DecompilerDriver.main(DecompilerDriver.java:138)
        // 
        throw new IllegalStateException("An error occurred while decompiling this method.");
    }
    
    public void markNotificationsAsRead(final List<IrisNotificationSummary> p0, final BrowseAgentCallback p1) {
        // 
        // This method could not be decompiled.
        // 
        // Original Bytecode:
        // 
        //     0: aload_0        
        //     1: new             new            !!! ERROR
        //     4: dup            
        //     5: aload_0        
        //     6: aload_1        
        //     7: aload_2        
        //     8: invokespecial   invokespecial  !!! ERROR
        //    11: invokespecial   com/netflix/falkor/CachedModelProxy.launchTask:(Ljava/lang/Runnable;)V
        //    14: return         
        //    Signature:
        //  (Ljava/util/List<Lcom/netflix/model/leafs/social/IrisNotificationSummary;>;Lcom/netflix/mediaclient/service/browse/BrowseAgentCallback;)V
        // 
        // The error that occurred was:
        // 
        // java.lang.IllegalArgumentException: Argument 'typeArguments' must not have any null elements.
        //     at com.strobel.core.VerifyArgument.noNullElementsAndNotEmpty(VerifyArgument.java:145)
        //     at com.strobel.assembler.metadata.CoreMetadataFactory$UnresolvedType.makeGenericType(CoreMetadataFactory.java:570)
        //     at com.strobel.assembler.metadata.CoreMetadataFactory.makeParameterizedType(CoreMetadataFactory.java:156)
        //     at com.strobel.assembler.metadata.signatures.Reifier.visitClassTypeSignature(Reifier.java:125)
        //     at com.strobel.assembler.metadata.signatures.ClassTypeSignature.accept(ClassTypeSignature.java:46)
        //     at com.strobel.assembler.metadata.MetadataParser.parseClassSignature(MetadataParser.java:394)
        //     at com.strobel.assembler.metadata.ClassFileReader.populateBaseTypes(ClassFileReader.java:665)
        //     at com.strobel.assembler.metadata.ClassFileReader.readClass(ClassFileReader.java:438)
        //     at com.strobel.assembler.metadata.ClassFileReader.readClass(ClassFileReader.java:366)
        //     at com.strobel.assembler.metadata.MetadataSystem.resolveType(MetadataSystem.java:124)
        //     at com.strobel.decompiler.NoRetryMetadataSystem.resolveType(DecompilerDriver.java:463)
        //     at com.strobel.assembler.metadata.MetadataSystem.resolveCore(MetadataSystem.java:76)
        //     at com.strobel.assembler.metadata.MetadataResolver.resolve(MetadataResolver.java:104)
        //     at com.strobel.assembler.metadata.CoreMetadataFactory$UnresolvedType.resolve(CoreMetadataFactory.java:589)
        //     at com.strobel.assembler.metadata.MetadataResolver.resolve(MetadataResolver.java:128)
        //     at com.strobel.assembler.metadata.CoreMetadataFactory$UnresolvedType.resolve(CoreMetadataFactory.java:599)
        //     at com.strobel.assembler.metadata.MethodReference.resolve(MethodReference.java:172)
        //     at com.strobel.decompiler.ast.TypeAnalysis.inferCall(TypeAnalysis.java:2428)
        //     at com.strobel.decompiler.ast.TypeAnalysis.doInferTypeForExpression(TypeAnalysis.java:1029)
        //     at com.strobel.decompiler.ast.TypeAnalysis.inferTypeForExpression(TypeAnalysis.java:803)
        //     at com.strobel.decompiler.ast.TypeAnalysis.runInference(TypeAnalysis.java:672)
        //     at com.strobel.decompiler.ast.TypeAnalysis.runInference(TypeAnalysis.java:655)
        //     at com.strobel.decompiler.ast.TypeAnalysis.runInference(TypeAnalysis.java:365)
        //     at com.strobel.decompiler.ast.TypeAnalysis.run(TypeAnalysis.java:96)
        //     at com.strobel.decompiler.ast.AstOptimizer.optimize(AstOptimizer.java:109)
        //     at com.strobel.decompiler.ast.AstOptimizer.optimize(AstOptimizer.java:42)
        //     at com.strobel.decompiler.languages.java.ast.AstMethodBodyBuilder.createMethodBody(AstMethodBodyBuilder.java:214)
        //     at com.strobel.decompiler.languages.java.ast.AstMethodBodyBuilder.createMethodBody(AstMethodBodyBuilder.java:99)
        //     at com.strobel.decompiler.languages.java.ast.AstBuilder.createMethodBody(AstBuilder.java:757)
        //     at com.strobel.decompiler.languages.java.ast.AstBuilder.createMethod(AstBuilder.java:655)
        //     at com.strobel.decompiler.languages.java.ast.AstBuilder.addTypeMembers(AstBuilder.java:532)
        //     at com.strobel.decompiler.languages.java.ast.AstBuilder.createTypeCore(AstBuilder.java:499)
        //     at com.strobel.decompiler.languages.java.ast.AstBuilder.createTypeNoCache(AstBuilder.java:141)
        //     at com.strobel.decompiler.languages.java.ast.AstBuilder.createType(AstBuilder.java:130)
        //     at com.strobel.decompiler.languages.java.ast.AstBuilder.addType(AstBuilder.java:105)
        //     at com.strobel.decompiler.languages.java.JavaLanguage.buildAst(JavaLanguage.java:71)
        //     at com.strobel.decompiler.languages.java.JavaLanguage.decompileType(JavaLanguage.java:59)
        //     at com.strobel.decompiler.DecompilerDriver.decompileType(DecompilerDriver.java:317)
        //     at com.strobel.decompiler.DecompilerDriver.decompileJar(DecompilerDriver.java:238)
        //     at com.strobel.decompiler.DecompilerDriver.main(DecompilerDriver.java:138)
        // 
        throw new IllegalStateException("An error occurred while decompiling this method.");
    }
    
    public void prefetchGenreLoLoMo(final String p0, final int p1, final int p2, final int p3, final int p4, final boolean p5, final BrowseAgentCallback p6) {
        // 
        // This method could not be decompiled.
        // 
        // Original Bytecode:
        // 
        //     0: aload_0        
        //     1: new             new            !!! ERROR
        //     4: dup            
        //     5: aload_0        
        //     6: aload_1        
        //     7: iload_3        
        //     8: iload           5
        //    10: iload           6
        //    12: aload           7
        //    14: invokespecial   invokespecial  !!! ERROR
        //    17: invokespecial   com/netflix/falkor/CachedModelProxy.launchTask:(Ljava/lang/Runnable;)V
        //    20: return         
        // 
        // The error that occurred was:
        // 
        // java.lang.IllegalArgumentException: Argument 'typeArguments' must not have any null elements.
        //     at com.strobel.core.VerifyArgument.noNullElementsAndNotEmpty(VerifyArgument.java:145)
        //     at com.strobel.assembler.metadata.CoreMetadataFactory$UnresolvedType.makeGenericType(CoreMetadataFactory.java:570)
        //     at com.strobel.assembler.metadata.CoreMetadataFactory.makeParameterizedType(CoreMetadataFactory.java:156)
        //     at com.strobel.assembler.metadata.signatures.Reifier.visitClassTypeSignature(Reifier.java:125)
        //     at com.strobel.assembler.metadata.signatures.ClassTypeSignature.accept(ClassTypeSignature.java:46)
        //     at com.strobel.assembler.metadata.MetadataParser.parseClassSignature(MetadataParser.java:394)
        //     at com.strobel.assembler.metadata.ClassFileReader.populateBaseTypes(ClassFileReader.java:665)
        //     at com.strobel.assembler.metadata.ClassFileReader.readClass(ClassFileReader.java:438)
        //     at com.strobel.assembler.metadata.ClassFileReader.readClass(ClassFileReader.java:366)
        //     at com.strobel.assembler.metadata.MetadataSystem.resolveType(MetadataSystem.java:124)
        //     at com.strobel.decompiler.NoRetryMetadataSystem.resolveType(DecompilerDriver.java:463)
        //     at com.strobel.assembler.metadata.MetadataSystem.resolveCore(MetadataSystem.java:76)
        //     at com.strobel.assembler.metadata.MetadataResolver.resolve(MetadataResolver.java:104)
        //     at com.strobel.assembler.metadata.CoreMetadataFactory$UnresolvedType.resolve(CoreMetadataFactory.java:589)
        //     at com.strobel.assembler.metadata.MetadataResolver.resolve(MetadataResolver.java:128)
        //     at com.strobel.assembler.metadata.CoreMetadataFactory$UnresolvedType.resolve(CoreMetadataFactory.java:599)
        //     at com.strobel.assembler.metadata.MethodReference.resolve(MethodReference.java:172)
        //     at com.strobel.decompiler.ast.TypeAnalysis.inferCall(TypeAnalysis.java:2428)
        //     at com.strobel.decompiler.ast.TypeAnalysis.doInferTypeForExpression(TypeAnalysis.java:1029)
        //     at com.strobel.decompiler.ast.TypeAnalysis.inferTypeForExpression(TypeAnalysis.java:803)
        //     at com.strobel.decompiler.ast.TypeAnalysis.runInference(TypeAnalysis.java:672)
        //     at com.strobel.decompiler.ast.TypeAnalysis.runInference(TypeAnalysis.java:655)
        //     at com.strobel.decompiler.ast.TypeAnalysis.runInference(TypeAnalysis.java:365)
        //     at com.strobel.decompiler.ast.TypeAnalysis.run(TypeAnalysis.java:96)
        //     at com.strobel.decompiler.ast.AstOptimizer.optimize(AstOptimizer.java:109)
        //     at com.strobel.decompiler.ast.AstOptimizer.optimize(AstOptimizer.java:42)
        //     at com.strobel.decompiler.languages.java.ast.AstMethodBodyBuilder.createMethodBody(AstMethodBodyBuilder.java:214)
        //     at com.strobel.decompiler.languages.java.ast.AstMethodBodyBuilder.createMethodBody(AstMethodBodyBuilder.java:99)
        //     at com.strobel.decompiler.languages.java.ast.AstBuilder.createMethodBody(AstBuilder.java:757)
        //     at com.strobel.decompiler.languages.java.ast.AstBuilder.createMethod(AstBuilder.java:655)
        //     at com.strobel.decompiler.languages.java.ast.AstBuilder.addTypeMembers(AstBuilder.java:532)
        //     at com.strobel.decompiler.languages.java.ast.AstBuilder.createTypeCore(AstBuilder.java:499)
        //     at com.strobel.decompiler.languages.java.ast.AstBuilder.createTypeNoCache(AstBuilder.java:141)
        //     at com.strobel.decompiler.languages.java.ast.AstBuilder.createType(AstBuilder.java:130)
        //     at com.strobel.decompiler.languages.java.ast.AstBuilder.addType(AstBuilder.java:105)
        //     at com.strobel.decompiler.languages.java.JavaLanguage.buildAst(JavaLanguage.java:71)
        //     at com.strobel.decompiler.languages.java.JavaLanguage.decompileType(JavaLanguage.java:59)
        //     at com.strobel.decompiler.DecompilerDriver.decompileType(DecompilerDriver.java:317)
        //     at com.strobel.decompiler.DecompilerDriver.decompileJar(DecompilerDriver.java:238)
        //     at com.strobel.decompiler.DecompilerDriver.main(DecompilerDriver.java:138)
        // 
        throw new IllegalStateException("An error occurred while decompiling this method.");
    }
    
    public void prefetchLoLoMo(final int p0, final int p1, final int p2, final int p3, final int p4, final int p5, final boolean p6, final boolean p7, final boolean p8, final BrowseAgentCallback p9) {
        // 
        // This method could not be decompiled.
        // 
        // Original Bytecode:
        // 
        //     0: aload_0        
        //     1: iload_3        
        //     2: putfield        com/netflix/falkor/CachedModelProxy.lastPrefetchFromVideo:I
        //     5: aload_0        
        //     6: iload           4
        //     8: putfield        com/netflix/falkor/CachedModelProxy.lastPrefetchToVideo:I
        //    11: aload_0        
        //    12: new             new            !!! ERROR
        //    15: dup            
        //    16: aload_0        
        //    17: iload_2        
        //    18: iload           4
        //    20: iload           6
        //    22: bipush          9
        //    24: iload           7
        //    26: iload           8
        //    28: aload           10
        //    30: invokespecial   invokespecial  !!! ERROR
        //    33: invokespecial   com/netflix/falkor/CachedModelProxy.launchTask:(Ljava/lang/Runnable;)V
        //    36: return         
        // 
        // The error that occurred was:
        // 
        // java.lang.IllegalArgumentException: Argument 'typeArguments' must not have any null elements.
        //     at com.strobel.core.VerifyArgument.noNullElementsAndNotEmpty(VerifyArgument.java:145)
        //     at com.strobel.assembler.metadata.CoreMetadataFactory$UnresolvedType.makeGenericType(CoreMetadataFactory.java:570)
        //     at com.strobel.assembler.metadata.CoreMetadataFactory.makeParameterizedType(CoreMetadataFactory.java:156)
        //     at com.strobel.assembler.metadata.signatures.Reifier.visitClassTypeSignature(Reifier.java:125)
        //     at com.strobel.assembler.metadata.signatures.ClassTypeSignature.accept(ClassTypeSignature.java:46)
        //     at com.strobel.assembler.metadata.MetadataParser.parseClassSignature(MetadataParser.java:394)
        //     at com.strobel.assembler.metadata.ClassFileReader.populateBaseTypes(ClassFileReader.java:665)
        //     at com.strobel.assembler.metadata.ClassFileReader.readClass(ClassFileReader.java:438)
        //     at com.strobel.assembler.metadata.ClassFileReader.readClass(ClassFileReader.java:366)
        //     at com.strobel.assembler.metadata.MetadataSystem.resolveType(MetadataSystem.java:124)
        //     at com.strobel.decompiler.NoRetryMetadataSystem.resolveType(DecompilerDriver.java:463)
        //     at com.strobel.assembler.metadata.MetadataSystem.resolveCore(MetadataSystem.java:76)
        //     at com.strobel.assembler.metadata.MetadataResolver.resolve(MetadataResolver.java:104)
        //     at com.strobel.assembler.metadata.CoreMetadataFactory$UnresolvedType.resolve(CoreMetadataFactory.java:589)
        //     at com.strobel.assembler.metadata.MetadataResolver.resolve(MetadataResolver.java:128)
        //     at com.strobel.assembler.metadata.CoreMetadataFactory$UnresolvedType.resolve(CoreMetadataFactory.java:599)
        //     at com.strobel.assembler.metadata.MethodReference.resolve(MethodReference.java:172)
        //     at com.strobel.decompiler.ast.TypeAnalysis.inferCall(TypeAnalysis.java:2428)
        //     at com.strobel.decompiler.ast.TypeAnalysis.doInferTypeForExpression(TypeAnalysis.java:1029)
        //     at com.strobel.decompiler.ast.TypeAnalysis.inferTypeForExpression(TypeAnalysis.java:803)
        //     at com.strobel.decompiler.ast.TypeAnalysis.runInference(TypeAnalysis.java:672)
        //     at com.strobel.decompiler.ast.TypeAnalysis.runInference(TypeAnalysis.java:655)
        //     at com.strobel.decompiler.ast.TypeAnalysis.runInference(TypeAnalysis.java:365)
        //     at com.strobel.decompiler.ast.TypeAnalysis.run(TypeAnalysis.java:96)
        //     at com.strobel.decompiler.ast.AstOptimizer.optimize(AstOptimizer.java:109)
        //     at com.strobel.decompiler.ast.AstOptimizer.optimize(AstOptimizer.java:42)
        //     at com.strobel.decompiler.languages.java.ast.AstMethodBodyBuilder.createMethodBody(AstMethodBodyBuilder.java:214)
        //     at com.strobel.decompiler.languages.java.ast.AstMethodBodyBuilder.createMethodBody(AstMethodBodyBuilder.java:99)
        //     at com.strobel.decompiler.languages.java.ast.AstBuilder.createMethodBody(AstBuilder.java:757)
        //     at com.strobel.decompiler.languages.java.ast.AstBuilder.createMethod(AstBuilder.java:655)
        //     at com.strobel.decompiler.languages.java.ast.AstBuilder.addTypeMembers(AstBuilder.java:532)
        //     at com.strobel.decompiler.languages.java.ast.AstBuilder.createTypeCore(AstBuilder.java:499)
        //     at com.strobel.decompiler.languages.java.ast.AstBuilder.createTypeNoCache(AstBuilder.java:141)
        //     at com.strobel.decompiler.languages.java.ast.AstBuilder.createType(AstBuilder.java:130)
        //     at com.strobel.decompiler.languages.java.ast.AstBuilder.addType(AstBuilder.java:105)
        //     at com.strobel.decompiler.languages.java.JavaLanguage.buildAst(JavaLanguage.java:71)
        //     at com.strobel.decompiler.languages.java.JavaLanguage.decompileType(JavaLanguage.java:59)
        //     at com.strobel.decompiler.DecompilerDriver.decompileType(DecompilerDriver.java:317)
        //     at com.strobel.decompiler.DecompilerDriver.decompileJar(DecompilerDriver.java:238)
        //     at com.strobel.decompiler.DecompilerDriver.main(DecompilerDriver.java:138)
        // 
        throw new IllegalStateException("An error occurred while decompiling this method.");
    }
    
    public void refreshCw() {
        // 
        // This method could not be decompiled.
        // 
        // Original Bytecode:
        // 
        //     0: aload_0        
        //     1: invokevirtual   com/netflix/falkor/CachedModelProxy.doesCwExist:()Z
        //     4: ifne            17
        //     7: ldc             "CachedModelProxy"
        //     9: ldc_w           "Can't refresh CW "
        //    12: invokestatic    com/netflix/mediaclient/Log.d:(Ljava/lang/String;Ljava/lang/String;)I
        //    15: pop            
        //    16: return         
        //    17: aload_0        
        //    18: invokespecial   com/netflix/falkor/CachedModelProxy.getCurrLolomoId:()Ljava/lang/String;
        //    21: astore_1       
        //    22: aload_0        
        //    23: getstatic       com/netflix/mediaclient/servicemgr/interface_/LoMoType.CONTINUE_WATCHING:Lcom/netflix/mediaclient/servicemgr/interface_/LoMoType;
        //    26: invokespecial   com/netflix/falkor/CachedModelProxy.getCurrLomoInfo:(Lcom/netflix/mediaclient/servicemgr/interface_/LoMoType;)Lcom/netflix/mediaclient/util/DataUtil$StringPair;
        //    29: astore_2       
        //    30: aload_0        
        //    31: new             new            !!! ERROR
        //    34: dup            
        //    35: aload_0        
        //    36: aload_1        
        //    37: aload_2        
        //    38: getfield        com/netflix/mediaclient/util/DataUtil$StringPair.first:Ljava/lang/Object;
        //    41: checkcast       Ljava/lang/String;
        //    44: aload_2        
        //    45: getfield        com/netflix/mediaclient/util/DataUtil$StringPair.second:Ljava/lang/Object;
        //    48: checkcast       Ljava/lang/String;
        //    51: invokespecial   invokespecial  !!! ERROR
        //    54: invokespecial   com/netflix/falkor/CachedModelProxy.launchTask:(Ljava/lang/Runnable;)V
        //    57: return         
        // 
        // The error that occurred was:
        // 
        // java.lang.IllegalArgumentException: Argument 'typeArguments' must not have any null elements.
        //     at com.strobel.core.VerifyArgument.noNullElementsAndNotEmpty(VerifyArgument.java:145)
        //     at com.strobel.assembler.metadata.CoreMetadataFactory$UnresolvedType.makeGenericType(CoreMetadataFactory.java:570)
        //     at com.strobel.assembler.metadata.CoreMetadataFactory.makeParameterizedType(CoreMetadataFactory.java:156)
        //     at com.strobel.assembler.metadata.signatures.Reifier.visitClassTypeSignature(Reifier.java:125)
        //     at com.strobel.assembler.metadata.signatures.ClassTypeSignature.accept(ClassTypeSignature.java:46)
        //     at com.strobel.assembler.metadata.MetadataParser.parseClassSignature(MetadataParser.java:394)
        //     at com.strobel.assembler.metadata.ClassFileReader.populateBaseTypes(ClassFileReader.java:665)
        //     at com.strobel.assembler.metadata.ClassFileReader.readClass(ClassFileReader.java:438)
        //     at com.strobel.assembler.metadata.ClassFileReader.readClass(ClassFileReader.java:366)
        //     at com.strobel.assembler.metadata.MetadataSystem.resolveType(MetadataSystem.java:124)
        //     at com.strobel.decompiler.NoRetryMetadataSystem.resolveType(DecompilerDriver.java:463)
        //     at com.strobel.assembler.metadata.MetadataSystem.resolveCore(MetadataSystem.java:76)
        //     at com.strobel.assembler.metadata.MetadataResolver.resolve(MetadataResolver.java:104)
        //     at com.strobel.assembler.metadata.CoreMetadataFactory$UnresolvedType.resolve(CoreMetadataFactory.java:589)
        //     at com.strobel.assembler.metadata.MetadataResolver.resolve(MetadataResolver.java:128)
        //     at com.strobel.assembler.metadata.CoreMetadataFactory$UnresolvedType.resolve(CoreMetadataFactory.java:599)
        //     at com.strobel.assembler.metadata.MethodReference.resolve(MethodReference.java:172)
        //     at com.strobel.decompiler.ast.TypeAnalysis.inferCall(TypeAnalysis.java:2428)
        //     at com.strobel.decompiler.ast.TypeAnalysis.doInferTypeForExpression(TypeAnalysis.java:1029)
        //     at com.strobel.decompiler.ast.TypeAnalysis.inferTypeForExpression(TypeAnalysis.java:803)
        //     at com.strobel.decompiler.ast.TypeAnalysis.runInference(TypeAnalysis.java:672)
        //     at com.strobel.decompiler.ast.TypeAnalysis.runInference(TypeAnalysis.java:655)
        //     at com.strobel.decompiler.ast.TypeAnalysis.runInference(TypeAnalysis.java:365)
        //     at com.strobel.decompiler.ast.TypeAnalysis.run(TypeAnalysis.java:96)
        //     at com.strobel.decompiler.ast.AstOptimizer.optimize(AstOptimizer.java:109)
        //     at com.strobel.decompiler.ast.AstOptimizer.optimize(AstOptimizer.java:42)
        //     at com.strobel.decompiler.languages.java.ast.AstMethodBodyBuilder.createMethodBody(AstMethodBodyBuilder.java:214)
        //     at com.strobel.decompiler.languages.java.ast.AstMethodBodyBuilder.createMethodBody(AstMethodBodyBuilder.java:99)
        //     at com.strobel.decompiler.languages.java.ast.AstBuilder.createMethodBody(AstBuilder.java:757)
        //     at com.strobel.decompiler.languages.java.ast.AstBuilder.createMethod(AstBuilder.java:655)
        //     at com.strobel.decompiler.languages.java.ast.AstBuilder.addTypeMembers(AstBuilder.java:532)
        //     at com.strobel.decompiler.languages.java.ast.AstBuilder.createTypeCore(AstBuilder.java:499)
        //     at com.strobel.decompiler.languages.java.ast.AstBuilder.createTypeNoCache(AstBuilder.java:141)
        //     at com.strobel.decompiler.languages.java.ast.AstBuilder.createType(AstBuilder.java:130)
        //     at com.strobel.decompiler.languages.java.ast.AstBuilder.addType(AstBuilder.java:105)
        //     at com.strobel.decompiler.languages.java.JavaLanguage.buildAst(JavaLanguage.java:71)
        //     at com.strobel.decompiler.languages.java.JavaLanguage.decompileType(JavaLanguage.java:59)
        //     at com.strobel.decompiler.DecompilerDriver.decompileType(DecompilerDriver.java:317)
        //     at com.strobel.decompiler.DecompilerDriver.decompileJar(DecompilerDriver.java:238)
        //     at com.strobel.decompiler.DecompilerDriver.main(DecompilerDriver.java:138)
        // 
        throw new IllegalStateException("An error occurred while decompiling this method.");
    }
    
    public void refreshIq() {
        // 
        // This method could not be decompiled.
        // 
        // Original Bytecode:
        // 
        //     0: aload_0        
        //     1: invokespecial   com/netflix/falkor/CachedModelProxy.getCurrLolomoId:()Ljava/lang/String;
        //     4: astore_1       
        //     5: aload_0        
        //     6: getstatic       com/netflix/mediaclient/servicemgr/interface_/LoMoType.INSTANT_QUEUE:Lcom/netflix/mediaclient/servicemgr/interface_/LoMoType;
        //     9: invokespecial   com/netflix/falkor/CachedModelProxy.getCurrLomoInfo:(Lcom/netflix/mediaclient/servicemgr/interface_/LoMoType;)Lcom/netflix/mediaclient/util/DataUtil$StringPair;
        //    12: astore_2       
        //    13: aload_1        
        //    14: invokestatic    com/netflix/mediaclient/util/StringUtils.isEmpty:(Ljava/lang/String;)Z
        //    17: ifeq            30
        //    20: ldc             "CachedModelProxy"
        //    22: ldc_w           "Can't refresh IQ - lolomoId is empty"
        //    25: invokestatic    com/netflix/mediaclient/Log.d:(Ljava/lang/String;Ljava/lang/String;)I
        //    28: pop            
        //    29: return         
        //    30: aload_2        
        //    31: getfield        com/netflix/mediaclient/util/DataUtil$StringPair.first:Ljava/lang/Object;
        //    34: checkcast       Ljava/lang/String;
        //    37: invokestatic    com/netflix/mediaclient/util/StringUtils.isEmpty:(Ljava/lang/String;)Z
        //    40: ifeq            53
        //    43: ldc             "CachedModelProxy"
        //    45: ldc_w           "Can't refresh IQ - lomo id is empty"
        //    48: invokestatic    com/netflix/mediaclient/Log.d:(Ljava/lang/String;Ljava/lang/String;)I
        //    51: pop            
        //    52: return         
        //    53: iconst_m1      
        //    54: invokestatic    java/lang/String.valueOf:(I)Ljava/lang/String;
        //    57: aload_2        
        //    58: getfield        com/netflix/mediaclient/util/DataUtil$StringPair.second:Ljava/lang/Object;
        //    61: invokevirtual   java/lang/String.equals:(Ljava/lang/Object;)Z
        //    64: ifeq            77
        //    67: ldc             "CachedModelProxy"
        //    69: ldc_w           "Can't refresh IQ - lomo index is invalid"
        //    72: invokestatic    com/netflix/mediaclient/Log.d:(Ljava/lang/String;Ljava/lang/String;)I
        //    75: pop            
        //    76: return         
        //    77: aload_0        
        //    78: new             new            !!! ERROR
        //    81: dup            
        //    82: aload_0        
        //    83: aload_1        
        //    84: aload_2        
        //    85: getfield        com/netflix/mediaclient/util/DataUtil$StringPair.first:Ljava/lang/Object;
        //    88: checkcast       Ljava/lang/String;
        //    91: aload_2        
        //    92: getfield        com/netflix/mediaclient/util/DataUtil$StringPair.second:Ljava/lang/Object;
        //    95: checkcast       Ljava/lang/String;
        //    98: invokespecial   invokespecial  !!! ERROR
        //   101: invokespecial   com/netflix/falkor/CachedModelProxy.launchTask:(Ljava/lang/Runnable;)V
        //   104: return         
        // 
        // The error that occurred was:
        // 
        // java.lang.IllegalArgumentException: Argument 'typeArguments' must not have any null elements.
        //     at com.strobel.core.VerifyArgument.noNullElementsAndNotEmpty(VerifyArgument.java:145)
        //     at com.strobel.assembler.metadata.CoreMetadataFactory$UnresolvedType.makeGenericType(CoreMetadataFactory.java:570)
        //     at com.strobel.assembler.metadata.CoreMetadataFactory.makeParameterizedType(CoreMetadataFactory.java:156)
        //     at com.strobel.assembler.metadata.signatures.Reifier.visitClassTypeSignature(Reifier.java:125)
        //     at com.strobel.assembler.metadata.signatures.ClassTypeSignature.accept(ClassTypeSignature.java:46)
        //     at com.strobel.assembler.metadata.MetadataParser.parseClassSignature(MetadataParser.java:394)
        //     at com.strobel.assembler.metadata.ClassFileReader.populateBaseTypes(ClassFileReader.java:665)
        //     at com.strobel.assembler.metadata.ClassFileReader.readClass(ClassFileReader.java:438)
        //     at com.strobel.assembler.metadata.ClassFileReader.readClass(ClassFileReader.java:366)
        //     at com.strobel.assembler.metadata.MetadataSystem.resolveType(MetadataSystem.java:124)
        //     at com.strobel.decompiler.NoRetryMetadataSystem.resolveType(DecompilerDriver.java:463)
        //     at com.strobel.assembler.metadata.MetadataSystem.resolveCore(MetadataSystem.java:76)
        //     at com.strobel.assembler.metadata.MetadataResolver.resolve(MetadataResolver.java:104)
        //     at com.strobel.assembler.metadata.CoreMetadataFactory$UnresolvedType.resolve(CoreMetadataFactory.java:589)
        //     at com.strobel.assembler.metadata.MetadataResolver.resolve(MetadataResolver.java:128)
        //     at com.strobel.assembler.metadata.CoreMetadataFactory$UnresolvedType.resolve(CoreMetadataFactory.java:599)
        //     at com.strobel.assembler.metadata.MethodReference.resolve(MethodReference.java:172)
        //     at com.strobel.decompiler.ast.TypeAnalysis.inferCall(TypeAnalysis.java:2428)
        //     at com.strobel.decompiler.ast.TypeAnalysis.doInferTypeForExpression(TypeAnalysis.java:1029)
        //     at com.strobel.decompiler.ast.TypeAnalysis.inferTypeForExpression(TypeAnalysis.java:803)
        //     at com.strobel.decompiler.ast.TypeAnalysis.runInference(TypeAnalysis.java:672)
        //     at com.strobel.decompiler.ast.TypeAnalysis.runInference(TypeAnalysis.java:655)
        //     at com.strobel.decompiler.ast.TypeAnalysis.runInference(TypeAnalysis.java:365)
        //     at com.strobel.decompiler.ast.TypeAnalysis.run(TypeAnalysis.java:96)
        //     at com.strobel.decompiler.ast.AstOptimizer.optimize(AstOptimizer.java:109)
        //     at com.strobel.decompiler.ast.AstOptimizer.optimize(AstOptimizer.java:42)
        //     at com.strobel.decompiler.languages.java.ast.AstMethodBodyBuilder.createMethodBody(AstMethodBodyBuilder.java:214)
        //     at com.strobel.decompiler.languages.java.ast.AstMethodBodyBuilder.createMethodBody(AstMethodBodyBuilder.java:99)
        //     at com.strobel.decompiler.languages.java.ast.AstBuilder.createMethodBody(AstBuilder.java:757)
        //     at com.strobel.decompiler.languages.java.ast.AstBuilder.createMethod(AstBuilder.java:655)
        //     at com.strobel.decompiler.languages.java.ast.AstBuilder.addTypeMembers(AstBuilder.java:532)
        //     at com.strobel.decompiler.languages.java.ast.AstBuilder.createTypeCore(AstBuilder.java:499)
        //     at com.strobel.decompiler.languages.java.ast.AstBuilder.createTypeNoCache(AstBuilder.java:141)
        //     at com.strobel.decompiler.languages.java.ast.AstBuilder.createType(AstBuilder.java:130)
        //     at com.strobel.decompiler.languages.java.ast.AstBuilder.addType(AstBuilder.java:105)
        //     at com.strobel.decompiler.languages.java.JavaLanguage.buildAst(JavaLanguage.java:71)
        //     at com.strobel.decompiler.languages.java.JavaLanguage.decompileType(JavaLanguage.java:59)
        //     at com.strobel.decompiler.DecompilerDriver.decompileType(DecompilerDriver.java:317)
        //     at com.strobel.decompiler.DecompilerDriver.decompileJar(DecompilerDriver.java:238)
        //     at com.strobel.decompiler.DecompilerDriver.main(DecompilerDriver.java:138)
        // 
        throw new IllegalStateException("An error occurred while decompiling this method.");
    }
    
    public void refreshPopularTitlesLomo() {
        // 
        // This method could not be decompiled.
        // 
        // Original Bytecode:
        // 
        //     0: aload_0        
        //     1: invokespecial   com/netflix/falkor/CachedModelProxy.getCurrLolomoId:()Ljava/lang/String;
        //     4: astore_1       
        //     5: aload_0        
        //     6: getstatic       com/netflix/mediaclient/servicemgr/interface_/LoMoType.POPULAR_TITLES:Lcom/netflix/mediaclient/servicemgr/interface_/LoMoType;
        //     9: invokespecial   com/netflix/falkor/CachedModelProxy.getCurrLomoInfo:(Lcom/netflix/mediaclient/servicemgr/interface_/LoMoType;)Lcom/netflix/mediaclient/util/DataUtil$StringPair;
        //    12: astore_2       
        //    13: aload_1        
        //    14: invokestatic    com/netflix/mediaclient/util/StringUtils.isEmpty:(Ljava/lang/String;)Z
        //    17: ifeq            30
        //    20: ldc             "CachedModelProxy"
        //    22: ldc_w           "Can't refresh Popular Titles - lolomoId is empty"
        //    25: invokestatic    com/netflix/mediaclient/Log.d:(Ljava/lang/String;Ljava/lang/String;)I
        //    28: pop            
        //    29: return         
        //    30: aload_2        
        //    31: getfield        com/netflix/mediaclient/util/DataUtil$StringPair.first:Ljava/lang/Object;
        //    34: checkcast       Ljava/lang/String;
        //    37: invokestatic    com/netflix/mediaclient/util/StringUtils.isEmpty:(Ljava/lang/String;)Z
        //    40: ifeq            53
        //    43: ldc             "CachedModelProxy"
        //    45: ldc_w           "Can't refresh Popular Titles - lomo id is empty"
        //    48: invokestatic    com/netflix/mediaclient/Log.d:(Ljava/lang/String;Ljava/lang/String;)I
        //    51: pop            
        //    52: return         
        //    53: iconst_m1      
        //    54: invokestatic    java/lang/String.valueOf:(I)Ljava/lang/String;
        //    57: aload_2        
        //    58: getfield        com/netflix/mediaclient/util/DataUtil$StringPair.second:Ljava/lang/Object;
        //    61: invokevirtual   java/lang/String.equals:(Ljava/lang/Object;)Z
        //    64: ifeq            77
        //    67: ldc             "CachedModelProxy"
        //    69: ldc_w           "Can't refresh Popular Titles - lomo index is invalid"
        //    72: invokestatic    com/netflix/mediaclient/Log.d:(Ljava/lang/String;Ljava/lang/String;)I
        //    75: pop            
        //    76: return         
        //    77: aload_0        
        //    78: new             new            !!! ERROR
        //    81: dup            
        //    82: aload_0        
        //    83: aload_1        
        //    84: aload_2        
        //    85: getfield        com/netflix/mediaclient/util/DataUtil$StringPair.first:Ljava/lang/Object;
        //    88: checkcast       Ljava/lang/String;
        //    91: aload_2        
        //    92: getfield        com/netflix/mediaclient/util/DataUtil$StringPair.second:Ljava/lang/Object;
        //    95: checkcast       Ljava/lang/String;
        //    98: invokespecial   invokespecial  !!! ERROR
        //   101: invokespecial   com/netflix/falkor/CachedModelProxy.launchTask:(Ljava/lang/Runnable;)V
        //   104: return         
        // 
        // The error that occurred was:
        // 
        // java.lang.IllegalArgumentException: Argument 'typeArguments' must not have any null elements.
        //     at com.strobel.core.VerifyArgument.noNullElementsAndNotEmpty(VerifyArgument.java:145)
        //     at com.strobel.assembler.metadata.CoreMetadataFactory$UnresolvedType.makeGenericType(CoreMetadataFactory.java:570)
        //     at com.strobel.assembler.metadata.CoreMetadataFactory.makeParameterizedType(CoreMetadataFactory.java:156)
        //     at com.strobel.assembler.metadata.signatures.Reifier.visitClassTypeSignature(Reifier.java:125)
        //     at com.strobel.assembler.metadata.signatures.ClassTypeSignature.accept(ClassTypeSignature.java:46)
        //     at com.strobel.assembler.metadata.MetadataParser.parseClassSignature(MetadataParser.java:394)
        //     at com.strobel.assembler.metadata.ClassFileReader.populateBaseTypes(ClassFileReader.java:665)
        //     at com.strobel.assembler.metadata.ClassFileReader.readClass(ClassFileReader.java:438)
        //     at com.strobel.assembler.metadata.ClassFileReader.readClass(ClassFileReader.java:366)
        //     at com.strobel.assembler.metadata.MetadataSystem.resolveType(MetadataSystem.java:124)
        //     at com.strobel.decompiler.NoRetryMetadataSystem.resolveType(DecompilerDriver.java:463)
        //     at com.strobel.assembler.metadata.MetadataSystem.resolveCore(MetadataSystem.java:76)
        //     at com.strobel.assembler.metadata.MetadataResolver.resolve(MetadataResolver.java:104)
        //     at com.strobel.assembler.metadata.CoreMetadataFactory$UnresolvedType.resolve(CoreMetadataFactory.java:589)
        //     at com.strobel.assembler.metadata.MetadataResolver.resolve(MetadataResolver.java:128)
        //     at com.strobel.assembler.metadata.CoreMetadataFactory$UnresolvedType.resolve(CoreMetadataFactory.java:599)
        //     at com.strobel.assembler.metadata.MethodReference.resolve(MethodReference.java:172)
        //     at com.strobel.decompiler.ast.TypeAnalysis.inferCall(TypeAnalysis.java:2428)
        //     at com.strobel.decompiler.ast.TypeAnalysis.doInferTypeForExpression(TypeAnalysis.java:1029)
        //     at com.strobel.decompiler.ast.TypeAnalysis.inferTypeForExpression(TypeAnalysis.java:803)
        //     at com.strobel.decompiler.ast.TypeAnalysis.runInference(TypeAnalysis.java:672)
        //     at com.strobel.decompiler.ast.TypeAnalysis.runInference(TypeAnalysis.java:655)
        //     at com.strobel.decompiler.ast.TypeAnalysis.runInference(TypeAnalysis.java:365)
        //     at com.strobel.decompiler.ast.TypeAnalysis.run(TypeAnalysis.java:96)
        //     at com.strobel.decompiler.ast.AstOptimizer.optimize(AstOptimizer.java:109)
        //     at com.strobel.decompiler.ast.AstOptimizer.optimize(AstOptimizer.java:42)
        //     at com.strobel.decompiler.languages.java.ast.AstMethodBodyBuilder.createMethodBody(AstMethodBodyBuilder.java:214)
        //     at com.strobel.decompiler.languages.java.ast.AstMethodBodyBuilder.createMethodBody(AstMethodBodyBuilder.java:99)
        //     at com.strobel.decompiler.languages.java.ast.AstBuilder.createMethodBody(AstBuilder.java:757)
        //     at com.strobel.decompiler.languages.java.ast.AstBuilder.createMethod(AstBuilder.java:655)
        //     at com.strobel.decompiler.languages.java.ast.AstBuilder.addTypeMembers(AstBuilder.java:532)
        //     at com.strobel.decompiler.languages.java.ast.AstBuilder.createTypeCore(AstBuilder.java:499)
        //     at com.strobel.decompiler.languages.java.ast.AstBuilder.createTypeNoCache(AstBuilder.java:141)
        //     at com.strobel.decompiler.languages.java.ast.AstBuilder.createType(AstBuilder.java:130)
        //     at com.strobel.decompiler.languages.java.ast.AstBuilder.addType(AstBuilder.java:105)
        //     at com.strobel.decompiler.languages.java.JavaLanguage.buildAst(JavaLanguage.java:71)
        //     at com.strobel.decompiler.languages.java.JavaLanguage.decompileType(JavaLanguage.java:59)
        //     at com.strobel.decompiler.DecompilerDriver.decompileType(DecompilerDriver.java:317)
        //     at com.strobel.decompiler.DecompilerDriver.decompileJar(DecompilerDriver.java:238)
        //     at com.strobel.decompiler.DecompilerDriver.main(DecompilerDriver.java:138)
        // 
        throw new IllegalStateException("An error occurred while decompiling this method.");
    }
    
    public void removeFromQueue(final String p0, final VideoType p1, final String p2, final BrowseAgentCallback p3) {
        // 
        // This method could not be decompiled.
        // 
        // Original Bytecode:
        // 
        //     0: aload_0        
        //     1: invokespecial   com/netflix/falkor/CachedModelProxy.getCurrLolomoId:()Ljava/lang/String;
        //     4: astore          5
        //     6: aload_0        
        //     7: getstatic       com/netflix/mediaclient/servicemgr/interface_/LoMoType.INSTANT_QUEUE:Lcom/netflix/mediaclient/servicemgr/interface_/LoMoType;
        //    10: invokespecial   com/netflix/falkor/CachedModelProxy.getCurrLomoInfo:(Lcom/netflix/mediaclient/servicemgr/interface_/LoMoType;)Lcom/netflix/mediaclient/util/DataUtil$StringPair;
        //    13: astore          6
        //    15: aload_0        
        //    16: new             new            !!! ERROR
        //    19: dup            
        //    20: aload_0        
        //    21: aload_1        
        //    22: aload_2        
        //    23: aload           5
        //    25: aload           6
        //    27: getfield        com/netflix/mediaclient/util/DataUtil$StringPair.first:Ljava/lang/Object;
        //    30: checkcast       Ljava/lang/String;
        //    33: aload           6
        //    35: getfield        com/netflix/mediaclient/util/DataUtil$StringPair.second:Ljava/lang/Object;
        //    38: checkcast       Ljava/lang/String;
        //    41: aload_3        
        //    42: aload           4
        //    44: invokespecial   invokespecial  !!! ERROR
        //    47: invokespecial   com/netflix/falkor/CachedModelProxy.launchTask:(Ljava/lang/Runnable;)V
        //    50: return         
        // 
        // The error that occurred was:
        // 
        // java.lang.IllegalArgumentException: Argument 'typeArguments' must not have any null elements.
        //     at com.strobel.core.VerifyArgument.noNullElementsAndNotEmpty(VerifyArgument.java:145)
        //     at com.strobel.assembler.metadata.CoreMetadataFactory$UnresolvedType.makeGenericType(CoreMetadataFactory.java:570)
        //     at com.strobel.assembler.metadata.CoreMetadataFactory.makeParameterizedType(CoreMetadataFactory.java:156)
        //     at com.strobel.assembler.metadata.signatures.Reifier.visitClassTypeSignature(Reifier.java:125)
        //     at com.strobel.assembler.metadata.signatures.ClassTypeSignature.accept(ClassTypeSignature.java:46)
        //     at com.strobel.assembler.metadata.MetadataParser.parseClassSignature(MetadataParser.java:394)
        //     at com.strobel.assembler.metadata.ClassFileReader.populateBaseTypes(ClassFileReader.java:665)
        //     at com.strobel.assembler.metadata.ClassFileReader.readClass(ClassFileReader.java:438)
        //     at com.strobel.assembler.metadata.ClassFileReader.readClass(ClassFileReader.java:366)
        //     at com.strobel.assembler.metadata.MetadataSystem.resolveType(MetadataSystem.java:124)
        //     at com.strobel.decompiler.NoRetryMetadataSystem.resolveType(DecompilerDriver.java:463)
        //     at com.strobel.assembler.metadata.MetadataSystem.resolveCore(MetadataSystem.java:76)
        //     at com.strobel.assembler.metadata.MetadataResolver.resolve(MetadataResolver.java:104)
        //     at com.strobel.assembler.metadata.CoreMetadataFactory$UnresolvedType.resolve(CoreMetadataFactory.java:589)
        //     at com.strobel.assembler.metadata.MetadataResolver.resolve(MetadataResolver.java:128)
        //     at com.strobel.assembler.metadata.CoreMetadataFactory$UnresolvedType.resolve(CoreMetadataFactory.java:599)
        //     at com.strobel.assembler.metadata.MethodReference.resolve(MethodReference.java:172)
        //     at com.strobel.decompiler.ast.TypeAnalysis.inferCall(TypeAnalysis.java:2428)
        //     at com.strobel.decompiler.ast.TypeAnalysis.doInferTypeForExpression(TypeAnalysis.java:1029)
        //     at com.strobel.decompiler.ast.TypeAnalysis.inferTypeForExpression(TypeAnalysis.java:803)
        //     at com.strobel.decompiler.ast.TypeAnalysis.runInference(TypeAnalysis.java:672)
        //     at com.strobel.decompiler.ast.TypeAnalysis.runInference(TypeAnalysis.java:655)
        //     at com.strobel.decompiler.ast.TypeAnalysis.runInference(TypeAnalysis.java:365)
        //     at com.strobel.decompiler.ast.TypeAnalysis.run(TypeAnalysis.java:96)
        //     at com.strobel.decompiler.ast.AstOptimizer.optimize(AstOptimizer.java:109)
        //     at com.strobel.decompiler.ast.AstOptimizer.optimize(AstOptimizer.java:42)
        //     at com.strobel.decompiler.languages.java.ast.AstMethodBodyBuilder.createMethodBody(AstMethodBodyBuilder.java:214)
        //     at com.strobel.decompiler.languages.java.ast.AstMethodBodyBuilder.createMethodBody(AstMethodBodyBuilder.java:99)
        //     at com.strobel.decompiler.languages.java.ast.AstBuilder.createMethodBody(AstBuilder.java:757)
        //     at com.strobel.decompiler.languages.java.ast.AstBuilder.createMethod(AstBuilder.java:655)
        //     at com.strobel.decompiler.languages.java.ast.AstBuilder.addTypeMembers(AstBuilder.java:532)
        //     at com.strobel.decompiler.languages.java.ast.AstBuilder.createTypeCore(AstBuilder.java:499)
        //     at com.strobel.decompiler.languages.java.ast.AstBuilder.createTypeNoCache(AstBuilder.java:141)
        //     at com.strobel.decompiler.languages.java.ast.AstBuilder.createType(AstBuilder.java:130)
        //     at com.strobel.decompiler.languages.java.ast.AstBuilder.addType(AstBuilder.java:105)
        //     at com.strobel.decompiler.languages.java.JavaLanguage.buildAst(JavaLanguage.java:71)
        //     at com.strobel.decompiler.languages.java.JavaLanguage.decompileType(JavaLanguage.java:59)
        //     at com.strobel.decompiler.DecompilerDriver.decompileType(DecompilerDriver.java:317)
        //     at com.strobel.decompiler.DecompilerDriver.decompileJar(DecompilerDriver.java:238)
        //     at com.strobel.decompiler.DecompilerDriver.main(DecompilerDriver.java:138)
        // 
        throw new IllegalStateException("An error occurred while decompiling this method.");
    }
    
    public void searchNetflix(final String p0, final BrowseAgentCallback p1) {
        // 
        // This method could not be decompiled.
        // 
        // Original Bytecode:
        // 
        //     0: aload_0        
        //     1: new             new            !!! ERROR
        //     4: dup            
        //     5: aload_0        
        //     6: aload_1        
        //     7: aload_2        
        //     8: invokespecial   invokespecial  !!! ERROR
        //    11: invokespecial   com/netflix/falkor/CachedModelProxy.launchTask:(Ljava/lang/Runnable;)V
        //    14: return         
        // 
        // The error that occurred was:
        // 
        // java.lang.IllegalArgumentException: Argument 'typeArguments' must not have any null elements.
        //     at com.strobel.core.VerifyArgument.noNullElementsAndNotEmpty(VerifyArgument.java:145)
        //     at com.strobel.assembler.metadata.CoreMetadataFactory$UnresolvedType.makeGenericType(CoreMetadataFactory.java:570)
        //     at com.strobel.assembler.metadata.CoreMetadataFactory.makeParameterizedType(CoreMetadataFactory.java:156)
        //     at com.strobel.assembler.metadata.signatures.Reifier.visitClassTypeSignature(Reifier.java:125)
        //     at com.strobel.assembler.metadata.signatures.ClassTypeSignature.accept(ClassTypeSignature.java:46)
        //     at com.strobel.assembler.metadata.MetadataParser.parseClassSignature(MetadataParser.java:394)
        //     at com.strobel.assembler.metadata.ClassFileReader.populateBaseTypes(ClassFileReader.java:665)
        //     at com.strobel.assembler.metadata.ClassFileReader.readClass(ClassFileReader.java:438)
        //     at com.strobel.assembler.metadata.ClassFileReader.readClass(ClassFileReader.java:366)
        //     at com.strobel.assembler.metadata.MetadataSystem.resolveType(MetadataSystem.java:124)
        //     at com.strobel.decompiler.NoRetryMetadataSystem.resolveType(DecompilerDriver.java:463)
        //     at com.strobel.assembler.metadata.MetadataSystem.resolveCore(MetadataSystem.java:76)
        //     at com.strobel.assembler.metadata.MetadataResolver.resolve(MetadataResolver.java:104)
        //     at com.strobel.assembler.metadata.CoreMetadataFactory$UnresolvedType.resolve(CoreMetadataFactory.java:589)
        //     at com.strobel.assembler.metadata.MetadataResolver.resolve(MetadataResolver.java:128)
        //     at com.strobel.assembler.metadata.CoreMetadataFactory$UnresolvedType.resolve(CoreMetadataFactory.java:599)
        //     at com.strobel.assembler.metadata.MethodReference.resolve(MethodReference.java:172)
        //     at com.strobel.decompiler.ast.TypeAnalysis.inferCall(TypeAnalysis.java:2428)
        //     at com.strobel.decompiler.ast.TypeAnalysis.doInferTypeForExpression(TypeAnalysis.java:1029)
        //     at com.strobel.decompiler.ast.TypeAnalysis.inferTypeForExpression(TypeAnalysis.java:803)
        //     at com.strobel.decompiler.ast.TypeAnalysis.runInference(TypeAnalysis.java:672)
        //     at com.strobel.decompiler.ast.TypeAnalysis.runInference(TypeAnalysis.java:655)
        //     at com.strobel.decompiler.ast.TypeAnalysis.runInference(TypeAnalysis.java:365)
        //     at com.strobel.decompiler.ast.TypeAnalysis.run(TypeAnalysis.java:96)
        //     at com.strobel.decompiler.ast.AstOptimizer.optimize(AstOptimizer.java:109)
        //     at com.strobel.decompiler.ast.AstOptimizer.optimize(AstOptimizer.java:42)
        //     at com.strobel.decompiler.languages.java.ast.AstMethodBodyBuilder.createMethodBody(AstMethodBodyBuilder.java:214)
        //     at com.strobel.decompiler.languages.java.ast.AstMethodBodyBuilder.createMethodBody(AstMethodBodyBuilder.java:99)
        //     at com.strobel.decompiler.languages.java.ast.AstBuilder.createMethodBody(AstBuilder.java:757)
        //     at com.strobel.decompiler.languages.java.ast.AstBuilder.createMethod(AstBuilder.java:655)
        //     at com.strobel.decompiler.languages.java.ast.AstBuilder.addTypeMembers(AstBuilder.java:532)
        //     at com.strobel.decompiler.languages.java.ast.AstBuilder.createTypeCore(AstBuilder.java:499)
        //     at com.strobel.decompiler.languages.java.ast.AstBuilder.createTypeNoCache(AstBuilder.java:141)
        //     at com.strobel.decompiler.languages.java.ast.AstBuilder.createType(AstBuilder.java:130)
        //     at com.strobel.decompiler.languages.java.ast.AstBuilder.addType(AstBuilder.java:105)
        //     at com.strobel.decompiler.languages.java.JavaLanguage.buildAst(JavaLanguage.java:71)
        //     at com.strobel.decompiler.languages.java.JavaLanguage.decompileType(JavaLanguage.java:59)
        //     at com.strobel.decompiler.DecompilerDriver.decompileType(DecompilerDriver.java:317)
        //     at com.strobel.decompiler.DecompilerDriver.decompileJar(DecompilerDriver.java:238)
        //     at com.strobel.decompiler.DecompilerDriver.main(DecompilerDriver.java:138)
        // 
        throw new IllegalStateException("An error occurred while decompiling this method.");
    }
    
    public void setVideoRating(final String p0, final VideoType p1, final int p2, final int p3, final BrowseAgentCallback p4) {
        // 
        // This method could not be decompiled.
        // 
        // Original Bytecode:
        // 
        //     0: aload_0        
        //     1: new             new            !!! ERROR
        //     4: dup            
        //     5: aload_0        
        //     6: aload_1        
        //     7: aload_2        
        //     8: iload_3        
        //     9: iload           4
        //    11: aload           5
        //    13: invokespecial   invokespecial  !!! ERROR
        //    16: invokespecial   com/netflix/falkor/CachedModelProxy.launchTask:(Ljava/lang/Runnable;)V
        //    19: return         
        // 
        // The error that occurred was:
        // 
        // java.lang.IllegalArgumentException: Argument 'typeArguments' must not have any null elements.
        //     at com.strobel.core.VerifyArgument.noNullElementsAndNotEmpty(VerifyArgument.java:145)
        //     at com.strobel.assembler.metadata.CoreMetadataFactory$UnresolvedType.makeGenericType(CoreMetadataFactory.java:570)
        //     at com.strobel.assembler.metadata.CoreMetadataFactory.makeParameterizedType(CoreMetadataFactory.java:156)
        //     at com.strobel.assembler.metadata.signatures.Reifier.visitClassTypeSignature(Reifier.java:125)
        //     at com.strobel.assembler.metadata.signatures.ClassTypeSignature.accept(ClassTypeSignature.java:46)
        //     at com.strobel.assembler.metadata.MetadataParser.parseClassSignature(MetadataParser.java:394)
        //     at com.strobel.assembler.metadata.ClassFileReader.populateBaseTypes(ClassFileReader.java:665)
        //     at com.strobel.assembler.metadata.ClassFileReader.readClass(ClassFileReader.java:438)
        //     at com.strobel.assembler.metadata.ClassFileReader.readClass(ClassFileReader.java:366)
        //     at com.strobel.assembler.metadata.MetadataSystem.resolveType(MetadataSystem.java:124)
        //     at com.strobel.decompiler.NoRetryMetadataSystem.resolveType(DecompilerDriver.java:463)
        //     at com.strobel.assembler.metadata.MetadataSystem.resolveCore(MetadataSystem.java:76)
        //     at com.strobel.assembler.metadata.MetadataResolver.resolve(MetadataResolver.java:104)
        //     at com.strobel.assembler.metadata.CoreMetadataFactory$UnresolvedType.resolve(CoreMetadataFactory.java:589)
        //     at com.strobel.assembler.metadata.MetadataResolver.resolve(MetadataResolver.java:128)
        //     at com.strobel.assembler.metadata.CoreMetadataFactory$UnresolvedType.resolve(CoreMetadataFactory.java:599)
        //     at com.strobel.assembler.metadata.MethodReference.resolve(MethodReference.java:172)
        //     at com.strobel.decompiler.ast.TypeAnalysis.inferCall(TypeAnalysis.java:2428)
        //     at com.strobel.decompiler.ast.TypeAnalysis.doInferTypeForExpression(TypeAnalysis.java:1029)
        //     at com.strobel.decompiler.ast.TypeAnalysis.inferTypeForExpression(TypeAnalysis.java:803)
        //     at com.strobel.decompiler.ast.TypeAnalysis.runInference(TypeAnalysis.java:672)
        //     at com.strobel.decompiler.ast.TypeAnalysis.runInference(TypeAnalysis.java:655)
        //     at com.strobel.decompiler.ast.TypeAnalysis.runInference(TypeAnalysis.java:365)
        //     at com.strobel.decompiler.ast.TypeAnalysis.run(TypeAnalysis.java:96)
        //     at com.strobel.decompiler.ast.AstOptimizer.optimize(AstOptimizer.java:109)
        //     at com.strobel.decompiler.ast.AstOptimizer.optimize(AstOptimizer.java:42)
        //     at com.strobel.decompiler.languages.java.ast.AstMethodBodyBuilder.createMethodBody(AstMethodBodyBuilder.java:214)
        //     at com.strobel.decompiler.languages.java.ast.AstMethodBodyBuilder.createMethodBody(AstMethodBodyBuilder.java:99)
        //     at com.strobel.decompiler.languages.java.ast.AstBuilder.createMethodBody(AstBuilder.java:757)
        //     at com.strobel.decompiler.languages.java.ast.AstBuilder.createMethod(AstBuilder.java:655)
        //     at com.strobel.decompiler.languages.java.ast.AstBuilder.addTypeMembers(AstBuilder.java:532)
        //     at com.strobel.decompiler.languages.java.ast.AstBuilder.createTypeCore(AstBuilder.java:499)
        //     at com.strobel.decompiler.languages.java.ast.AstBuilder.createTypeNoCache(AstBuilder.java:141)
        //     at com.strobel.decompiler.languages.java.ast.AstBuilder.createType(AstBuilder.java:130)
        //     at com.strobel.decompiler.languages.java.ast.AstBuilder.addType(AstBuilder.java:105)
        //     at com.strobel.decompiler.languages.java.JavaLanguage.buildAst(JavaLanguage.java:71)
        //     at com.strobel.decompiler.languages.java.JavaLanguage.decompileType(JavaLanguage.java:59)
        //     at com.strobel.decompiler.DecompilerDriver.decompileType(DecompilerDriver.java:317)
        //     at com.strobel.decompiler.DecompilerDriver.decompileJar(DecompilerDriver.java:238)
        //     at com.strobel.decompiler.DecompilerDriver.main(DecompilerDriver.java:138)
        // 
        throw new IllegalStateException("An error occurred while decompiling this method.");
    }
    
    @Override
    public String toString() {
        synchronized (this) {
            return "CachedModelProxy cache: " + this.root.toString();
        }
    }
    
    public void updateBookmarkPosition(final Asset asset) {
        if (asset == null) {
            Log.w("CachedModelProxy", "Can't update bookmark position - asset is null");
        }
        else {
            final int playbackBookmark = asset.getPlaybackBookmark();
            if (Falkor.ENABLE_VERBOSE_LOGGING) {
                Log.v("CachedModelProxy", "Updating video positions for asset: " + asset.getTitle() + ", playable bookmark: " + playbackBookmark);
            }
            if (playbackBookmark <= 0) {
                if (Log.isLoggable()) {
                    Log.w("CachedModelProxy", "updateBookmarkPosition - bookmarkPos <= 0");
                }
            }
            else {
                if (StringUtils.isEmpty(asset.getPlayableId())) {
                    Log.w("CachedModelProxy", String.format("asset with null playableId, asset:%s", asset));
                    return;
                }
                String s;
                if (asset.isEpisode()) {
                    s = VideoType.EPISODE.getValue();
                }
                else {
                    s = VideoType.MOVIE.getValue();
                }
                final FalkorVideo falkorVideo = (FalkorVideo)this.getVideo(PQL.create(s, asset.getPlayableId(), "bookmark"));
                if (falkorVideo == null) {
                    if (Log.isLoggable()) {
                        Log.w("CachedModelProxy", "updateBookmarkPosition - video is null, id: " + asset.getPlayableId());
                    }
                }
                else {
                    final Video$Bookmark bookmark = falkorVideo.getBookmark();
                    if (bookmark != null) {
                        bookmark.setBookmarkPosition(playbackBookmark);
                        bookmark.setLastModified(System.currentTimeMillis());
                        return;
                    }
                    if (Log.isLoggable()) {
                        Log.w("CachedModelProxy", "updateBookmarkPosition - bookmark is null, video id: " + asset.getPlayableId());
                    }
                }
            }
        }
    }
}
